Workbook

Sheet 📊 Dashboard
A1: 📊 TABLEAU DE BORD — Portefeuille Brevets UM6P | S1: Tous | T1: Toutes | U1: Toutes | V1: Agriculture, biostimulants & protection végétale | W1: {=SUMPRODUCT(('📋 Inventaire Complet'!$C$3:$C$517=$V1)*(($B$5="Tous")+('📋 Inventaire Complet'!$B$3:$B$517=$B$5)>0)*(($E$5="Toutes")+(LEFT('📋 Inventaire Complet'!$J$3:$J$517,4)=$E$5&"")>0)*(($H$5="Toutes")+('📋 Inventaire Complet'!$F$3:$F$517=$H$5)>0)*(LEN('📋 Inventaire Complet'!$D$3:$D$517)>0)*(($K$5="Tous")+(ISNUMBER(SEARCH($K$5,'📋 Inventaire Complet'!$L$3:$L$517)))>0))} -> 0 | X1: =W1+ROW()/10000 -> 0.0001 | Y1: LAKSSIR, BOUZIDA, BENNANI | Z1: {=IF(Y1="",0,SUMPRODUCT(('📋 Inventaire Complet'!$E$3:$E$517=Y1)*((COUNTIF($B$6:$B$10,TRUE)=0)+ISNUMBER(IFERROR(MATCH('📋 Inventaire Complet'!$B$3:$B$517,IF($B$6:$B$10,$A$6:$A$10),0),""))>0)*((COUNTIF($D$6:$D$22,TRUE)=0)+ISNUMBER(IFERROR(MATCH(LEFT('📋 Inventaire Complet'!$J$3:$J$517,4),IF($D$6:$D$22,$C$6:$C$22&""),0),""))>0)*((COUNTIF($F$6:$F$20,TRUE)=0)+(ISNUMBER(IFERROR(MATCH('📋 Inventaire Complet'!$F$3:$F$517,IF($F$6:$F$19,$E$6:$E$19),0),""))+($F$20*ISNUMBER(MATCH('📋 Inventaire Complet'!$F$3:$F$517,{"D4R";"CEPH";"ISTI";"COLCOM";"HTMR"},0))))>0)*((COUNTIF($H$6:$H$10,TRUE)=0)+(($H$6*ISNUMBER(SEARCH($G$6,'📋 Inventaire Complet'!$L$3:$L$517)))+($H$7*ISNUMBER(SEARCH($G$7,'📋 Inventaire Complet'!$L$3:$L$517)))+($H$8*ISNUMBER(SEARCH($G$8,'📋 Inventaire Complet'!$L$3:$L$517)))+($H$9*ISNUMBER(SEARCH($G$9,'📋 Inventaire Complet'!$L$3:$L$517)))+($H$10*ISNUMBER(SEARCH($G$10,'📋 Inventaire Complet'!$L$3:$L$517))))>0)))} -> 1 | AA1: =IF(Y1="",0,Z1+ROW()/10000) -> 1.0001
S2: Environmental Tech & Digital Mining | T2: 2010 | U2: MAScIR | V2: Biotechnologies, diagnostic & molécules bioactives | W2: {=SUMPRODUCT(('📋 Inventaire Complet'!$C$3:$C$517=$V2)*(($B$5="Tous")+('📋 Inventaire Complet'!$B$3:$B$517=$B$5)>0)*(($E$5="Toutes")+(LEFT('📋 Inventaire Complet'!$J$3:$J$517,4)=$E$5&"")>0)*(($H$5="Toutes")+('📋 Inventaire Complet'!$F$3:$F$517=$H$5)>0)*(LEN('📋 Inventaire Complet'!$D$3:$D$517)>0)*(($K$5="Tous")+(ISNUMBER(SEARCH($K$5,'📋 Inventaire Complet'!$L$3:$L$517)))>0))} -> 0 | X2: =W2+ROW()/10000 -> 0.0002 | Y2: AMAR OUMKELTOUM; ZENNAYI YAHYA; BOURJA OMAR; BOURZEIX FRANCOIS | Z2: {=IF(Y2="",0,SUMPRODUCT(('📋 Inventaire Complet'!$E$3:$E$517=Y2)*((COUNTIF($B$6:$B$10,TRUE)=0)+ISNUMBER(IFERROR(MATCH('📋 Inventaire Complet'!$B$3:$B$517,IF($B$6:$B$10,$A$6:$A$10),0),""))>0)*((COUNTIF($D$6:$D$22,TRUE)=0)+ISNUMBER(IFERROR(MATCH(LEFT('📋 Inventaire Complet'!$J$3:$J$517,4),IF($D$6:$D$22,$C$6:$C$22&""),0),""))>0)*((COUNTIF($F$6:$F$20,TRUE)=0)+(ISNUMBER(IFERROR(MATCH('📋 Inventaire Complet'!$F$3:$F$517,IF($F$6:$F$19,$E$6:$E$19),0),""))+($F$20*ISNUMBER(MATCH('📋 Inventaire Complet'!$F$3:$F$517,{"D4R";"CEPH";"ISTI";"COLCOM";"HTMR"},0))))>0)*((COUNTIF($H$6:$H$10,TRUE)=0)+(($H$6*ISNUMBER(SEARCH($G$6,'📋 Inventaire Complet'!$L$3:$L$517)))+($H$7*ISNUMBER(SEARCH($G$7,'📋 Inventaire Complet'!$L$3:$L$517)))+($H$8*ISNUMBER(SEARCH($G$8,'📋 Inventaire Complet'!$L$3:$L$517)))+($H$9*ISNUMBER(SEARCH($G$9,'📋 Inventaire Complet'!$L$3:$L$517)))+($H$10*ISNUMBER(SEARCH($G$10,'📋 Inventaire Complet'!$L$3:$L$517))))>0)))} -> 1 | AA2: =IF(Y2="",0,Z2+ROW()/10000) -> 1.0002
S3: Mineral Processing & Strategic Synthesis | T3: 2011 | U3: OCP | CERPHOS (historique) | V3: Capteurs, spectroscopie & micro-ondes | W3: {=SUMPRODUCT(('📋 Inventaire Complet'!$C$3:$C$517=$V3)*(($B$5="Tous")+('📋 Inventaire Complet'!$B$3:$B$517=$B$5)>0)*(($E$5="Toutes")+(LEFT('📋 Inventaire Complet'!$J$3:$J$517,4)=$E$5&"")>0)*(($H$5="Toutes")+('📋 Inventaire Complet'!$F$3:$F$517=$H$5)>0)*(LEN('📋 Inventaire Complet'!$D$3:$D$517)>0)*(($K$5="Tous")+(ISNUMBER(SEARCH($K$5,'📋 Inventaire Complet'!$L$3:$L$517)))>0))} -> 0 | X3: =W3+ROW()/10000 -> 0.0003 | Y3: Yahya ZENNAYI; Hamd AIT ABDELALI; Soukayna BENAISSA; Jihad BOURASSI | Z3: {=IF(Y3="",0,SUMPRODUCT(('📋 Inventaire Complet'!$E$3:$E$517=Y3)*((COUNTIF($B$6:$B$10,TRUE)=0)+ISNUMBER(IFERROR(MATCH('📋 Inventaire Complet'!$B$3:$B$517,IF($B$6:$B$10,$A$6:$A$10),0),""))>0)*((COUNTIF($D$6:$D$22,TRUE)=0)+ISNUMBER(IFERROR(MATCH(LEFT('📋 Inventaire Complet'!$J$3:$J$517,4),IF($D$6:$D$22,$C$6:$C$22&""),0),""))>0)*((COUNTIF($F$6:$F$20,TRUE)=0)+(ISNUMBER(IFERROR(MATCH('📋 Inventaire Complet'!$F$3:$F$517,IF($F$6:$F$19,$E$6:$E$19),0),""))+($F$20*ISNUMBER(MATCH('📋 Inventaire Complet'!$F$3:$F$517,{"D4R";"CEPH";"ISTI";"COLCOM";"HTMR"},0))))>0)*((COUNTIF($H$6:$H$10,TRUE)=0)+(($H$6*ISNUMBER(SEARCH($G$6,'📋 Inventaire Complet'!$L$3:$L$517)))+($H$7*ISNUMBER(SEARCH($G$7,'📋 Inventaire Complet'!$L$3:$L$517)))+($H$8*ISNUMBER(SEARCH($G$8,'📋 Inventaire Complet'!$L$3:$L$517)))+($H$9*ISNUMBER(SEARCH($G$9,'📋 Inventaire Complet'!$L$3:$L$517)))+($H$10*ISNUMBER(SEARCH($G$10,'📋 Inventaire Complet'!$L$3:$L$517))))>0)))} -> 1 | AA3: =IF(Y3="",0,Z3+ROW()/10000) -> 1.0003
A4: 🔍 FILTRES INTERACTIFS — Cocher pour filtrer (multi-sélection). Aucune case cochée dans un filtre = toutes les valeurs. | S4: Circular Chemistry & Waste Valorization | T4: 2012 | U4: MSN | V4: Matériaux composites, polymères & revêtements | W4: {=SUMPRODUCT(('📋 Inventaire Complet'!$C$3:$C$517=$V4)*(($B$5="Tous")+('📋 Inventaire Complet'!$B$3:$B$517=$B$5)>0)*(($E$5="Toutes")+(LEFT('📋 Inventaire Complet'!$J$3:$J$517,4)=$E$5&"")>0)*(($H$5="Toutes")+('📋 Inventaire Complet'!$F$3:$F$517=$H$5)>0)*(LEN('📋 Inventaire Complet'!$D$3:$D$517)>0)*(($K$5="Tous")+(ISNUMBER(SEARCH($K$5,'📋 Inventaire Complet'!$L$3:$L$517)))>0))} -> 0 | X4: =W4+ROW()/10000 -> 0.0004 | Y4: BALOUIRI MOUNYR; EL HADI HICHAM; MOUMEN ABDELADIM | Z4: {=IF(Y4="",0,SUMPRODUCT(('📋 Inventaire Complet'!$E$3:$E$517=Y4)*((COUNTIF($B$6:$B$10,TRUE)=0)+ISNUMBER(IFERROR(MATCH('📋 Inventaire Complet'!$B$3:$B$517,IF($B$6:$B$10,$A$6:$A$10),0),""))>0)*((COUNTIF($D$6:$D$22,TRUE)=0)+ISNUMBER(IFERROR(MATCH(LEFT('📋 Inventaire Complet'!$J$3:$J$517,4),IF($D$6:$D$22,$C$6:$C$22&""),0),""))>0)*((COUNTIF($F$6:$F$20,TRUE)=0)+(ISNUMBER(IFERROR(MATCH('📋 Inventaire Complet'!$F$3:$F$517,IF($F$6:$F$19,$E$6:$E$19),0),""))+($F$20*ISNUMBER(MATCH('📋 Inventaire Complet'!$F$3:$F$517,{"D4R";"CEPH";"ISTI";"COLCOM";"HTMR"},0))))>0)*((COUNTIF($H$6:$H$10,TRUE)=0)+(($H$6*ISNUMBER(SEARCH($G$6,'📋 Inventaire Complet'!$L$3:$L$517)))+($H$7*ISNUMBER(SEARCH($G$7,'📋 Inventaire Complet'!$L$3:$L$517)))+($H$8*ISNUMBER(SEARCH($G$8,'📋 Inventaire Complet'!$L$3:$L$517)))+($H$9*ISNUMBER(SEARCH($G$9,'📋 Inventaire Complet'!$L$3:$L$517)))+($H$10*ISNUMBER(SEARCH($G$10,'📋 Inventaire Complet'!$L$3:$L$517))))>0)))} -> 1 | AA4: =IF(Y4="",0,Z4+ROW()/10000) -> 1.0004
A5: Thématique | C5: Année | E5: Hub / Laboratoire | G5: Statut | J5: État | K5: Sélection | S5: Green Agriculture & Biotechnology | T5: 2013 | U5: CERPHOS (historique) | V5: Nanomatériaux, céramiques & matériaux fonctionnels | W5: {=SUMPRODUCT(('📋 Inventaire Complet'!$C$3:$C$517=$V5)*(($B$5="Tous")+('📋 Inventaire Complet'!$B$3:$B$517=$B$5)>0)*(($E$5="Toutes")+(LEFT('📋 Inventaire Complet'!$J$3:$J$517,4)=$E$5&"")>0)*(($H$5="Toutes")+('📋 Inventaire Complet'!$F$3:$F$517=$H$5)>0)*(LEN('📋 Inventaire Complet'!$D$3:$D$517)>0)*(($K$5="Tous")+(ISNUMBER(SEARCH($K$5,'📋 Inventaire Complet'!$L$3:$L$517)))>0))} -> 0 | X5: =W5+ROW()/10000 -> 0.0005 | Y5: EL KAMOUNY Khadija; Fatima Ezzahra EL KAMOUNY | Z5: {=IF(Y5="",0,SUMPRODUCT(('📋 Inventaire Complet'!$E$3:$E$517=Y5)*((COUNTIF($B$6:$B$10,TRUE)=0)+ISNUMBER(IFERROR(MATCH('📋 Inventaire Complet'!$B$3:$B$517,IF($B$6:$B$10,$A$6:$A$10),0),""))>0)*((COUNTIF($D$6:$D$22,TRUE)=0)+ISNUMBER(IFERROR(MATCH(LEFT('📋 Inventaire Complet'!$J$3:$J$517,4),IF($D$6:$D$22,$C$6:$C$22&""),0),""))>0)*((COUNTIF($F$6:$F$20,TRUE)=0)+(ISNUMBER(IFERROR(MATCH('📋 Inventaire Complet'!$F$3:$F$517,IF($F$6:$F$19,$E$6:$E$19),0),""))+($F$20*ISNUMBER(MATCH('📋 Inventaire Complet'!$F$3:$F$517,{"D4R";"CEPH";"ISTI";"COLCOM";"HTMR"},0))))>0)*((COUNTIF($H$6:$H$10,TRUE)=0)+(($H$6*ISNUMBER(SEARCH($G$6,'📋 Inventaire Complet'!$L$3:$L$517)))+($H$7*ISNUMBER(SEARCH($G$7,'📋 Inventaire Complet'!$L$3:$L$517)))+($H$8*ISNUMBER(SEARCH($G$8,'📋 Inventaire Complet'!$L$3:$L$517)))+($H$9*ISNUMBER(SEARCH($G$9,'📋 Inventaire Complet'!$L$3:$L$517)))+($H$10*ISNUMBER(SEARCH($G$10,'📋 Inventaire Complet'!$L$3:$L$517))))>0)))} -> 1 | AA5: =IF(Y5="",0,Z5+ROW()/10000) -> 1.0005
A6: Environmental Tech & Digital Mining | B6: FALSE | C6: 2010 | D6: FALSE | E6: MAScIR | F6: FALSE | G6: Maintenu | H6: FALSE | S6: Sustainable Energy Storage & Management | T6: 2014 | U6: ACER CoE | V6: Procédés phosphates, phosphogypse & chimie industrielle | W6: {=SUMPRODUCT(('📋 Inventaire Complet'!$C$3:$C$517=$V6)*(($B$5="Tous")+('📋 Inventaire Complet'!$B$3:$B$517=$B$5)>0)*(($E$5="Toutes")+(LEFT('📋 Inventaire Complet'!$J$3:$J$517,4)=$E$5&"")>0)*(($H$5="Toutes")+('📋 Inventaire Complet'!$F$3:$F$517=$H$5)>0)*(LEN('📋 Inventaire Complet'!$D$3:$D$517)>0)*(($K$5="Tous")+(ISNUMBER(SEARCH($K$5,'📋 Inventaire Complet'!$L$3:$L$517)))>0))} -> 0 | X6: =W6+ROW()/10000 -> 0.0006 | Y6: EL BOURKADI KHADIJA; MERGHOUB NAWAL; QAISS ABOU EL KACEM; BOUHFID RACHID | Z6: {=IF(Y6="",0,SUMPRODUCT(('📋 Inventaire Complet'!$E$3:$E$517=Y6)*((COUNTIF($B$6:$B$10,TRUE)=0)+ISNUMBER(IFERROR(MATCH('📋 Inventaire Complet'!$B$3:$B$517,IF($B$6:$B$10,$A$6:$A$10),0),""))>0)*((COUNTIF($D$6:$D$22,TRUE)=0)+ISNUMBER(IFERROR(MATCH(LEFT('📋 Inventaire Complet'!$J$3:$J$517,4),IF($D$6:$D$22,$C$6:$C$22&""),0),""))>0)*((COUNTIF($F$6:$F$20,TRUE)=0)+(ISNUMBER(IFERROR(MATCH('📋 Inventaire Complet'!$F$3:$F$517,IF($F$6:$F$19,$E$6:$E$19),0),""))+($F$20*ISNUMBER(MATCH('📋 Inventaire Complet'!$F$3:$F$517,{"D4R";"CEPH";"ISTI";"COLCOM";"HTMR"},0))))>0)*((COUNTIF($H$6:$H$10,TRUE)=0)+(($H$6*ISNUMBER(SEARCH($G$6,'📋 Inventaire Complet'!$L$3:$L$517)))+($H$7*ISNUMBER(SEARCH($G$7,'📋 Inventaire Complet'!$L$3:$L$517)))+($H$8*ISNUMBER(SEARCH($G$8,'📋 Inventaire Complet'!$L$3:$L$517)))+($H$9*ISNUMBER(SEARCH($G$9,'📋 Inventaire Complet'!$L$3:$L$517)))+($H$10*ISNUMBER(SEARCH($G$10,'📋 Inventaire Complet'!$L$3:$L$517))))>0)))} -> 1 | AA6: =IF(Y6="",0,Z6+ROW()/10000) -> 1.0006
A7: Mineral Processing & Strategic Synthesis | B7: FALSE | C7: 2011 | D7: FALSE | E7: OCP / CERPHOS (historique) | F7: FALSE | G7: Délivré | H7: FALSE | T7: 2015 | U7: CBS | V7: Traitement de l’eau, effluents & dépollution | W7: {=SUMPRODUCT(('📋 Inventaire Complet'!$C$3:$C$517=$V7)*(($B$5="Tous")+('📋 Inventaire Complet'!$B$3:$B$517=$B$5)>0)*(($E$5="Toutes")+(LEFT('📋 Inventaire Complet'!$J$3:$J$517,4)=$E$5&"")>0)*(($H$5="Toutes")+('📋 Inventaire Complet'!$F$3:$F$517=$H$5)>0)*(LEN('📋 Inventaire Complet'!$D$3:$D$517)>0)*(($K$5="Tous")+(ISNUMBER(SEARCH($K$5,'📋 Inventaire Complet'!$L$3:$L$517)))>0))} -> 0 | X7: =W7+ROW()/10000 -> 0.0007 | Y7: Hassan AIT BENHASSOU, Abdeladim MOUMEN, Hicham EL HADI, El Mehdi BENTALEB | Z7: {=IF(Y7="",0,SUMPRODUCT(('📋 Inventaire Complet'!$E$3:$E$517=Y7)*((COUNTIF($B$6:$B$10,TRUE)=0)+ISNUMBER(IFERROR(MATCH('📋 Inventaire Complet'!$B$3:$B$517,IF($B$6:$B$10,$A$6:$A$10),0),""))>0)*((COUNTIF($D$6:$D$22,TRUE)=0)+ISNUMBER(IFERROR(MATCH(LEFT('📋 Inventaire Complet'!$J$3:$J$517,4),IF($D$6:$D$22,$C$6:$C$22&""),0),""))>0)*((COUNTIF($F$6:$F$20,TRUE)=0)+(ISNUMBER(IFERROR(MATCH('📋 Inventaire Complet'!$F$3:$F$517,IF($F$6:$F$19,$E$6:$E$19),0),""))+($F$20*ISNUMBER(MATCH('📋 Inventaire Complet'!$F$3:$F$517,{"D4R";"CEPH";"ISTI";"COLCOM";"HTMR"},0))))>0)*((COUNTIF($H$6:$H$10,TRUE)=0)+(($H$6*ISNUMBER(SEARCH($G$6,'📋 Inventaire Complet'!$L$3:$L$517)))+($H$7*ISNUMBER(SEARCH($G$7,'📋 Inventaire Complet'!$L$3:$L$517)))+($H$8*ISNUMBER(SEARCH($G$8,'📋 Inventaire Complet'!$L$3:$L$517)))+($H$9*ISNUMBER(SEARCH($G$9,'📋 Inventaire Complet'!$L$3:$L$517)))+($H$10*ISNUMBER(SEARCH($G$10,'📋 Inventaire Complet'!$L$3:$L$517))))>0)))} -> 1 | AA7: =IF(Y7="",0,Z7+ROW()/10000) -> 1.0007
A8: Circular Chemistry & Waste Valorization | B8: FALSE | C8: 2012 | D8: FALSE | E8: MSN | F8: FALSE | G8: PCT | H8: FALSE | Y8: Ressami, Ait Benhassou, Lakssir | Z8: {=IF(Y8="",0,SUMPRODUCT(('📋 Inventaire Complet'!$E$3:$E$517=Y8)*((COUNTIF($B$6:$B$10,TRUE)=0)+ISNUMBER(IFERROR(MATCH('📋 Inventaire Complet'!$B$3:$B$517,IF($B$6:$B$10,$A$6:$A$10),0),""))>0)*((COUNTIF($D$6:$D$22,TRUE)=0)+ISNUMBER(IFERROR(MATCH(LEFT('📋 Inventaire Complet'!$J$3:$J$517,4),IF($D$6:$D$22,$C$6:$C$22&""),0),""))>0)*((COUNTIF($F$6:$F$20,TRUE)=0)+(ISNUMBER(IFERROR(MATCH('📋 Inventaire Complet'!$F$3:$F$517,IF($F$6:$F$19,$E$6:$E$19),0),""))+($F$20*ISNUMBER(MATCH('📋 Inventaire Complet'!$F$3:$F$517,{"D4R";"CEPH";"ISTI";"COLCOM";"HTMR"},0))))>0)*((COUNTIF($H$6:$H$10,TRUE)=0)+(($H$6*ISNUMBER(SEARCH($G$6,'📋 Inventaire Complet'!$L$3:$L$517)))+($H$7*ISNUMBER(SEARCH($G$7,'📋 Inventaire Complet'!$L$3:$L$517)))+($H$8*ISNUMBER(SEARCH($G$8,'📋 Inventaire Complet'!$L$3:$L$517)))+($H$9*ISNUMBER(SEARCH($G$9,'📋 Inventaire Complet'!$L$3:$L$517)))+($H$10*ISNUMBER(SEARCH($G$10,'📋 Inventaire Complet'!$L$3:$L$517))))>0)))} -> 1 | AA8: =IF(Y8="",0,Z8+ROW()/10000) -> 1.0008
A9: Green Agriculture & Biotechnology | B9: FALSE | C9: 2013 | D9: FALSE | E9: CERPHOS (historique) | F9: FALSE | G9: OMPIC | H9: FALSE | Y9: BOUHFID RACHID QAISS ABOU EL KACEM MERGHOUB NAWAL Mekhzoum Mohamed El Mehdi EL BOURAKADI KHADIJA | Z9: {=IF(Y9="",0,SUMPRODUCT(('📋 Inventaire Complet'!$E$3:$E$517=Y9)*((COUNTIF($B$6:$B$10,TRUE)=0)+ISNUMBER(IFERROR(MATCH('📋 Inventaire Complet'!$B$3:$B$517,IF($B$6:$B$10,$A$6:$A$10),0),""))>0)*((COUNTIF($D$6:$D$22,TRUE)=0)+ISNUMBER(IFERROR(MATCH(LEFT('📋 Inventaire Complet'!$J$3:$J$517,4),IF($D$6:$D$22,$C$6:$C$22&""),0),""))>0)*((COUNTIF($F$6:$F$20,TRUE)=0)+(ISNUMBER(IFERROR(MATCH('📋 Inventaire Complet'!$F$3:$F$517,IF($F$6:$F$19,$E$6:$E$19),0),""))+($F$20*ISNUMBER(MATCH('📋 Inventaire Complet'!$F$3:$F$517,{"D4R";"CEPH";"ISTI";"COLCOM";"HTMR"},0))))>0)*((COUNTIF($H$6:$H$10,TRUE)=0)+(($H$6*ISNUMBER(SEARCH($G$6,'📋 Inventaire Complet'!$L$3:$L$517)))+($H$7*ISNUMBER(SEARCH($G$7,'📋 Inventaire Complet'!$L$3:$L$517)))+($H$8*ISNUMBER(SEARCH($G$8,'📋 Inventaire Complet'!$L$3:$L$517)))+($H$9*ISNUMBER(SEARCH($G$9,'📋 Inventaire Complet'!$L$3:$L$517)))+($H$10*ISNUMBER(SEARCH($G$10,'📋 Inventaire Complet'!$L$3:$L$517))))>0)))} -> 2 | AA9: =IF(Y9="",0,Z9+ROW()/10000) -> 2.0009
A10: Sustainable Energy Storage & Management | B10: FALSE | C10: 2014 | D10: FALSE | E10: ACER CoE | F10: FALSE | G10: Abandonné | H10: FALSE | Y10: EL BOURKADI KHADIJA; ESSASSI EL MOKHTAR; QAISS ABOU EL KACEM; BOUHFID RACHID | Z10: {=IF(Y10="",0,SUMPRODUCT(('📋 Inventaire Complet'!$E$3:$E$517=Y10)*((COUNTIF($B$6:$B$10,TRUE)=0)+ISNUMBER(IFERROR(MATCH('📋 Inventaire Complet'!$B$3:$B$517,IF($B$6:$B$10,$A$6:$A$10),0),""))>0)*((COUNTIF($D$6:$D$22,TRUE)=0)+ISNUMBER(IFERROR(MATCH(LEFT('📋 Inventaire Complet'!$J$3:$J$517,4),IF($D$6:$D$22,$C$6:$C$22&""),0),""))>0)*((COUNTIF($F$6:$F$20,TRUE)=0)+(ISNUMBER(IFERROR(MATCH('📋 Inventaire Complet'!$F$3:$F$517,IF($F$6:$F$19,$E$6:$E$19),0),""))+($F$20*ISNUMBER(MATCH('📋 Inventaire Complet'!$F$3:$F$517,{"D4R";"CEPH";"ISTI";"COLCOM";"HTMR"},0))))>0)*((COUNTIF($H$6:$H$10,TRUE)=0)+(($H$6*ISNUMBER(SEARCH($G$6,'📋 Inventaire Complet'!$L$3:$L$517)))+($H$7*ISNUMBER(SEARCH($G$7,'📋 Inventaire Complet'!$L$3:$L$517)))+($H$8*ISNUMBER(SEARCH($G$8,'📋 Inventaire Complet'!$L$3:$L$517)))+($H$9*ISNUMBER(SEARCH($G$9,'📋 Inventaire Complet'!$L$3:$L$517)))+($H$10*ISNUMBER(SEARCH($G$10,'📋 Inventaire Complet'!$L$3:$L$517))))>0)))} -> 1 | AA10: =IF(Y10="",0,Z10+ROW()/10000) -> 1.001
C11: 2015 | D11: FALSE | E11: CBS | F11: FALSE | Y11: ISSAM, KASMI YASSINE | Z11: {=IF(Y11="",0,SUMPRODUCT(('📋 Inventaire Complet'!$E$3:$E$517=Y11)*((COUNTIF($B$6:$B$10,TRUE)=0)+ISNUMBER(IFERROR(MATCH('📋 Inventaire Complet'!$B$3:$B$517,IF($B$6:$B$10,$A$6:$A$10),0),""))>0)*((COUNTIF($D$6:$D$22,TRUE)=0)+ISNUMBER(IFERROR(MATCH(LEFT('📋 Inventaire Complet'!$J$3:$J$517,4),IF($D$6:$D$22,$C$6:$C$22&""),0),""))>0)*((COUNTIF($F$6:$F$20,TRUE)=0)+(ISNUMBER(IFERROR(MATCH('📋 Inventaire Complet'!$F$3:$F$517,IF($F$6:$F$19,$E$6:$E$19),0),""))+($F$20*ISNUMBER(MATCH('📋 Inventaire Complet'!$F$3:$F$517,{"D4R";"CEPH";"ISTI";"COLCOM";"HTMR"},0))))>0)*((COUNTIF($H$6:$H$10,TRUE)=0)+(($H$6*ISNUMBER(SEARCH($G$6,'📋 Inventaire Complet'!$L$3:$L$517)))+($H$7*ISNUMBER(SEARCH($G$7,'📋 Inventaire Complet'!$L$3:$L$517)))+($H$8*ISNUMBER(SEARCH($G$8,'📋 Inventaire Complet'!$L$3:$L$517)))+($H$9*ISNUMBER(SEARCH($G$9,'📋 Inventaire Complet'!$L$3:$L$517)))+($H$10*ISNUMBER(SEARCH($G$10,'📋 Inventaire Complet'!$L$3:$L$517))))>0)))} -> 1 | AA11: =IF(Y11="",0,Z11+ROW()/10000) -> 1.0011
C12: 2016 | D12: FALSE | E12: ASARI | F12: FALSE | Y12: Sbihi Younes; Qmichou Zineb; El Abbadi Najia; El Mzibri Mohammed; Sefrioui Hassan | Z12: {=IF(Y12="",0,SUMPRODUCT(('📋 Inventaire Complet'!$E$3:$E$517=Y12)*((COUNTIF($B$6:$B$10,TRUE)=0)+ISNUMBER(IFERROR(MATCH('📋 Inventaire Complet'!$B$3:$B$517,IF($B$6:$B$10,$A$6:$A$10),0),""))>0)*((COUNTIF($D$6:$D$22,TRUE)=0)+ISNUMBER(IFERROR(MATCH(LEFT('📋 Inventaire Complet'!$J$3:$J$517,4),IF($D$6:$D$22,$C$6:$C$22&""),0),""))>0)*((COUNTIF($F$6:$F$20,TRUE)=0)+(ISNUMBER(IFERROR(MATCH('📋 Inventaire Complet'!$F$3:$F$517,IF($F$6:$F$19,$E$6:$E$19),0),""))+($F$20*ISNUMBER(MATCH('📋 Inventaire Complet'!$F$3:$F$517,{"D4R";"CEPH";"ISTI";"COLCOM";"HTMR"},0))))>0)*((COUNTIF($H$6:$H$10,TRUE)=0)+(($H$6*ISNUMBER(SEARCH($G$6,'📋 Inventaire Complet'!$L$3:$L$517)))+($H$7*ISNUMBER(SEARCH($G$7,'📋 Inventaire Complet'!$L$3:$L$517)))+($H$8*ISNUMBER(SEARCH($G$8,'📋 Inventaire Complet'!$L$3:$L$517)))+($H$9*ISNUMBER(SEARCH($G$9,'📋 Inventaire Complet'!$L$3:$L$517)))+($H$10*ISNUMBER(SEARCH($G$10,'📋 Inventaire Complet'!$L$3:$L$517))))>0)))} -> 1 | AA12: =IF(Y12="",0,Z12+ROW()/10000) -> 1.0012
C13: 2017 | D13: FALSE | E13: GTI | F13: FALSE | Y13: AIT BENHASSOU, BENTALEB, SEFRIOUI | Z13: {=IF(Y13="",0,SUMPRODUCT(('📋 Inventaire Complet'!$E$3:$E$517=Y13)*((COUNTIF($B$6:$B$10,TRUE)=0)+ISNUMBER(IFERROR(MATCH('📋 Inventaire Complet'!$B$3:$B$517,IF($B$6:$B$10,$A$6:$A$10),0),""))>0)*((COUNTIF($D$6:$D$22,TRUE)=0)+ISNUMBER(IFERROR(MATCH(LEFT('📋 Inventaire Complet'!$J$3:$J$517,4),IF($D$6:$D$22,$C$6:$C$22&""),0),""))>0)*((COUNTIF($F$6:$F$20,TRUE)=0)+(ISNUMBER(IFERROR(MATCH('📋 Inventaire Complet'!$F$3:$F$517,IF($F$6:$F$19,$E$6:$E$19),0),""))+($F$20*ISNUMBER(MATCH('📋 Inventaire Complet'!$F$3:$F$517,{"D4R";"CEPH";"ISTI";"COLCOM";"HTMR"},0))))>0)*((COUNTIF($H$6:$H$10,TRUE)=0)+(($H$6*ISNUMBER(SEARCH($G$6,'📋 Inventaire Complet'!$L$3:$L$517)))+($H$7*ISNUMBER(SEARCH($G$7,'📋 Inventaire Complet'!$L$3:$L$517)))+($H$8*ISNUMBER(SEARCH($G$8,'📋 Inventaire Complet'!$L$3:$L$517)))+($H$9*ISNUMBER(SEARCH($G$9,'📋 Inventaire Complet'!$L$3:$L$517)))+($H$10*ISNUMBER(SEARCH($G$10,'📋 Inventaire Complet'!$L$3:$L$517))))>0)))} -> 4 | AA13: =IF(Y13="",0,Z13+ROW()/10000) -> 4.0013
C14: 2018 | D14: FALSE | E14: GSMI | F14: FALSE | Y14: WAHBY, MERGHOUB | Z14: {=IF(Y14="",0,SUMPRODUCT(('📋 Inventaire Complet'!$E$3:$E$517=Y14)*((COUNTIF($B$6:$B$10,TRUE)=0)+ISNUMBER(IFERROR(MATCH('📋 Inventaire Complet'!$B$3:$B$517,IF($B$6:$B$10,$A$6:$A$10),0),""))>0)*((COUNTIF($D$6:$D$22,TRUE)=0)+ISNUMBER(IFERROR(MATCH(LEFT('📋 Inventaire Complet'!$J$3:$J$517,4),IF($D$6:$D$22,$C$6:$C$22&""),0),""))>0)*((COUNTIF($F$6:$F$20,TRUE)=0)+(ISNUMBER(IFERROR(MATCH('📋 Inventaire Complet'!$F$3:$F$517,IF($F$6:$F$19,$E$6:$E$19),0),""))+($F$20*ISNUMBER(MATCH('📋 Inventaire Complet'!$F$3:$F$517,{"D4R";"CEPH";"ISTI";"COLCOM";"HTMR"},0))))>0)*((COUNTIF($H$6:$H$10,TRUE)=0)+(($H$6*ISNUMBER(SEARCH($G$6,'📋 Inventaire Complet'!$L$3:$L$517)))+($H$7*ISNUMBER(SEARCH($G$7,'📋 Inventaire Complet'!$L$3:$L$517)))+($H$8*ISNUMBER(SEARCH($G$8,'📋 Inventaire Complet'!$L$3:$L$517)))+($H$9*ISNUMBER(SEARCH($G$9,'📋 Inventaire Complet'!$L$3:$L$517)))+($H$10*ISNUMBER(SEARCH($G$10,'📋 Inventaire Complet'!$L$3:$L$517))))>0)))} -> 1 | AA14: =IF(Y14="",0,Z14+ROW()/10000) -> 1.0014
C15: 2019 | D15: FALSE | E15: LIMSET | F15: FALSE | Y15: DMITRY, SEKKAT | Z15: {=IF(Y15="",0,SUMPRODUCT(('📋 Inventaire Complet'!$E$3:$E$517=Y15)*((COUNTIF($B$6:$B$10,TRUE)=0)+ISNUMBER(IFERROR(MATCH('📋 Inventaire Complet'!$B$3:$B$517,IF($B$6:$B$10,$A$6:$A$10),0),""))>0)*((COUNTIF($D$6:$D$22,TRUE)=0)+ISNUMBER(IFERROR(MATCH(LEFT('📋 Inventaire Complet'!$J$3:$J$517,4),IF($D$6:$D$22,$C$6:$C$22&""),0),""))>0)*((COUNTIF($F$6:$F$20,TRUE)=0)+(ISNUMBER(IFERROR(MATCH('📋 Inventaire Complet'!$F$3:$F$517,IF($F$6:$F$19,$E$6:$E$19),0),""))+($F$20*ISNUMBER(MATCH('📋 Inventaire Complet'!$F$3:$F$517,{"D4R";"CEPH";"ISTI";"COLCOM";"HTMR"},0))))>0)*((COUNTIF($H$6:$H$10,TRUE)=0)+(($H$6*ISNUMBER(SEARCH($G$6,'📋 Inventaire Complet'!$L$3:$L$517)))+($H$7*ISNUMBER(SEARCH($G$7,'📋 Inventaire Complet'!$L$3:$L$517)))+($H$8*ISNUMBER(SEARCH($G$8,'📋 Inventaire Complet'!$L$3:$L$517)))+($H$9*ISNUMBER(SEARCH($G$9,'📋 Inventaire Complet'!$L$3:$L$517)))+($H$10*ISNUMBER(SEARCH($G$10,'📋 Inventaire Complet'!$L$3:$L$517))))>0)))} -> 1 | AA15: =IF(Y15="",0,Z15+ROW()/10000) -> 1.0015
C16: 2020 | D16: FALSE | E16: DICE | F16: FALSE | Y16: Shinji HAYASHI Zouheir SEKKAT Dmitry V. NESTERENKO | Z16: {=IF(Y16="",0,SUMPRODUCT(('📋 Inventaire Complet'!$E$3:$E$517=Y16)*((COUNTIF($B$6:$B$10,TRUE)=0)+ISNUMBER(IFERROR(MATCH('📋 Inventaire Complet'!$B$3:$B$517,IF($B$6:$B$10,$A$6:$A$10),0),""))>0)*((COUNTIF($D$6:$D$22,TRUE)=0)+ISNUMBER(IFERROR(MATCH(LEFT('📋 Inventaire Complet'!$J$3:$J$517,4),IF($D$6:$D$22,$C$6:$C$22&""),0),""))>0)*((COUNTIF($F$6:$F$20,TRUE)=0)+(ISNUMBER(IFERROR(MATCH('📋 Inventaire Complet'!$F$3:$F$517,IF($F$6:$F$19,$E$6:$E$19),0),""))+($F$20*ISNUMBER(MATCH('📋 Inventaire Complet'!$F$3:$F$517,{"D4R";"CEPH";"ISTI";"COLCOM";"HTMR"},0))))>0)*((COUNTIF($H$6:$H$10,TRUE)=0)+(($H$6*ISNUMBER(SEARCH($G$6,'📋 Inventaire Complet'!$L$3:$L$517)))+($H$7*ISNUMBER(SEARCH($G$7,'📋 Inventaire Complet'!$L$3:$L$517)))+($H$8*ISNUMBER(SEARCH($G$8,'📋 Inventaire Complet'!$L$3:$L$517)))+($H$9*ISNUMBER(SEARCH($G$9,'📋 Inventaire Complet'!$L$3:$L$517)))+($H$10*ISNUMBER(SEARCH($G$10,'📋 Inventaire Complet'!$L$3:$L$517))))>0)))} -> 1 | AA16: =IF(Y16="",0,Z16+ROW()/10000) -> 1.0016
C17: 2021 | D17: FALSE | E17: TechCell | F17: FALSE | Y17: LAHLALIA Ayoub; Khadija EL KAMOUNY | Z17: {=IF(Y17="",0,SUMPRODUCT(('📋 Inventaire Complet'!$E$3:$E$517=Y17)*((COUNTIF($B$6:$B$10,TRUE)=0)+ISNUMBER(IFERROR(MATCH('📋 Inventaire Complet'!$B$3:$B$517,IF($B$6:$B$10,$A$6:$A$10),0),""))>0)*((COUNTIF($D$6:$D$22,TRUE)=0)+ISNUMBER(IFERROR(MATCH(LEFT('📋 Inventaire Complet'!$J$3:$J$517,4),IF($D$6:$D$22,$C$6:$C$22&""),0),""))>0)*((COUNTIF($F$6:$F$20,TRUE)=0)+(ISNUMBER(IFERROR(MATCH('📋 Inventaire Complet'!$F$3:$F$517,IF($F$6:$F$19,$E$6:$E$19),0),""))+($F$20*ISNUMBER(MATCH('📋 Inventaire Complet'!$F$3:$F$517,{"D4R";"CEPH";"ISTI";"COLCOM";"HTMR"},0))))>0)*((COUNTIF($H$6:$H$10,TRUE)=0)+(($H$6*ISNUMBER(SEARCH($G$6,'📋 Inventaire Complet'!$L$3:$L$517)))+($H$7*ISNUMBER(SEARCH($G$7,'📋 Inventaire Complet'!$L$3:$L$517)))+($H$8*ISNUMBER(SEARCH($G$8,'📋 Inventaire Complet'!$L$3:$L$517)))+($H$9*ISNUMBER(SEARCH($G$9,'📋 Inventaire Complet'!$L$3:$L$517)))+($H$10*ISNUMBER(SEARCH($G$10,'📋 Inventaire Complet'!$L$3:$L$517))))>0)))} -> 1 | AA17: =IF(Y17="",0,Z17+ROW()/10000) -> 1.0017
C18: 2022 | D18: FALSE | E18: ILO | F18: FALSE | Y18: LAHLALIA Ayoub; EL KAMOUNY Khadija | Z18: {=IF(Y18="",0,SUMPRODUCT(('📋 Inventaire Complet'!$E$3:$E$517=Y18)*((COUNTIF($B$6:$B$10,TRUE)=0)+ISNUMBER(IFERROR(MATCH('📋 Inventaire Complet'!$B$3:$B$517,IF($B$6:$B$10,$A$6:$A$10),0),""))>0)*((COUNTIF($D$6:$D$22,TRUE)=0)+ISNUMBER(IFERROR(MATCH(LEFT('📋 Inventaire Complet'!$J$3:$J$517,4),IF($D$6:$D$22,$C$6:$C$22&""),0),""))>0)*((COUNTIF($F$6:$F$20,TRUE)=0)+(ISNUMBER(IFERROR(MATCH('📋 Inventaire Complet'!$F$3:$F$517,IF($F$6:$F$19,$E$6:$E$19),0),""))+($F$20*ISNUMBER(MATCH('📋 Inventaire Complet'!$F$3:$F$517,{"D4R";"CEPH";"ISTI";"COLCOM";"HTMR"},0))))>0)*((COUNTIF($H$6:$H$10,TRUE)=0)+(($H$6*ISNUMBER(SEARCH($G$6,'📋 Inventaire Complet'!$L$3:$L$517)))+($H$7*ISNUMBER(SEARCH($G$7,'📋 Inventaire Complet'!$L$3:$L$517)))+($H$8*ISNUMBER(SEARCH($G$8,'📋 Inventaire Complet'!$L$3:$L$517)))+($H$9*ISNUMBER(SEARCH($G$9,'📋 Inventaire Complet'!$L$3:$L$517)))+($H$10*ISNUMBER(SEARCH($G$10,'📋 Inventaire Complet'!$L$3:$L$517))))>0)))} -> 1 | AA18: =IF(Y18="",0,Z18+ROW()/10000) -> 1.0018
C19: 2023 | D19: FALSE | E19: Al-Moutmir | F19: FALSE | Y19: Zouheir Sekkat Dmitry V. Nesterenko | Z19: {=IF(Y19="",0,SUMPRODUCT(('📋 Inventaire Complet'!$E$3:$E$517=Y19)*((COUNTIF($B$6:$B$10,TRUE)=0)+ISNUMBER(IFERROR(MATCH('📋 Inventaire Complet'!$B$3:$B$517,IF($B$6:$B$10,$A$6:$A$10),0),""))>0)*((COUNTIF($D$6:$D$22,TRUE)=0)+ISNUMBER(IFERROR(MATCH(LEFT('📋 Inventaire Complet'!$J$3:$J$517,4),IF($D$6:$D$22,$C$6:$C$22&""),0),""))>0)*((COUNTIF($F$6:$F$20,TRUE)=0)+(ISNUMBER(IFERROR(MATCH('📋 Inventaire Complet'!$F$3:$F$517,IF($F$6:$F$19,$E$6:$E$19),0),""))+($F$20*ISNUMBER(MATCH('📋 Inventaire Complet'!$F$3:$F$517,{"D4R";"CEPH";"ISTI";"COLCOM";"HTMR"},0))))>0)*((COUNTIF($H$6:$H$10,TRUE)=0)+(($H$6*ISNUMBER(SEARCH($G$6,'📋 Inventaire Complet'!$L$3:$L$517)))+($H$7*ISNUMBER(SEARCH($G$7,'📋 Inventaire Complet'!$L$3:$L$517)))+($H$8*ISNUMBER(SEARCH($G$8,'📋 Inventaire Complet'!$L$3:$L$517)))+($H$9*ISNUMBER(SEARCH($G$9,'📋 Inventaire Complet'!$L$3:$L$517)))+($H$10*ISNUMBER(SEARCH($G$10,'📋 Inventaire Complet'!$L$3:$L$517))))>0)))} -> 1 | AA19: =IF(Y19="",0,Z19+ROW()/10000) -> 1.0019
C20: 2024 | D20: FALSE | E20: Autres (D4R/CEPH/ISTI/COLCOM/HTMR) | F20: FALSE | Y20: Zouheir SEKKAT Dmitry NESTERENKO | Z20: {=IF(Y20="",0,SUMPRODUCT(('📋 Inventaire Complet'!$E$3:$E$517=Y20)*((COUNTIF($B$6:$B$10,TRUE)=0)+ISNUMBER(IFERROR(MATCH('📋 Inventaire Complet'!$B$3:$B$517,IF($B$6:$B$10,$A$6:$A$10),0),""))>0)*((COUNTIF($D$6:$D$22,TRUE)=0)+ISNUMBER(IFERROR(MATCH(LEFT('📋 Inventaire Complet'!$J$3:$J$517,4),IF($D$6:$D$22,$C$6:$C$22&""),0),""))>0)*((COUNTIF($F$6:$F$20,TRUE)=0)+(ISNUMBER(IFERROR(MATCH('📋 Inventaire Complet'!$F$3:$F$517,IF($F$6:$F$19,$E$6:$E$19),0),""))+($F$20*ISNUMBER(MATCH('📋 Inventaire Complet'!$F$3:$F$517,{"D4R";"CEPH";"ISTI";"COLCOM";"HTMR"},0))))>0)*((COUNTIF($H$6:$H$10,TRUE)=0)+(($H$6*ISNUMBER(SEARCH($G$6,'📋 Inventaire Complet'!$L$3:$L$517)))+($H$7*ISNUMBER(SEARCH($G$7,'📋 Inventaire Complet'!$L$3:$L$517)))+($H$8*ISNUMBER(SEARCH($G$8,'📋 Inventaire Complet'!$L$3:$L$517)))+($H$9*ISNUMBER(SEARCH($G$9,'📋 Inventaire Complet'!$L$3:$L$517)))+($H$10*ISNUMBER(SEARCH($G$10,'📋 Inventaire Complet'!$L$3:$L$517))))>0)))} -> 1 | AA20: =IF(Y20="",0,Z20+ROW()/10000) -> 1.002
C21: 2025 | D21: FALSE | Y21: Ouadi SAIDI Ilham BOUZIDA Brahim LAKSSIR Reda RABIE | Z21: {=IF(Y21="",0,SUMPRODUCT(('📋 Inventaire Complet'!$E$3:$E$517=Y21)*((COUNTIF($B$6:$B$10,TRUE)=0)+ISNUMBER(IFERROR(MATCH('📋 Inventaire Complet'!$B$3:$B$517,IF($B$6:$B$10,$A$6:$A$10),0),""))>0)*((COUNTIF($D$6:$D$22,TRUE)=0)+ISNUMBER(IFERROR(MATCH(LEFT('📋 Inventaire Complet'!$J$3:$J$517,4),IF($D$6:$D$22,$C$6:$C$22&""),0),""))>0)*((COUNTIF($F$6:$F$20,TRUE)=0)+(ISNUMBER(IFERROR(MATCH('📋 Inventaire Complet'!$F$3:$F$517,IF($F$6:$F$19,$E$6:$E$19),0),""))+($F$20*ISNUMBER(MATCH('📋 Inventaire Complet'!$F$3:$F$517,{"D4R";"CEPH";"ISTI";"COLCOM";"HTMR"},0))))>0)*((COUNTIF($H$6:$H$10,TRUE)=0)+(($H$6*ISNUMBER(SEARCH($G$6,'📋 Inventaire Complet'!$L$3:$L$517)))+($H$7*ISNUMBER(SEARCH($G$7,'📋 Inventaire Complet'!$L$3:$L$517)))+($H$8*ISNUMBER(SEARCH($G$8,'📋 Inventaire Complet'!$L$3:$L$517)))+($H$9*ISNUMBER(SEARCH($G$9,'📋 Inventaire Complet'!$L$3:$L$517)))+($H$10*ISNUMBER(SEARCH($G$10,'📋 Inventaire Complet'!$L$3:$L$517))))>0)))} -> 1 | AA21: =IF(Y21="",0,Z21+ROW()/10000) -> 1.0021
C22: 2026 | D22: FALSE | Y22: Rachid Benani, Brahim Lakssir, Abdelhafid ALMATROUCH | Z22: {=IF(Y22="",0,SUMPRODUCT(('📋 Inventaire Complet'!$E$3:$E$517=Y22)*((COUNTIF($B$6:$B$10,TRUE)=0)+ISNUMBER(IFERROR(MATCH('📋 Inventaire Complet'!$B$3:$B$517,IF($B$6:$B$10,$A$6:$A$10),0),""))>0)*((COUNTIF($D$6:$D$22,TRUE)=0)+ISNUMBER(IFERROR(MATCH(LEFT('📋 Inventaire Complet'!$J$3:$J$517,4),IF($D$6:$D$22,$C$6:$C$22&""),0),""))>0)*((COUNTIF($F$6:$F$20,TRUE)=0)+(ISNUMBER(IFERROR(MATCH('📋 Inventaire Complet'!$F$3:$F$517,IF($F$6:$F$19,$E$6:$E$19),0),""))+($F$20*ISNUMBER(MATCH('📋 Inventaire Complet'!$F$3:$F$517,{"D4R";"CEPH";"ISTI";"COLCOM";"HTMR"},0))))>0)*((COUNTIF($H$6:$H$10,TRUE)=0)+(($H$6*ISNUMBER(SEARCH($G$6,'📋 Inventaire Complet'!$L$3:$L$517)))+($H$7*ISNUMBER(SEARCH($G$7,'📋 Inventaire Complet'!$L$3:$L$517)))+($H$8*ISNUMBER(SEARCH($G$8,'📋 Inventaire Complet'!$L$3:$L$517)))+($H$9*ISNUMBER(SEARCH($G$9,'📋 Inventaire Complet'!$L$3:$L$517)))+($H$10*ISNUMBER(SEARCH($G$10,'📋 Inventaire Complet'!$L$3:$L$517))))>0)))} -> 1 | AA22: =IF(Y22="",0,Z22+ROW()/10000) -> 1.0022
Y23: Zouheir SEKKAT Zakaria LAGHFOUR Safae AAZOU | Z23: {=IF(Y23="",0,SUMPRODUCT(('📋 Inventaire Complet'!$E$3:$E$517=Y23)*((COUNTIF($B$6:$B$10,TRUE)=0)+ISNUMBER(IFERROR(MATCH('📋 Inventaire Complet'!$B$3:$B$517,IF($B$6:$B$10,$A$6:$A$10),0),""))>0)*((COUNTIF($D$6:$D$22,TRUE)=0)+ISNUMBER(IFERROR(MATCH(LEFT('📋 Inventaire Complet'!$J$3:$J$517,4),IF($D$6:$D$22,$C$6:$C$22&""),0),""))>0)*((COUNTIF($F$6:$F$20,TRUE)=0)+(ISNUMBER(IFERROR(MATCH('📋 Inventaire Complet'!$F$3:$F$517,IF($F$6:$F$19,$E$6:$E$19),0),""))+($F$20*ISNUMBER(MATCH('📋 Inventaire Complet'!$F$3:$F$517,{"D4R";"CEPH";"ISTI";"COLCOM";"HTMR"},0))))>0)*((COUNTIF($H$6:$H$10,TRUE)=0)+(($H$6*ISNUMBER(SEARCH($G$6,'📋 Inventaire Complet'!$L$3:$L$517)))+($H$7*ISNUMBER(SEARCH($G$7,'📋 Inventaire Complet'!$L$3:$L$517)))+($H$8*ISNUMBER(SEARCH($G$8,'📋 Inventaire Complet'!$L$3:$L$517)))+($H$9*ISNUMBER(SEARCH($G$9,'📋 Inventaire Complet'!$L$3:$L$517)))+($H$10*ISNUMBER(SEARCH($G$10,'📋 Inventaire Complet'!$L$3:$L$517))))>0)))} -> 1 | AA23: =IF(Y23="",0,Z23+ROW()/10000) -> 1.0023
Y24: Rahmouni Anouar Mahboub Oussama Sekkat Zouheir | Z24: {=IF(Y24="",0,SUMPRODUCT(('📋 Inventaire Complet'!$E$3:$E$517=Y24)*((COUNTIF($B$6:$B$10,TRUE)=0)+ISNUMBER(IFERROR(MATCH('📋 Inventaire Complet'!$B$3:$B$517,IF($B$6:$B$10,$A$6:$A$10),0),""))>0)*((COUNTIF($D$6:$D$22,TRUE)=0)+ISNUMBER(IFERROR(MATCH(LEFT('📋 Inventaire Complet'!$J$3:$J$517,4),IF($D$6:$D$22,$C$6:$C$22&""),0),""))>0)*((COUNTIF($F$6:$F$20,TRUE)=0)+(ISNUMBER(IFERROR(MATCH('📋 Inventaire Complet'!$F$3:$F$517,IF($F$6:$F$19,$E$6:$E$19),0),""))+($F$20*ISNUMBER(MATCH('📋 Inventaire Complet'!$F$3:$F$517,{"D4R";"CEPH";"ISTI";"COLCOM";"HTMR"},0))))>0)*((COUNTIF($H$6:$H$10,TRUE)=0)+(($H$6*ISNUMBER(SEARCH($G$6,'📋 Inventaire Complet'!$L$3:$L$517)))+($H$7*ISNUMBER(SEARCH($G$7,'📋 Inventaire Complet'!$L$3:$L$517)))+($H$8*ISNUMBER(SEARCH($G$8,'📋 Inventaire Complet'!$L$3:$L$517)))+($H$9*ISNUMBER(SEARCH($G$9,'📋 Inventaire Complet'!$L$3:$L$517)))+($H$10*ISNUMBER(SEARCH($G$10,'📋 Inventaire Complet'!$L$3:$L$517))))>0)))} -> 1 | AA24: =IF(Y24="",0,Z24+ROW()/10000) -> 1.0024
Y25: BOURJA OMAR; ZENNAYI YAHYA; KABBAJ KAOUTAR | Z25: {=IF(Y25="",0,SUMPRODUCT(('📋 Inventaire Complet'!$E$3:$E$517=Y25)*((COUNTIF($B$6:$B$10,TRUE)=0)+ISNUMBER(IFERROR(MATCH('📋 Inventaire Complet'!$B$3:$B$517,IF($B$6:$B$10,$A$6:$A$10),0),""))>0)*((COUNTIF($D$6:$D$22,TRUE)=0)+ISNUMBER(IFERROR(MATCH(LEFT('📋 Inventaire Complet'!$J$3:$J$517,4),IF($D$6:$D$22,$C$6:$C$22&""),0),""))>0)*((COUNTIF($F$6:$F$20,TRUE)=0)+(ISNUMBER(IFERROR(MATCH('📋 Inventaire Complet'!$F$3:$F$517,IF($F$6:$F$19,$E$6:$E$19),0),""))+($F$20*ISNUMBER(MATCH('📋 Inventaire Complet'!$F$3:$F$517,{"D4R";"CEPH";"ISTI";"COLCOM";"HTMR"},0))))>0)*((COUNTIF($H$6:$H$10,TRUE)=0)+(($H$6*ISNUMBER(SEARCH($G$6,'📋 Inventaire Complet'!$L$3:$L$517)))+($H$7*ISNUMBER(SEARCH($G$7,'📋 Inventaire Complet'!$L$3:$L$517)))+($H$8*ISNUMBER(SEARCH($G$8,'📋 Inventaire Complet'!$L$3:$L$517)))+($H$9*ISNUMBER(SEARCH($G$9,'📋 Inventaire Complet'!$L$3:$L$517)))+($H$10*ISNUMBER(SEARCH($G$10,'📋 Inventaire Complet'!$L$3:$L$517))))>0)))} -> 1 | AA25: =IF(Y25="",0,Z25+ROW()/10000) -> 1.0025
A26: INDICATEURS CLÉS DE PERFORMANCE | T26: 2016 | U26: ASARI | V26: Vision artificielle, trafic & inspection | W26: {=SUMPRODUCT(('📋 Inventaire Complet'!$C$3:$C$517=$V26)*(((COUNTIF($B$6:$B$10,TRUE)=0)+ISNUMBER(IFERROR(MATCH('📋 Inventaire Complet'!$B$3:$B$517,IF($B$6:$B$10,$A$6:$A$10),0),""))>0))*(((COUNTIF($D$6:$D$22,TRUE)=0)+ISNUMBER(IFERROR(MATCH(LEFT('📋 Inventaire Complet'!$J$3:$J$517,4),IF($D$6:$D$22,$C$6:$C$22&""),0),""))>0))*(((COUNTIF($F$6:$F$20,TRUE)=0)+(ISNUMBER(IFERROR(MATCH('📋 Inventaire Complet'!$F$3:$F$517,IF($F$6:$F$19,$E$6:$E$19),0),""))+($F$20*ISNUMBER(MATCH('📋 Inventaire Complet'!$F$3:$F$517,{"D4R";"CEPH";"ISTI";"COLCOM";"HTMR"},0))))>0))*(LEN('📋 Inventaire Complet'!$D$3:$D$517)>0)*(((COUNTIF($H$6:$H$10,TRUE)=0)+(($H$6*ISNUMBER(SEARCH($G$6,'📋 Inventaire Complet'!$L$3:$L$517)))+($H$7*ISNUMBER(SEARCH($G$7,'📋 Inventaire Complet'!$L$3:$L$517)))+($H$8*ISNUMBER(SEARCH($G$8,'📋 Inventaire Complet'!$L$3:$L$517)))+($H$9*ISNUMBER(SEARCH($G$9,'📋 Inventaire Complet'!$L$3:$L$517)))+($H$10*ISNUMBER(SEARCH($G$10,'📋 Inventaire Complet'!$L$3:$L$517))))>0)))} -> 19 | X26: =W26+ROW()/10000 -> 19.0026 | Y26: LAKSSIR, Ouadi | Z26: {=IF(Y26="",0,SUMPRODUCT(('📋 Inventaire Complet'!$E$3:$E$517=Y26)*((COUNTIF($B$6:$B$10,TRUE)=0)+ISNUMBER(IFERROR(MATCH('📋 Inventaire Complet'!$B$3:$B$517,IF($B$6:$B$10,$A$6:$A$10),0),""))>0)*((COUNTIF($D$6:$D$22,TRUE)=0)+ISNUMBER(IFERROR(MATCH(LEFT('📋 Inventaire Complet'!$J$3:$J$517,4),IF($D$6:$D$22,$C$6:$C$22&""),0),""))>0)*((COUNTIF($F$6:$F$20,TRUE)=0)+(ISNUMBER(IFERROR(MATCH('📋 Inventaire Complet'!$F$3:$F$517,IF($F$6:$F$19,$E$6:$E$19),0),""))+($F$20*ISNUMBER(MATCH('📋 Inventaire Complet'!$F$3:$F$517,{"D4R";"CEPH";"ISTI";"COLCOM";"HTMR"},0))))>0)*((COUNTIF($H$6:$H$10,TRUE)=0)+(($H$6*ISNUMBER(SEARCH($G$6,'📋 Inventaire Complet'!$L$3:$L$517)))+($H$7*ISNUMBER(SEARCH($G$7,'📋 Inventaire Complet'!$L$3:$L$517)))+($H$8*ISNUMBER(SEARCH($G$8,'📋 Inventaire Complet'!$L$3:$L$517)))+($H$9*ISNUMBER(SEARCH($G$9,'📋 Inventaire Complet'!$L$3:$L$517)))+($H$10*ISNUMBER(SEARCH($G$10,'📋 Inventaire Complet'!$L$3:$L$517))))>0)))} -> 1 | AA26: =IF(Y26="",0,Z26+ROW()/10000) -> 1.0026
A27: Total brevets | B27: Maintenus actifs | C27: Délivrés / Actifs | D27: PCT international | E27: OMPIC en cours | F27: Abandonnés | G27: Inventeurs uniques | H27: Hub / Laboratoire impliquées | T27: 2017 | U27: GTI | V27: Électronique embarquée, RFID & IoT | W27: {=SUMPRODUCT(('📋 Inventaire Complet'!$C$3:$C$517=$V27)*(((COUNTIF($B$6:$B$10,TRUE)=0)+ISNUMBER(IFERROR(MATCH('📋 Inventaire Complet'!$B$3:$B$517,IF($B$6:$B$10,$A$6:$A$10),0),""))>0))*(((COUNTIF($D$6:$D$22,TRUE)=0)+ISNUMBER(IFERROR(MATCH(LEFT('📋 Inventaire Complet'!$J$3:$J$517,4),IF($D$6:$D$22,$C$6:$C$22&""),0),""))>0))*(((COUNTIF($F$6:$F$20,TRUE)=0)+(ISNUMBER(IFERROR(MATCH('📋 Inventaire Complet'!$F$3:$F$517,IF($F$6:$F$19,$E$6:$E$19),0),""))+($F$20*ISNUMBER(MATCH('📋 Inventaire Complet'!$F$3:$F$517,{"D4R";"CEPH";"ISTI";"COLCOM";"HTMR"},0))))>0))*(LEN('📋 Inventaire Complet'!$D$3:$D$517)>0)*(((COUNTIF($H$6:$H$10,TRUE)=0)+(($H$6*ISNUMBER(SEARCH($G$6,'📋 Inventaire Complet'!$L$3:$L$517)))+($H$7*ISNUMBER(SEARCH($G$7,'📋 Inventaire Complet'!$L$3:$L$517)))+($H$8*ISNUMBER(SEARCH($G$8,'📋 Inventaire Complet'!$L$3:$L$517)))+($H$9*ISNUMBER(SEARCH($G$9,'📋 Inventaire Complet'!$L$3:$L$517)))+($H$10*ISNUMBER(SEARCH($G$10,'📋 Inventaire Complet'!$L$3:$L$517))))>0)))} -> 10 | X27: =W27+ROW()/10000 -> 10.0027 | Y27: Bouhfid, Qaiss | Z27: {=IF(Y27="",0,SUMPRODUCT(('📋 Inventaire Complet'!$E$3:$E$517=Y27)*((COUNTIF($B$6:$B$10,TRUE)=0)+ISNUMBER(IFERROR(MATCH('📋 Inventaire Complet'!$B$3:$B$517,IF($B$6:$B$10,$A$6:$A$10),0),""))>0)*((COUNTIF($D$6:$D$22,TRUE)=0)+ISNUMBER(IFERROR(MATCH(LEFT('📋 Inventaire Complet'!$J$3:$J$517,4),IF($D$6:$D$22,$C$6:$C$22&""),0),""))>0)*((COUNTIF($F$6:$F$20,TRUE)=0)+(ISNUMBER(IFERROR(MATCH('📋 Inventaire Complet'!$F$3:$F$517,IF($F$6:$F$19,$E$6:$E$19),0),""))+($F$20*ISNUMBER(MATCH('📋 Inventaire Complet'!$F$3:$F$517,{"D4R";"CEPH";"ISTI";"COLCOM";"HTMR"},0))))>0)*((COUNTIF($H$6:$H$10,TRUE)=0)+(($H$6*ISNUMBER(SEARCH($G$6,'📋 Inventaire Complet'!$L$3:$L$517)))+($H$7*ISNUMBER(SEARCH($G$7,'📋 Inventaire Complet'!$L$3:$L$517)))+($H$8*ISNUMBER(SEARCH($G$8,'📋 Inventaire Complet'!$L$3:$L$517)))+($H$9*ISNUMBER(SEARCH($G$9,'📋 Inventaire Complet'!$L$3:$L$517)))+($H$10*ISNUMBER(SEARCH($G$10,'📋 Inventaire Complet'!$L$3:$L$517))))>0)))} -> 1 | AA27: =IF(Y27="",0,Z27+ROW()/10000) -> 1.0027
A28: {=SUMPRODUCT((LEN('📋 Inventaire Complet'!D3:D517)>0)*(((COUNTIF($B$6:$B$10,TRUE)=0)+ISNUMBER(IFERROR(MATCH('📋 Inventaire Complet'!$B$3:$B$517,IF($B$6:$B$10,$A$6:$A$10),0),""))>0))*(((COUNTIF($D$6:$D$22,TRUE)=0)+ISNUMBER(IFERROR(MATCH(LEFT('📋 Inventaire Complet'!$J$3:$J$517,4),IF($D$6:$D$22,$C$6:$C$22&""),0),""))>0))*(((COUNTIF($F$6:$F$20,TRUE)=0)+(ISNUMBER(IFERROR(MATCH('📋 Inventaire Complet'!$F$3:$F$517,IF($F$6:$F$19,$E$6:$E$19),0),""))+($F$20*ISNUMBER(MATCH('📋 Inventaire Complet'!F3:F517,{"D4R";"CEPH";"ISTI";"COLCOM";"HTMR"},0))))>0))*(((COUNTIF($H$6:$H$10,TRUE)=0)+(($H$6*ISNUMBER(SEARCH($G$6,'📋 Inventaire Complet'!$L$3:$L$517)))+($H$7*ISNUMBER(SEARCH($G$7,'📋 Inventaire Complet'!$L$3:$L$517)))+($H$8*ISNUMBER(SEARCH($G$8,'📋 Inventaire Complet'!$L$3:$L$517)))+($H$9*ISNUMBER(SEARCH($G$9,'📋 Inventaire Complet'!$L$3:$L$517)))+($H$10*ISNUMBER(SEARCH($G$10,'📋 Inventaire Complet'!$L$3:$L$517))))>0)))} -> 393 | B28: {=SUMPRODUCT((LEN('📋 Inventaire Complet'!D3:D517)>0)*(ISNUMBER(SEARCH("Maintenu",'📋 Inventaire Complet'!L3:L517)))*(((COUNTIF($B$6:$B$10,TRUE)=0)+ISNUMBER(IFERROR(MATCH('📋 Inventaire Complet'!$B$3:$B$517,IF($B$6:$B$10,$A$6:$A$10),0),""))>0))*(((COUNTIF($D$6:$D$22,TRUE)=0)+ISNUMBER(IFERROR(MATCH(LEFT('📋 Inventaire Complet'!$J$3:$J$517,4),IF($D$6:$D$22,$C$6:$C$22&""),0),""))>0))*(((COUNTIF($F$6:$F$20,TRUE)=0)+(ISNUMBER(IFERROR(MATCH('📋 Inventaire Complet'!$F$3:$F$517,IF($F$6:$F$19,$E$6:$E$19),0),""))+($F$20*ISNUMBER(MATCH('📋 Inventaire Complet'!F3:F517,{"D4R";"CEPH";"ISTI";"COLCOM";"HTMR"},0))))>0))*(((COUNTIF($H$6:$H$10,TRUE)=0)+(($H$6*ISNUMBER(SEARCH($G$6,'📋 Inventaire Complet'!$L$3:$L$517)))+($H$7*ISNUMBER(SEARCH($G$7,'📋 Inventaire Complet'!$L$3:$L$517)))+($H$8*ISNUMBER(SEARCH($G$8,'📋 Inventaire Complet'!$L$3:$L$517)))+($H$9*ISNUMBER(SEARCH($G$9,'📋 Inventaire Complet'!$L$3:$L$517)))+($H$10*ISNUMBER(SEARCH($G$10,'📋 Inventaire Complet'!$L$3:$L$517))))>0)))} -> 121 | C28: {=SUMPRODUCT((LEN('📋 Inventaire Complet'!D3:D517)>0)*(ISNUMBER(SEARCH("Délivré",'📋 Inventaire Complet'!L3:L517)))*(((COUNTIF($B$6:$B$10,TRUE)=0)+ISNUMBER(IFERROR(MATCH('📋 Inventaire Complet'!$B$3:$B$517,IF($B$6:$B$10,$A$6:$A$10),0),""))>0))*(((COUNTIF($D$6:$D$22,TRUE)=0)+ISNUMBER(IFERROR(MATCH(LEFT('📋 Inventaire Complet'!$J$3:$J$517,4),IF($D$6:$D$22,$C$6:$C$22&""),0),""))>0))*(((COUNTIF($F$6:$F$20,TRUE)=0)+(ISNUMBER(IFERROR(MATCH('📋 Inventaire Complet'!$F$3:$F$517,IF($F$6:$F$19,$E$6:$E$19),0),""))+($F$20*ISNUMBER(MATCH('📋 Inventaire Complet'!F3:F517,{"D4R";"CEPH";"ISTI";"COLCOM";"HTMR"},0))))>0))*(((COUNTIF($H$6:$H$10,TRUE)=0)+(($H$6*ISNUMBER(SEARCH($G$6,'📋 Inventaire Complet'!$L$3:$L$517)))+($H$7*ISNUMBER(SEARCH($G$7,'📋 Inventaire Complet'!$L$3:$L$517)))+($H$8*ISNUMBER(SEARCH($G$8,'📋 Inventaire Complet'!$L$3:$L$517)))+($H$9*ISNUMBER(SEARCH($G$9,'📋 Inventaire Complet'!$L$3:$L$517)))+($H$10*ISNUMBER(SEARCH($G$10,'📋 Inventaire Complet'!$L$3:$L$517))))>0)))} -> 51 | D28: {=SUMPRODUCT((LEN('📋 Inventaire Complet'!D3:D517)>0)*(ISNUMBER(SEARCH("PCT",'📋 Inventaire Complet'!L3:L517)))*(((COUNTIF($B$6:$B$10,TRUE)=0)+ISNUMBER(IFERROR(MATCH('📋 Inventaire Complet'!$B$3:$B$517,IF($B$6:$B$10,$A$6:$A$10),0),""))>0))*(((COUNTIF($D$6:$D$22,TRUE)=0)+ISNUMBER(IFERROR(MATCH(LEFT('📋 Inventaire Complet'!$J$3:$J$517,4),IF($D$6:$D$22,$C$6:$C$22&""),0),""))>0))*(((COUNTIF($F$6:$F$20,TRUE)=0)+(ISNUMBER(IFERROR(MATCH('📋 Inventaire Complet'!$F$3:$F$517,IF($F$6:$F$19,$E$6:$E$19),0),""))+($F$20*ISNUMBER(MATCH('📋 Inventaire Complet'!F3:F517,{"D4R";"CEPH";"ISTI";"COLCOM";"HTMR"},0))))>0))*(((COUNTIF($H$6:$H$10,TRUE)=0)+(($H$6*ISNUMBER(SEARCH($G$6,'📋 Inventaire Complet'!$L$3:$L$517)))+($H$7*ISNUMBER(SEARCH($G$7,'📋 Inventaire Complet'!$L$3:$L$517)))+($H$8*ISNUMBER(SEARCH($G$8,'📋 Inventaire Complet'!$L$3:$L$517)))+($H$9*ISNUMBER(SEARCH($G$9,'📋 Inventaire Complet'!$L$3:$L$517)))+($H$10*ISNUMBER(SEARCH($G$10,'📋 Inventaire Complet'!$L$3:$L$517))))>0)))} -> 26 | E28: {=SUMPRODUCT((LEN('📋 Inventaire Complet'!D3:D517)>0)*(ISNUMBER(SEARCH("OMPIC",'📋 Inventaire Complet'!L3:L517)))*(((COUNTIF($B$6:$B$10,TRUE)=0)+ISNUMBER(IFERROR(MATCH('📋 Inventaire Complet'!$B$3:$B$517,IF($B$6:$B$10,$A$6:$A$10),0),""))>0))*(((COUNTIF($D$6:$D$22,TRUE)=0)+ISNUMBER(IFERROR(MATCH(LEFT('📋 Inventaire Complet'!$J$3:$J$517,4),IF($D$6:$D$22,$C$6:$C$22&""),0),""))>0))*(((COUNTIF($F$6:$F$20,TRUE)=0)+(ISNUMBER(IFERROR(MATCH('📋 Inventaire Complet'!$F$3:$F$517,IF($F$6:$F$19,$E$6:$E$19),0),""))+($F$20*ISNUMBER(MATCH('📋 Inventaire Complet'!F3:F517,{"D4R";"CEPH";"ISTI";"COLCOM";"HTMR"},0))))>0))*(((COUNTIF($H$6:$H$10,TRUE)=0)+(($H$6*ISNUMBER(SEARCH($G$6,'📋 Inventaire Complet'!$L$3:$L$517)))+($H$7*ISNUMBER(SEARCH($G$7,'📋 Inventaire Complet'!$L$3:$L$517)))+($H$8*ISNUMBER(SEARCH($G$8,'📋 Inventaire Complet'!$L$3:$L$517)))+($H$9*ISNUMBER(SEARCH($G$9,'📋 Inventaire Complet'!$L$3:$L$517)))+($H$10*ISNUMBER(SEARCH($G$10,'📋 Inventaire Complet'!$L$3:$L$517))))>0)))} -> 56 | F28: {=SUMPRODUCT((LEN('📋 Inventaire Complet'!D3:D517)>0)*(ISNUMBER(SEARCH("Abandonné",'📋 Inventaire Complet'!L3:L517)))*(((COUNTIF($B$6:$B$10,TRUE)=0)+ISNUMBER(IFERROR(MATCH('📋 Inventaire Complet'!$B$3:$B$517,IF($B$6:$B$10,$A$6:$A$10),0),""))>0))*(((COUNTIF($D$6:$D$22,TRUE)=0)+ISNUMBER(IFERROR(MATCH(LEFT('📋 Inventaire Complet'!$J$3:$J$517,4),IF($D$6:$D$22,$C$6:$C$22&""),0),""))>0))*(((COUNTIF($F$6:$F$20,TRUE)=0)+(ISNUMBER(IFERROR(MATCH('📋 Inventaire Complet'!$F$3:$F$517,IF($F$6:$F$19,$E$6:$E$19),0),""))+($F$20*ISNUMBER(MATCH('📋 Inventaire Complet'!F3:F517,{"D4R";"CEPH";"ISTI";"COLCOM";"HTMR"},0))))>0))*(((COUNTIF($H$6:$H$10,TRUE)=0)+(($H$6*ISNUMBER(SEARCH($G$6,'📋 Inventaire Complet'!$L$3:$L$517)))+($H$7*ISNUMBER(SEARCH($G$7,'📋 Inventaire Complet'!$L$3:$L$517)))+($H$8*ISNUMBER(SEARCH($G$8,'📋 Inventaire Complet'!$L$3:$L$517)))+($H$9*ISNUMBER(SEARCH($G$9,'📋 Inventaire Complet'!$L$3:$L$517)))+($H$10*ISNUMBER(SEARCH($G$10,'📋 Inventaire Complet'!$L$3:$L$517))))>0)))} -> 44 | G28: {=SUMPRODUCT((LEN('📋 Inventaire Complet'!E3:E517)>0)*(LEN('📋 Inventaire Complet'!D3:D517)>0)*(((COUNTIF($B$6:$B$10,TRUE)=0)+ISNUMBER(IFERROR(MATCH('📋 Inventaire Complet'!$B$3:$B$517,IF($B$6:$B$10,$A$6:$A$10),0),""))>0))*(((COUNTIF($D$6:$D$22,TRUE)=0)+ISNUMBER(IFERROR(MATCH(LEFT('📋 Inventaire Complet'!$J$3:$J$517,4),IF($D$6:$D$22,$C$6:$C$22&""),0),""))>0))*(((COUNTIF($F$6:$F$20,TRUE)=0)+(ISNUMBER(IFERROR(MATCH('📋 Inventaire Complet'!$F$3:$F$517,IF($F$6:$F$19,$E$6:$E$19),0),""))+($F$20*ISNUMBER(MATCH('📋 Inventaire Complet'!F3:F517,{"D4R";"CEPH";"ISTI";"COLCOM";"HTMR"},0))))>0)))} -> 192 | H28: {=SUMPRODUCT(IFERROR((MATCH('📋 Inventaire Complet'!F3:F517,'📋 Inventaire Complet'!F3:F517,0)=ROW('📋 Inventaire Complet'!F3:F517)-2)*(LEN('📋 Inventaire Complet'!F3:F517)>0)*(((COUNTIF($B$6:$B$10,TRUE)=0)+ISNUMBER(IFERROR(MATCH('📋 Inventaire Complet'!$B$3:$B$517,IF($B$6:$B$10,$A$6:$A$10),0),""))>0))*(((COUNTIF($F$6:$F$20,TRUE)=0)+(ISNUMBER(IFERROR(MATCH('📋 Inventaire Complet'!$F$3:$F$517,IF($F$6:$F$19,$E$6:$E$19),0),""))+($F$20*ISNUMBER(MATCH('📋 Inventaire Complet'!F3:F517,{"D4R";"CEPH";"ISTI";"COLCOM";"HTMR"},0))))>0)),0)*(LEN('📋 Inventaire Complet'!$D$3:$D$517)>0))} -> 19 | T28: 2018 | U28: GSMI | V28: Énergie, solaire & efficacité énergétique | W28: {=SUMPRODUCT(('📋 Inventaire Complet'!$C$3:$C$517=$V28)*(((COUNTIF($B$6:$B$10,TRUE)=0)+ISNUMBER(IFERROR(MATCH('📋 Inventaire Complet'!$B$3:$B$517,IF($B$6:$B$10,$A$6:$A$10),0),""))>0))*(((COUNTIF($D$6:$D$22,TRUE)=0)+ISNUMBER(IFERROR(MATCH(LEFT('📋 Inventaire Complet'!$J$3:$J$517,4),IF($D$6:$D$22,$C$6:$C$22&""),0),""))>0))*(((COUNTIF($F$6:$F$20,TRUE)=0)+(ISNUMBER(IFERROR(MATCH('📋 Inventaire Complet'!$F$3:$F$517,IF($F$6:$F$19,$E$6:$E$19),0),""))+($F$20*ISNUMBER(MATCH('📋 Inventaire Complet'!$F$3:$F$517,{"D4R";"CEPH";"ISTI";"COLCOM";"HTMR"},0))))>0))*(LEN('📋 Inventaire Complet'!$D$3:$D$517)>0)*(((COUNTIF($H$6:$H$10,TRUE)=0)+(($H$6*ISNUMBER(SEARCH($G$6,'📋 Inventaire Complet'!$L$3:$L$517)))+($H$7*ISNUMBER(SEARCH($G$7,'📋 Inventaire Complet'!$L$3:$L$517)))+($H$8*ISNUMBER(SEARCH($G$8,'📋 Inventaire Complet'!$L$3:$L$517)))+($H$9*ISNUMBER(SEARCH($G$9,'📋 Inventaire Complet'!$L$3:$L$517)))+($H$10*ISNUMBER(SEARCH($G$10,'📋 Inventaire Complet'!$L$3:$L$517))))>0)))} -> 3 | X28: =W28+ROW()/10000 -> 3.0028 | Y28: qaiss, Bouhfid | Z28: {=IF(Y28="",0,SUMPRODUCT(('📋 Inventaire Complet'!$E$3:$E$517=Y28)*((COUNTIF($B$6:$B$10,TRUE)=0)+ISNUMBER(IFERROR(MATCH('📋 Inventaire Complet'!$B$3:$B$517,IF($B$6:$B$10,$A$6:$A$10),0),""))>0)*((COUNTIF($D$6:$D$22,TRUE)=0)+ISNUMBER(IFERROR(MATCH(LEFT('📋 Inventaire Complet'!$J$3:$J$517,4),IF($D$6:$D$22,$C$6:$C$22&""),0),""))>0)*((COUNTIF($F$6:$F$20,TRUE)=0)+(ISNUMBER(IFERROR(MATCH('📋 Inventaire Complet'!$F$3:$F$517,IF($F$6:$F$19,$E$6:$E$19),0),""))+($F$20*ISNUMBER(MATCH('📋 Inventaire Complet'!$F$3:$F$517,{"D4R";"CEPH";"ISTI";"COLCOM";"HTMR"},0))))>0)*((COUNTIF($H$6:$H$10,TRUE)=0)+(($H$6*ISNUMBER(SEARCH($G$6,'📋 Inventaire Complet'!$L$3:$L$517)))+($H$7*ISNUMBER(SEARCH($G$7,'📋 Inventaire Complet'!$L$3:$L$517)))+($H$8*ISNUMBER(SEARCH($G$8,'📋 Inventaire Complet'!$L$3:$L$517)))+($H$9*ISNUMBER(SEARCH($G$9,'📋 Inventaire Complet'!$L$3:$L$517)))+($H$10*ISNUMBER(SEARCH($G$10,'📋 Inventaire Complet'!$L$3:$L$517))))>0)))} -> 2 | AA28: =IF(Y28="",0,Z28+ROW()/10000) -> 2.0028
T29: 2019 | U29: LIMSET | V29: Ferrites, nanomatériaux magnétiques & magnétocaloriques | W29: {=SUMPRODUCT(('📋 Inventaire Complet'!$C$3:$C$517=$V29)*(((COUNTIF($B$6:$B$10,TRUE)=0)+ISNUMBER(IFERROR(MATCH('📋 Inventaire Complet'!$B$3:$B$517,IF($B$6:$B$10,$A$6:$A$10),0),""))>0))*(((COUNTIF($D$6:$D$22,TRUE)=0)+ISNUMBER(IFERROR(MATCH(LEFT('📋 Inventaire Complet'!$J$3:$J$517,4),IF($D$6:$D$22,$C$6:$C$22&""),0),""))>0))*(((COUNTIF($F$6:$F$20,TRUE)=0)+(ISNUMBER(IFERROR(MATCH('📋 Inventaire Complet'!$F$3:$F$517,IF($F$6:$F$19,$E$6:$E$19),0),""))+($F$20*ISNUMBER(MATCH('📋 Inventaire Complet'!$F$3:$F$517,{"D4R";"CEPH";"ISTI";"COLCOM";"HTMR"},0))))>0))*(LEN('📋 Inventaire Complet'!$D$3:$D$517)>0)*(((COUNTIF($H$6:$H$10,TRUE)=0)+(($H$6*ISNUMBER(SEARCH($G$6,'📋 Inventaire Complet'!$L$3:$L$517)))+($H$7*ISNUMBER(SEARCH($G$7,'📋 Inventaire Complet'!$L$3:$L$517)))+($H$8*ISNUMBER(SEARCH($G$8,'📋 Inventaire Complet'!$L$3:$L$517)))+($H$9*ISNUMBER(SEARCH($G$9,'📋 Inventaire Complet'!$L$3:$L$517)))+($H$10*ISNUMBER(SEARCH($G$10,'📋 Inventaire Complet'!$L$3:$L$517))))>0)))} -> 18 | X29: =W29+ROW()/10000 -> 18.0029 | Y29: ABOU EL KACEM QAISS BOUHFID RACHID ESSABIR HAMID | Z29: {=IF(Y29="",0,SUMPRODUCT(('📋 Inventaire Complet'!$E$3:$E$517=Y29)*((COUNTIF($B$6:$B$10,TRUE)=0)+ISNUMBER(IFERROR(MATCH('📋 Inventaire Complet'!$B$3:$B$517,IF($B$6:$B$10,$A$6:$A$10),0),""))>0)*((COUNTIF($D$6:$D$22,TRUE)=0)+ISNUMBER(IFERROR(MATCH(LEFT('📋 Inventaire Complet'!$J$3:$J$517,4),IF($D$6:$D$22,$C$6:$C$22&""),0),""))>0)*((COUNTIF($F$6:$F$20,TRUE)=0)+(ISNUMBER(IFERROR(MATCH('📋 Inventaire Complet'!$F$3:$F$517,IF($F$6:$F$19,$E$6:$E$19),0),""))+($F$20*ISNUMBER(MATCH('📋 Inventaire Complet'!$F$3:$F$517,{"D4R";"CEPH";"ISTI";"COLCOM";"HTMR"},0))))>0)*((COUNTIF($H$6:$H$10,TRUE)=0)+(($H$6*ISNUMBER(SEARCH($G$6,'📋 Inventaire Complet'!$L$3:$L$517)))+($H$7*ISNUMBER(SEARCH($G$7,'📋 Inventaire Complet'!$L$3:$L$517)))+($H$8*ISNUMBER(SEARCH($G$8,'📋 Inventaire Complet'!$L$3:$L$517)))+($H$9*ISNUMBER(SEARCH($G$9,'📋 Inventaire Complet'!$L$3:$L$517)))+($H$10*ISNUMBER(SEARCH($G$10,'📋 Inventaire Complet'!$L$3:$L$517))))>0)))} -> 1 | AA29: =IF(Y29="",0,Z29+ROW()/10000) -> 1.0029
A30: 5 dernières années | B30: Moyenne /an | C30: Année record | D30: Dernier dépôt | E30: % Délivré + Maint. | F30: % Abandonné | G30: % Inv. renseigné | H30: % Couv. géo. | T30: 2020 | U30: DICE | V30: Fertilisants phosphatés & sels de phosphate | W30: {=SUMPRODUCT(('📋 Inventaire Complet'!$C$3:$C$517=$V30)*(((COUNTIF($B$6:$B$10,TRUE)=0)+ISNUMBER(IFERROR(MATCH('📋 Inventaire Complet'!$B$3:$B$517,IF($B$6:$B$10,$A$6:$A$10),0),""))>0))*(((COUNTIF($D$6:$D$22,TRUE)=0)+ISNUMBER(IFERROR(MATCH(LEFT('📋 Inventaire Complet'!$J$3:$J$517,4),IF($D$6:$D$22,$C$6:$C$22&""),0),""))>0))*(((COUNTIF($F$6:$F$20,TRUE)=0)+(ISNUMBER(IFERROR(MATCH('📋 Inventaire Complet'!$F$3:$F$517,IF($F$6:$F$19,$E$6:$E$19),0),""))+($F$20*ISNUMBER(MATCH('📋 Inventaire Complet'!$F$3:$F$517,{"D4R";"CEPH";"ISTI";"COLCOM";"HTMR"},0))))>0))*(LEN('📋 Inventaire Complet'!$D$3:$D$517)>0)*(((COUNTIF($H$6:$H$10,TRUE)=0)+(($H$6*ISNUMBER(SEARCH($G$6,'📋 Inventaire Complet'!$L$3:$L$517)))+($H$7*ISNUMBER(SEARCH($G$7,'📋 Inventaire Complet'!$L$3:$L$517)))+($H$8*ISNUMBER(SEARCH($G$8,'📋 Inventaire Complet'!$L$3:$L$517)))+($H$9*ISNUMBER(SEARCH($G$9,'📋 Inventaire Complet'!$L$3:$L$517)))+($H$10*ISNUMBER(SEARCH($G$10,'📋 Inventaire Complet'!$L$3:$L$517))))>0)))} -> 17 | X30: =W30+ROW()/10000 -> 17.003 | Y30: QAISS, BOUHFID | Z30: {=IF(Y30="",0,SUMPRODUCT(('📋 Inventaire Complet'!$E$3:$E$517=Y30)*((COUNTIF($B$6:$B$10,TRUE)=0)+ISNUMBER(IFERROR(MATCH('📋 Inventaire Complet'!$B$3:$B$517,IF($B$6:$B$10,$A$6:$A$10),0),""))>0)*((COUNTIF($D$6:$D$22,TRUE)=0)+ISNUMBER(IFERROR(MATCH(LEFT('📋 Inventaire Complet'!$J$3:$J$517,4),IF($D$6:$D$22,$C$6:$C$22&""),0),""))>0)*((COUNTIF($F$6:$F$20,TRUE)=0)+(ISNUMBER(IFERROR(MATCH('📋 Inventaire Complet'!$F$3:$F$517,IF($F$6:$F$19,$E$6:$E$19),0),""))+($F$20*ISNUMBER(MATCH('📋 Inventaire Complet'!$F$3:$F$517,{"D4R";"CEPH";"ISTI";"COLCOM";"HTMR"},0))))>0)*((COUNTIF($H$6:$H$10,TRUE)=0)+(($H$6*ISNUMBER(SEARCH($G$6,'📋 Inventaire Complet'!$L$3:$L$517)))+($H$7*ISNUMBER(SEARCH($G$7,'📋 Inventaire Complet'!$L$3:$L$517)))+($H$8*ISNUMBER(SEARCH($G$8,'📋 Inventaire Complet'!$L$3:$L$517)))+($H$9*ISNUMBER(SEARCH($G$9,'📋 Inventaire Complet'!$L$3:$L$517)))+($H$10*ISNUMBER(SEARCH($G$10,'📋 Inventaire Complet'!$L$3:$L$517))))>0)))} -> 2 | AA30: =IF(Y30="",0,Z30+ROW()/10000) -> 2.003
A31: {=SUMPRODUCT((LEN('📋 Inventaire Complet'!D3:D517)>0)*(IFERROR(VALUE(LEFT('📋 Inventaire Complet'!J3:J517,4)),0)>=YEAR(TODAY())-5)*(((COUNTIF($B$6:$B$10,TRUE)=0)+ISNUMBER(IFERROR(MATCH('📋 Inventaire Complet'!$B$3:$B$517,IF($B$6:$B$10,$A$6:$A$10),0),""))>0))*(((COUNTIF($F$6:$F$20,TRUE)=0)+(ISNUMBER(IFERROR(MATCH('📋 Inventaire Complet'!$F$3:$F$517,IF($F$6:$F$19,$E$6:$E$19),0),""))+($F$20*ISNUMBER(MATCH('📋 Inventaire Complet'!F3:F517,{"D4R";"CEPH";"ISTI";"COLCOM";"HTMR"},0))))>0))*(((COUNTIF($H$6:$H$10,TRUE)=0)+(($H$6*ISNUMBER(SEARCH($G$6,'📋 Inventaire Complet'!$L$3:$L$517)))+($H$7*ISNUMBER(SEARCH($G$7,'📋 Inventaire Complet'!$L$3:$L$517)))+($H$8*ISNUMBER(SEARCH($G$8,'📋 Inventaire Complet'!$L$3:$L$517)))+($H$9*ISNUMBER(SEARCH($G$9,'📋 Inventaire Complet'!$L$3:$L$517)))+($H$10*ISNUMBER(SEARCH($G$10,'📋 Inventaire Complet'!$L$3:$L$517))))>0)))} -> 101 | B31: {=IFERROR(SUMPRODUCT((LEN('📋 Inventaire Complet'!D3:D517)>0)*(IFERROR(VALUE(LEFT('📋 Inventaire Complet'!J3:J517,4)),0)>0)*(((COUNTIF($B$6:$B$10,TRUE)=0)+ISNUMBER(IFERROR(MATCH('📋 Inventaire Complet'!$B$3:$B$517,IF($B$6:$B$10,$A$6:$A$10),0),""))>0))*(((COUNTIF($F$6:$F$20,TRUE)=0)+(ISNUMBER(IFERROR(MATCH('📋 Inventaire Complet'!$F$3:$F$517,IF($F$6:$F$19,$E$6:$E$19),0),""))+($F$20*ISNUMBER(MATCH('📋 Inventaire Complet'!F3:F517,{"D4R";"CEPH";"ISTI";"COLCOM";"HTMR"},0))))>0))*(((COUNTIF($H$6:$H$10,TRUE)=0)+(($H$6*ISNUMBER(SEARCH($G$6,'📋 Inventaire Complet'!$L$3:$L$517)))+($H$7*ISNUMBER(SEARCH($G$7,'📋 Inventaire Complet'!$L$3:$L$517)))+($H$8*ISNUMBER(SEARCH($G$8,'📋 Inventaire Complet'!$L$3:$L$517)))+($H$9*ISNUMBER(SEARCH($G$9,'📋 Inventaire Complet'!$L$3:$L$517)))+($H$10*ISNUMBER(SEARCH($G$10,'📋 Inventaire Complet'!$L$3:$L$517))))>0)))/(MAX(IFERROR(VALUE(LEFT('📋 Inventaire Complet'!J3:J517,4)),0))-MIN(IF(IFERROR(VALUE(LEFT('📋 Inventaire Complet'!J3:J517,4)),0)>0,IFERROR(VALUE(LEFT('📋 Inventaire Complet'!J3:J517,4)),9999)))+1),0)} -> 16.117647 | C31: =IFERROR(INDEX($A$53:$A$69,MATCH(MAX($G$53:$G$69),$G$53:$G$69,0)),"-") -> 2015 | D31: {=MAX(IFERROR(VALUE(LEFT('📋 Inventaire Complet'!J3:J517,4)),0))} -> 2026 | E31: =IFERROR((B28+C28)/A28,0) -> 0.43765903 | F31: =IFERROR(F28/A28,0) -> 0.11195929 | G31: =IFERROR(G28/A28,0) -> 0.48854962 | H31: {=IFERROR(SUMPRODUCT((LEN('📋 Inventaire Complet'!D3:D517)>0)*(LEN('📋 Inventaire Complet'!M3:M517)>0)*(((COUNTIF($B$6:$B$10,TRUE)=0)+ISNUMBER(IFERROR(MATCH('📋 Inventaire Complet'!$B$3:$B$517,IF($B$6:$B$10,$A$6:$A$10),0),""))>0))*(((COUNTIF($D$6:$D$22,TRUE)=0)+ISNUMBER(IFERROR(MATCH(LEFT('📋 Inventaire Complet'!$J$3:$J$517,4),IF($D$6:$D$22,$C$6:$C$22&""),0),""))>0))*(((COUNTIF($F$6:$F$20,TRUE)=0)+(ISNUMBER(IFERROR(MATCH('📋 Inventaire Complet'!$F$3:$F$517,IF($F$6:$F$19,$E$6:$E$19),0),""))+($F$20*ISNUMBER(MATCH('📋 Inventaire Complet'!F3:F517,{"D4R";"CEPH";"ISTI";"COLCOM";"HTMR"},0))))>0)))/A28,0)} -> 0.67684478 | T31: 2021 | U31: TechCell | V31: Flottation & enrichissement des minerais | W31: {=SUMPRODUCT(('📋 Inventaire Complet'!$C$3:$C$517=$V31)*(((COUNTIF($B$6:$B$10,TRUE)=0)+ISNUMBER(IFERROR(MATCH('📋 Inventaire Complet'!$B$3:$B$517,IF($B$6:$B$10,$A$6:$A$10),0),""))>0))*(((COUNTIF($D$6:$D$22,TRUE)=0)+ISNUMBER(IFERROR(MATCH(LEFT('📋 Inventaire Complet'!$J$3:$J$517,4),IF($D$6:$D$22,$C$6:$C$22&""),0),""))>0))*(((COUNTIF($F$6:$F$20,TRUE)=0)+(ISNUMBER(IFERROR(MATCH('📋 Inventaire Complet'!$F$3:$F$517,IF($F$6:$F$19,$E$6:$E$19),0),""))+($F$20*ISNUMBER(MATCH('📋 Inventaire Complet'!$F$3:$F$517,{"D4R";"CEPH";"ISTI";"COLCOM";"HTMR"},0))))>0))*(LEN('📋 Inventaire Complet'!$D$3:$D$517)>0)*(((COUNTIF($H$6:$H$10,TRUE)=0)+(($H$6*ISNUMBER(SEARCH($G$6,'📋 Inventaire Complet'!$L$3:$L$517)))+($H$7*ISNUMBER(SEARCH($G$7,'📋 Inventaire Complet'!$L$3:$L$517)))+($H$8*ISNUMBER(SEARCH($G$8,'📋 Inventaire Complet'!$L$3:$L$517)))+($H$9*ISNUMBER(SEARCH($G$9,'📋 Inventaire Complet'!$L$3:$L$517)))+($H$10*ISNUMBER(SEARCH($G$10,'📋 Inventaire Complet'!$L$3:$L$517))))>0)))} -> 5 | X31: =W31+ROW()/10000 -> 5.0031 | Y31: El Moussaoui Hassan Hamedooune Mohammed Mounkachi Omar benyoussef Abdelilah | Z31: {=IF(Y31="",0,SUMPRODUCT(('📋 Inventaire Complet'!$E$3:$E$517=Y31)*((COUNTIF($B$6:$B$10,TRUE)=0)+ISNUMBER(IFERROR(MATCH('📋 Inventaire Complet'!$B$3:$B$517,IF($B$6:$B$10,$A$6:$A$10),0),""))>0)*((COUNTIF($D$6:$D$22,TRUE)=0)+ISNUMBER(IFERROR(MATCH(LEFT('📋 Inventaire Complet'!$J$3:$J$517,4),IF($D$6:$D$22,$C$6:$C$22&""),0),""))>0)*((COUNTIF($F$6:$F$20,TRUE)=0)+(ISNUMBER(IFERROR(MATCH('📋 Inventaire Complet'!$F$3:$F$517,IF($F$6:$F$19,$E$6:$E$19),0),""))+($F$20*ISNUMBER(MATCH('📋 Inventaire Complet'!$F$3:$F$517,{"D4R";"CEPH";"ISTI";"COLCOM";"HTMR"},0))))>0)*((COUNTIF($H$6:$H$10,TRUE)=0)+(($H$6*ISNUMBER(SEARCH($G$6,'📋 Inventaire Complet'!$L$3:$L$517)))+($H$7*ISNUMBER(SEARCH($G$7,'📋 Inventaire Complet'!$L$3:$L$517)))+($H$8*ISNUMBER(SEARCH($G$8,'📋 Inventaire Complet'!$L$3:$L$517)))+($H$9*ISNUMBER(SEARCH($G$9,'📋 Inventaire Complet'!$L$3:$L$517)))+($H$10*ISNUMBER(SEARCH($G$10,'📋 Inventaire Complet'!$L$3:$L$517))))>0)))} -> 1 | AA31: =IF(Y31="",0,Z31+ROW()/10000) -> 1.0031
T32: 2022 | U32: ILO | V32: Matériaux composites, verre & catalyseurs | W32: {=SUMPRODUCT(('📋 Inventaire Complet'!$C$3:$C$517=$V32)*(((COUNTIF($B$6:$B$10,TRUE)=0)+ISNUMBER(IFERROR(MATCH('📋 Inventaire Complet'!$B$3:$B$517,IF($B$6:$B$10,$A$6:$A$10),0),""))>0))*(((COUNTIF($D$6:$D$22,TRUE)=0)+ISNUMBER(IFERROR(MATCH(LEFT('📋 Inventaire Complet'!$J$3:$J$517,4),IF($D$6:$D$22,$C$6:$C$22&""),0),""))>0))*(((COUNTIF($F$6:$F$20,TRUE)=0)+(ISNUMBER(IFERROR(MATCH('📋 Inventaire Complet'!$F$3:$F$517,IF($F$6:$F$19,$E$6:$E$19),0),""))+($F$20*ISNUMBER(MATCH('📋 Inventaire Complet'!$F$3:$F$517,{"D4R";"CEPH";"ISTI";"COLCOM";"HTMR"},0))))>0))*(LEN('📋 Inventaire Complet'!$D$3:$D$517)>0)*(((COUNTIF($H$6:$H$10,TRUE)=0)+(($H$6*ISNUMBER(SEARCH($G$6,'📋 Inventaire Complet'!$L$3:$L$517)))+($H$7*ISNUMBER(SEARCH($G$7,'📋 Inventaire Complet'!$L$3:$L$517)))+($H$8*ISNUMBER(SEARCH($G$8,'📋 Inventaire Complet'!$L$3:$L$517)))+($H$9*ISNUMBER(SEARCH($G$9,'📋 Inventaire Complet'!$L$3:$L$517)))+($H$10*ISNUMBER(SEARCH($G$10,'📋 Inventaire Complet'!$L$3:$L$517))))>0)))} -> 12 | X32: =W32+ROW()/10000 -> 12.0032 | Y32: RAJI MARYA; QAISS ABOU EL KACEM; BOUHFID RACHID | Z32: {=IF(Y32="",0,SUMPRODUCT(('📋 Inventaire Complet'!$E$3:$E$517=Y32)*((COUNTIF($B$6:$B$10,TRUE)=0)+ISNUMBER(IFERROR(MATCH('📋 Inventaire Complet'!$B$3:$B$517,IF($B$6:$B$10,$A$6:$A$10),0),""))>0)*((COUNTIF($D$6:$D$22,TRUE)=0)+ISNUMBER(IFERROR(MATCH(LEFT('📋 Inventaire Complet'!$J$3:$J$517,4),IF($D$6:$D$22,$C$6:$C$22&""),0),""))>0)*((COUNTIF($F$6:$F$20,TRUE)=0)+(ISNUMBER(IFERROR(MATCH('📋 Inventaire Complet'!$F$3:$F$517,IF($F$6:$F$19,$E$6:$E$19),0),""))+($F$20*ISNUMBER(MATCH('📋 Inventaire Complet'!$F$3:$F$517,{"D4R";"CEPH";"ISTI";"COLCOM";"HTMR"},0))))>0)*((COUNTIF($H$6:$H$10,TRUE)=0)+(($H$6*ISNUMBER(SEARCH($G$6,'📋 Inventaire Complet'!$L$3:$L$517)))+($H$7*ISNUMBER(SEARCH($G$7,'📋 Inventaire Complet'!$L$3:$L$517)))+($H$8*ISNUMBER(SEARCH($G$8,'📋 Inventaire Complet'!$L$3:$L$517)))+($H$9*ISNUMBER(SEARCH($G$9,'📋 Inventaire Complet'!$L$3:$L$517)))+($H$10*ISNUMBER(SEARCH($G$10,'📋 Inventaire Complet'!$L$3:$L$517))))>0)))} -> 1 | AA32: =IF(Y32="",0,Z32+ROW()/10000) -> 1.0032
A33: RÉPARTITION PAR THÉMATIQUE | E33: RÉPARTITION PAR HUB/LABORATOIRE | I33: RÉPARTITION PAR STATUT | T33: 2023 | U33: Al-Moutmir | V33: Phosphogypse, gypse & co-produits | W33: {=SUMPRODUCT(('📋 Inventaire Complet'!$C$3:$C$517=$V33)*(((COUNTIF($B$6:$B$10,TRUE)=0)+ISNUMBER(IFERROR(MATCH('📋 Inventaire Complet'!$B$3:$B$517,IF($B$6:$B$10,$A$6:$A$10),0),""))>0))*(((COUNTIF($D$6:$D$22,TRUE)=0)+ISNUMBER(IFERROR(MATCH(LEFT('📋 Inventaire Complet'!$J$3:$J$517,4),IF($D$6:$D$22,$C$6:$C$22&""),0),""))>0))*(((COUNTIF($F$6:$F$20,TRUE)=0)+(ISNUMBER(IFERROR(MATCH('📋 Inventaire Complet'!$F$3:$F$517,IF($F$6:$F$19,$E$6:$E$19),0),""))+($F$20*ISNUMBER(MATCH('📋 Inventaire Complet'!$F$3:$F$517,{"D4R";"CEPH";"ISTI";"COLCOM";"HTMR"},0))))>0))*(LEN('📋 Inventaire Complet'!$D$3:$D$517)>0)*(((COUNTIF($H$6:$H$10,TRUE)=0)+(($H$6*ISNUMBER(SEARCH($G$6,'📋 Inventaire Complet'!$L$3:$L$517)))+($H$7*ISNUMBER(SEARCH($G$7,'📋 Inventaire Complet'!$L$3:$L$517)))+($H$8*ISNUMBER(SEARCH($G$8,'📋 Inventaire Complet'!$L$3:$L$517)))+($H$9*ISNUMBER(SEARCH($G$9,'📋 Inventaire Complet'!$L$3:$L$517)))+($H$10*ISNUMBER(SEARCH($G$10,'📋 Inventaire Complet'!$L$3:$L$517))))>0)))} -> 3 | X33: =W33+ROW()/10000 -> 3.0033 | Y33: BOUHFID Rachid ABOU EL KACEM Qaiss | Z33: {=IF(Y33="",0,SUMPRODUCT(('📋 Inventaire Complet'!$E$3:$E$517=Y33)*((COUNTIF($B$6:$B$10,TRUE)=0)+ISNUMBER(IFERROR(MATCH('📋 Inventaire Complet'!$B$3:$B$517,IF($B$6:$B$10,$A$6:$A$10),0),""))>0)*((COUNTIF($D$6:$D$22,TRUE)=0)+ISNUMBER(IFERROR(MATCH(LEFT('📋 Inventaire Complet'!$J$3:$J$517,4),IF($D$6:$D$22,$C$6:$C$22&""),0),""))>0)*((COUNTIF($F$6:$F$20,TRUE)=0)+(ISNUMBER(IFERROR(MATCH('📋 Inventaire Complet'!$F$3:$F$517,IF($F$6:$F$19,$E$6:$E$19),0),""))+($F$20*ISNUMBER(MATCH('📋 Inventaire Complet'!$F$3:$F$517,{"D4R";"CEPH";"ISTI";"COLCOM";"HTMR"},0))))>0)*((COUNTIF($H$6:$H$10,TRUE)=0)+(($H$6*ISNUMBER(SEARCH($G$6,'📋 Inventaire Complet'!$L$3:$L$517)))+($H$7*ISNUMBER(SEARCH($G$7,'📋 Inventaire Complet'!$L$3:$L$517)))+($H$8*ISNUMBER(SEARCH($G$8,'📋 Inventaire Complet'!$L$3:$L$517)))+($H$9*ISNUMBER(SEARCH($G$9,'📋 Inventaire Complet'!$L$3:$L$517)))+($H$10*ISNUMBER(SEARCH($G$10,'📋 Inventaire Complet'!$L$3:$L$517))))>0)))} -> 1 | AA33: =IF(Y33="",0,Z33+ROW()/10000) -> 1.0033
A34: Thématique | B34: Nombre | C34: % du total | E34: Hub / Laboratoire | F34: Nombre | G34: % du total | I34: Statut | J34: Nombre | K34: % du total | T34: 2024 | U34: D4R | V34: Potasse, carnallite & saumures | W34: {=SUMPRODUCT(('📋 Inventaire Complet'!$C$3:$C$517=$V34)*(((COUNTIF($B$6:$B$10,TRUE)=0)+ISNUMBER(IFERROR(MATCH('📋 Inventaire Complet'!$B$3:$B$517,IF($B$6:$B$10,$A$6:$A$10),0),""))>0))*(((COUNTIF($D$6:$D$22,TRUE)=0)+ISNUMBER(IFERROR(MATCH(LEFT('📋 Inventaire Complet'!$J$3:$J$517,4),IF($D$6:$D$22,$C$6:$C$22&""),0),""))>0))*(((COUNTIF($F$6:$F$20,TRUE)=0)+(ISNUMBER(IFERROR(MATCH('📋 Inventaire Complet'!$F$3:$F$517,IF($F$6:$F$19,$E$6:$E$19),0),""))+($F$20*ISNUMBER(MATCH('📋 Inventaire Complet'!$F$3:$F$517,{"D4R";"CEPH";"ISTI";"COLCOM";"HTMR"},0))))>0))*(LEN('📋 Inventaire Complet'!$D$3:$D$517)>0)*(((COUNTIF($H$6:$H$10,TRUE)=0)+(($H$6*ISNUMBER(SEARCH($G$6,'📋 Inventaire Complet'!$L$3:$L$517)))+($H$7*ISNUMBER(SEARCH($G$7,'📋 Inventaire Complet'!$L$3:$L$517)))+($H$8*ISNUMBER(SEARCH($G$8,'📋 Inventaire Complet'!$L$3:$L$517)))+($H$9*ISNUMBER(SEARCH($G$9,'📋 Inventaire Complet'!$L$3:$L$517)))+($H$10*ISNUMBER(SEARCH($G$10,'📋 Inventaire Complet'!$L$3:$L$517))))>0)))} -> 2 | X34: =W34+ROW()/10000 -> 2.0034 | Y34: BOUHFID RACHID Qaiss Abou el kacem Ourhim Wafa | Z34: {=IF(Y34="",0,SUMPRODUCT(('📋 Inventaire Complet'!$E$3:$E$517=Y34)*((COUNTIF($B$6:$B$10,TRUE)=0)+ISNUMBER(IFERROR(MATCH('📋 Inventaire Complet'!$B$3:$B$517,IF($B$6:$B$10,$A$6:$A$10),0),""))>0)*((COUNTIF($D$6:$D$22,TRUE)=0)+ISNUMBER(IFERROR(MATCH(LEFT('📋 Inventaire Complet'!$J$3:$J$517,4),IF($D$6:$D$22,$C$6:$C$22&""),0),""))>0)*((COUNTIF($F$6:$F$20,TRUE)=0)+(ISNUMBER(IFERROR(MATCH('📋 Inventaire Complet'!$F$3:$F$517,IF($F$6:$F$19,$E$6:$E$19),0),""))+($F$20*ISNUMBER(MATCH('📋 Inventaire Complet'!$F$3:$F$517,{"D4R";"CEPH";"ISTI";"COLCOM";"HTMR"},0))))>0)*((COUNTIF($H$6:$H$10,TRUE)=0)+(($H$6*ISNUMBER(SEARCH($G$6,'📋 Inventaire Complet'!$L$3:$L$517)))+($H$7*ISNUMBER(SEARCH($G$7,'📋 Inventaire Complet'!$L$3:$L$517)))+($H$8*ISNUMBER(SEARCH($G$8,'📋 Inventaire Complet'!$L$3:$L$517)))+($H$9*ISNUMBER(SEARCH($G$9,'📋 Inventaire Complet'!$L$3:$L$517)))+($H$10*ISNUMBER(SEARCH($G$10,'📋 Inventaire Complet'!$L$3:$L$517))))>0)))} -> 1 | AA34: =IF(Y34="",0,Z34+ROW()/10000) -> 1.0034
A35: Environmental Tech & Digital Mining | B35: {=SUMPRODUCT(('📋 Inventaire Complet'!$B$3:$B$517=$A35)*(((COUNTIF($D$6:$D$22,TRUE)=0)+ISNUMBER(IFERROR(MATCH(LEFT('📋 Inventaire Complet'!$J$3:$J$517,4),IF($D$6:$D$22,$C$6:$C$22&""),0),""))>0))*(((COUNTIF($F$6:$F$20,TRUE)=0)+(ISNUMBER(IFERROR(MATCH('📋 Inventaire Complet'!$F$3:$F$517,IF($F$6:$F$19,$E$6:$E$19),0),""))+($F$20*ISNUMBER(MATCH('📋 Inventaire Complet'!$F$3:$F$517,{"D4R";"CEPH";"ISTI";"COLCOM";"HTMR"},0))))>0))*(LEN('📋 Inventaire Complet'!$D$3:$D$517)>0)*(((COUNTIF($H$6:$H$10,TRUE)=0)+(($H$6*ISNUMBER(SEARCH($G$6,'📋 Inventaire Complet'!$L$3:$L$517)))+($H$7*ISNUMBER(SEARCH($G$7,'📋 Inventaire Complet'!$L$3:$L$517)))+($H$8*ISNUMBER(SEARCH($G$8,'📋 Inventaire Complet'!$L$3:$L$517)))+($H$9*ISNUMBER(SEARCH($G$9,'📋 Inventaire Complet'!$L$3:$L$517)))+($H$10*ISNUMBER(SEARCH($G$10,'📋 Inventaire Complet'!$L$3:$L$517))))>0)))} -> 161 | C35: =IFERROR(B35/$B$40,0) -> 0.41176471 | E35: MAScIR | F35: {=SUMPRODUCT(('📋 Inventaire Complet'!$F$3:$F$517=$E35)*(((COUNTIF($B$6:$B$10,TRUE)=0)+ISNUMBER(IFERROR(MATCH('📋 Inventaire Complet'!$B$3:$B$517,IF($B$6:$B$10,$A$6:$A$10),0),""))>0))*(((COUNTIF($D$6:$D$22,TRUE)=0)+ISNUMBER(IFERROR(MATCH(LEFT('📋 Inventaire Complet'!$J$3:$J$517,4),IF($D$6:$D$22,$C$6:$C$22&""),0),""))>0))*(LEN('📋 Inventaire Complet'!$D$3:$D$517)>0)*(((COUNTIF($H$6:$H$10,TRUE)=0)+(($H$6*ISNUMBER(SEARCH($G$6,'📋 Inventaire Complet'!$L$3:$L$517)))+($H$7*ISNUMBER(SEARCH($G$7,'📋 Inventaire Complet'!$L$3:$L$517)))+($H$8*ISNUMBER(SEARCH($G$8,'📋 Inventaire Complet'!$L$3:$L$517)))+($H$9*ISNUMBER(SEARCH($G$9,'📋 Inventaire Complet'!$L$3:$L$517)))+($H$10*ISNUMBER(SEARCH($G$10,'📋 Inventaire Complet'!$L$3:$L$517))))>0)))} -> 193 | G35: =IFERROR(F35/$F$50,0) -> 0.49109415 | I35: 🔵 Maintenu / En phase nationale | J35: {=SUMPRODUCT((ISNUMBER(SEARCH("Maintenu",'📋 Inventaire Complet'!$L$3:$L$517)))*(((COUNTIF($B$6:$B$10,TRUE)=0)+ISNUMBER(IFERROR(MATCH('📋 Inventaire Complet'!$B$3:$B$517,IF($B$6:$B$10,$A$6:$A$10),0),""))>0))*(((COUNTIF($D$6:$D$22,TRUE)=0)+ISNUMBER(IFERROR(MATCH(LEFT('📋 Inventaire Complet'!$J$3:$J$517,4),IF($D$6:$D$22,$C$6:$C$22&""),0),""))>0))*(((COUNTIF($F$6:$F$20,TRUE)=0)+(ISNUMBER(IFERROR(MATCH('📋 Inventaire Complet'!$F$3:$F$517,IF($F$6:$F$19,$E$6:$E$19),0),""))+($F$20*ISNUMBER(MATCH('📋 Inventaire Complet'!$F$3:$F$517,{"D4R";"CEPH";"ISTI";"COLCOM";"HTMR"},0))))>0))*(LEN('📋 Inventaire Complet'!$D$3:$D$517)>0))} -> 121 | K35: =IFERROR(J35/$A$28,0) -> 0.30788804 | T35: 2025 | U35: CEPH | V35: Procédés thermiques, calcination & traitement à sec | W35: {=SUMPRODUCT(('📋 Inventaire Complet'!$C$3:$C$517=$V35)*(((COUNTIF($B$6:$B$10,TRUE)=0)+ISNUMBER(IFERROR(MATCH('📋 Inventaire Complet'!$B$3:$B$517,IF($B$6:$B$10,$A$6:$A$10),0),""))>0))*(((COUNTIF($D$6:$D$22,TRUE)=0)+ISNUMBER(IFERROR(MATCH(LEFT('📋 Inventaire Complet'!$J$3:$J$517,4),IF($D$6:$D$22,$C$6:$C$22&""),0),""))>0))*(((COUNTIF($F$6:$F$20,TRUE)=0)+(ISNUMBER(IFERROR(MATCH('📋 Inventaire Complet'!$F$3:$F$517,IF($F$6:$F$19,$E$6:$E$19),0),""))+($F$20*ISNUMBER(MATCH('📋 Inventaire Complet'!$F$3:$F$517,{"D4R";"CEPH";"ISTI";"COLCOM";"HTMR"},0))))>0))*(LEN('📋 Inventaire Complet'!$D$3:$D$517)>0)*(((COUNTIF($H$6:$H$10,TRUE)=0)+(($H$6*ISNUMBER(SEARCH($G$6,'📋 Inventaire Complet'!$L$3:$L$517)))+($H$7*ISNUMBER(SEARCH($G$7,'📋 Inventaire Complet'!$L$3:$L$517)))+($H$8*ISNUMBER(SEARCH($G$8,'📋 Inventaire Complet'!$L$3:$L$517)))+($H$9*ISNUMBER(SEARCH($G$9,'📋 Inventaire Complet'!$L$3:$L$517)))+($H$10*ISNUMBER(SEARCH($G$10,'📋 Inventaire Complet'!$L$3:$L$517))))>0)))} -> 4 | X35: =W35+ROW()/10000 -> 4.0035 | Y35: Qaiss Abou el kacem Bouhfid Rachid | Z35: {=IF(Y35="",0,SUMPRODUCT(('📋 Inventaire Complet'!$E$3:$E$517=Y35)*((COUNTIF($B$6:$B$10,TRUE)=0)+ISNUMBER(IFERROR(MATCH('📋 Inventaire Complet'!$B$3:$B$517,IF($B$6:$B$10,$A$6:$A$10),0),""))>0)*((COUNTIF($D$6:$D$22,TRUE)=0)+ISNUMBER(IFERROR(MATCH(LEFT('📋 Inventaire Complet'!$J$3:$J$517,4),IF($D$6:$D$22,$C$6:$C$22&""),0),""))>0)*((COUNTIF($F$6:$F$20,TRUE)=0)+(ISNUMBER(IFERROR(MATCH('📋 Inventaire Complet'!$F$3:$F$517,IF($F$6:$F$19,$E$6:$E$19),0),""))+($F$20*ISNUMBER(MATCH('📋 Inventaire Complet'!$F$3:$F$517,{"D4R";"CEPH";"ISTI";"COLCOM";"HTMR"},0))))>0)*((COUNTIF($H$6:$H$10,TRUE)=0)+(($H$6*ISNUMBER(SEARCH($G$6,'📋 Inventaire Complet'!$L$3:$L$517)))+($H$7*ISNUMBER(SEARCH($G$7,'📋 Inventaire Complet'!$L$3:$L$517)))+($H$8*ISNUMBER(SEARCH($G$8,'📋 Inventaire Complet'!$L$3:$L$517)))+($H$9*ISNUMBER(SEARCH($G$9,'📋 Inventaire Complet'!$L$3:$L$517)))+($H$10*ISNUMBER(SEARCH($G$10,'📋 Inventaire Complet'!$L$3:$L$517))))>0)))} -> 2 | AA35: =IF(Y35="",0,Z35+ROW()/10000) -> 2.0035
A36: Mineral Processing & Strategic Synthesis | B36: {=SUMPRODUCT(('📋 Inventaire Complet'!$B$3:$B$517=$A36)*(((COUNTIF($D$6:$D$22,TRUE)=0)+ISNUMBER(IFERROR(MATCH(LEFT('📋 Inventaire Complet'!$J$3:$J$517,4),IF($D$6:$D$22,$C$6:$C$22&""),0),""))>0))*(((COUNTIF($F$6:$F$20,TRUE)=0)+(ISNUMBER(IFERROR(MATCH('📋 Inventaire Complet'!$F$3:$F$517,IF($F$6:$F$19,$E$6:$E$19),0),""))+($F$20*ISNUMBER(MATCH('📋 Inventaire Complet'!$F$3:$F$517,{"D4R";"CEPH";"ISTI";"COLCOM";"HTMR"},0))))>0))*(LEN('📋 Inventaire Complet'!$D$3:$D$517)>0)*(((COUNTIF($H$6:$H$10,TRUE)=0)+(($H$6*ISNUMBER(SEARCH($G$6,'📋 Inventaire Complet'!$L$3:$L$517)))+($H$7*ISNUMBER(SEARCH($G$7,'📋 Inventaire Complet'!$L$3:$L$517)))+($H$8*ISNUMBER(SEARCH($G$8,'📋 Inventaire Complet'!$L$3:$L$517)))+($H$9*ISNUMBER(SEARCH($G$9,'📋 Inventaire Complet'!$L$3:$L$517)))+($H$10*ISNUMBER(SEARCH($G$10,'📋 Inventaire Complet'!$L$3:$L$517))))>0)))} -> 101 | C36: =IFERROR(B36/$B$40,0) -> 0.25831202 | E36: OCP / CERPHOS (historique) | F36: {=SUMPRODUCT(('📋 Inventaire Complet'!$F$3:$F$517=$E36)*(((COUNTIF($B$6:$B$10,TRUE)=0)+ISNUMBER(IFERROR(MATCH('📋 Inventaire Complet'!$B$3:$B$517,IF($B$6:$B$10,$A$6:$A$10),0),""))>0))*(((COUNTIF($D$6:$D$22,TRUE)=0)+ISNUMBER(IFERROR(MATCH(LEFT('📋 Inventaire Complet'!$J$3:$J$517,4),IF($D$6:$D$22,$C$6:$C$22&""),0),""))>0))*(LEN('📋 Inventaire Complet'!$D$3:$D$517)>0)*(((COUNTIF($H$6:$H$10,TRUE)=0)+(($H$6*ISNUMBER(SEARCH($G$6,'📋 Inventaire Complet'!$L$3:$L$517)))+($H$7*ISNUMBER(SEARCH($G$7,'📋 Inventaire Complet'!$L$3:$L$517)))+($H$8*ISNUMBER(SEARCH($G$8,'📋 Inventaire Complet'!$L$3:$L$517)))+($H$9*ISNUMBER(SEARCH($G$9,'📋 Inventaire Complet'!$L$3:$L$517)))+($H$10*ISNUMBER(SEARCH($G$10,'📋 Inventaire Complet'!$L$3:$L$517))))>0)))} -> 92 | G36: =IFERROR(F36/$F$50,0) -> 0.23409669 | I36: ✅ Délivré / Actif | J36: {=SUMPRODUCT((ISNUMBER(SEARCH("Délivré",'📋 Inventaire Complet'!$L$3:$L$517)))*(((COUNTIF($B$6:$B$10,TRUE)=0)+ISNUMBER(IFERROR(MATCH('📋 Inventaire Complet'!$B$3:$B$517,IF($B$6:$B$10,$A$6:$A$10),0),""))>0))*(((COUNTIF($D$6:$D$22,TRUE)=0)+ISNUMBER(IFERROR(MATCH(LEFT('📋 Inventaire Complet'!$J$3:$J$517,4),IF($D$6:$D$22,$C$6:$C$22&""),0),""))>0))*(((COUNTIF($F$6:$F$20,TRUE)=0)+(ISNUMBER(IFERROR(MATCH('📋 Inventaire Complet'!$F$3:$F$517,IF($F$6:$F$19,$E$6:$E$19),0),""))+($F$20*ISNUMBER(MATCH('📋 Inventaire Complet'!$F$3:$F$517,{"D4R";"CEPH";"ISTI";"COLCOM";"HTMR"},0))))>0))*(LEN('📋 Inventaire Complet'!$D$3:$D$517)>0))} -> 51 | K36: =IFERROR(J36/$A$28,0) -> 0.12977099 | T36: 2026 | U36: ISTI | V36: Purification/démétallisation de l’acide phosphorique | W36: {=SUMPRODUCT(('📋 Inventaire Complet'!$C$3:$C$517=$V36)*(((COUNTIF($B$6:$B$10,TRUE)=0)+ISNUMBER(IFERROR(MATCH('📋 Inventaire Complet'!$B$3:$B$517,IF($B$6:$B$10,$A$6:$A$10),0),""))>0))*(((COUNTIF($D$6:$D$22,TRUE)=0)+ISNUMBER(IFERROR(MATCH(LEFT('📋 Inventaire Complet'!$J$3:$J$517,4),IF($D$6:$D$22,$C$6:$C$22&""),0),""))>0))*(((COUNTIF($F$6:$F$20,TRUE)=0)+(ISNUMBER(IFERROR(MATCH('📋 Inventaire Complet'!$F$3:$F$517,IF($F$6:$F$19,$E$6:$E$19),0),""))+($F$20*ISNUMBER(MATCH('📋 Inventaire Complet'!$F$3:$F$517,{"D4R";"CEPH";"ISTI";"COLCOM";"HTMR"},0))))>0))*(LEN('📋 Inventaire Complet'!$D$3:$D$517)>0)*(((COUNTIF($H$6:$H$10,TRUE)=0)+(($H$6*ISNUMBER(SEARCH($G$6,'📋 Inventaire Complet'!$L$3:$L$517)))+($H$7*ISNUMBER(SEARCH($G$7,'📋 Inventaire Complet'!$L$3:$L$517)))+($H$8*ISNUMBER(SEARCH($G$8,'📋 Inventaire Complet'!$L$3:$L$517)))+($H$9*ISNUMBER(SEARCH($G$9,'📋 Inventaire Complet'!$L$3:$L$517)))+($H$10*ISNUMBER(SEARCH($G$10,'📋 Inventaire Complet'!$L$3:$L$517))))>0)))} -> 19 | X36: =W36+ROW()/10000 -> 19.0036 | Y36: BOUHFID RACHID QAISS ABOU EL KACEM | Z36: {=IF(Y36="",0,SUMPRODUCT(('📋 Inventaire Complet'!$E$3:$E$517=Y36)*((COUNTIF($B$6:$B$10,TRUE)=0)+ISNUMBER(IFERROR(MATCH('📋 Inventaire Complet'!$B$3:$B$517,IF($B$6:$B$10,$A$6:$A$10),0),""))>0)*((COUNTIF($D$6:$D$22,TRUE)=0)+ISNUMBER(IFERROR(MATCH(LEFT('📋 Inventaire Complet'!$J$3:$J$517,4),IF($D$6:$D$22,$C$6:$C$22&""),0),""))>0)*((COUNTIF($F$6:$F$20,TRUE)=0)+(ISNUMBER(IFERROR(MATCH('📋 Inventaire Complet'!$F$3:$F$517,IF($F$6:$F$19,$E$6:$E$19),0),""))+($F$20*ISNUMBER(MATCH('📋 Inventaire Complet'!$F$3:$F$517,{"D4R";"CEPH";"ISTI";"COLCOM";"HTMR"},0))))>0)*((COUNTIF($H$6:$H$10,TRUE)=0)+(($H$6*ISNUMBER(SEARCH($G$6,'📋 Inventaire Complet'!$L$3:$L$517)))+($H$7*ISNUMBER(SEARCH($G$7,'📋 Inventaire Complet'!$L$3:$L$517)))+($H$8*ISNUMBER(SEARCH($G$8,'📋 Inventaire Complet'!$L$3:$L$517)))+($H$9*ISNUMBER(SEARCH($G$9,'📋 Inventaire Complet'!$L$3:$L$517)))+($H$10*ISNUMBER(SEARCH($G$10,'📋 Inventaire Complet'!$L$3:$L$517))))>0)))} -> 5 | AA36: =IF(Y36="",0,Z36+ROW()/10000) -> 5.0036
A37: Circular Chemistry & Waste Valorization | B37: {=SUMPRODUCT(('📋 Inventaire Complet'!$B$3:$B$517=$A37)*(((COUNTIF($D$6:$D$22,TRUE)=0)+ISNUMBER(IFERROR(MATCH(LEFT('📋 Inventaire Complet'!$J$3:$J$517,4),IF($D$6:$D$22,$C$6:$C$22&""),0),""))>0))*(((COUNTIF($F$6:$F$20,TRUE)=0)+(ISNUMBER(IFERROR(MATCH('📋 Inventaire Complet'!$F$3:$F$517,IF($F$6:$F$19,$E$6:$E$19),0),""))+($F$20*ISNUMBER(MATCH('📋 Inventaire Complet'!$F$3:$F$517,{"D4R";"CEPH";"ISTI";"COLCOM";"HTMR"},0))))>0))*(LEN('📋 Inventaire Complet'!$D$3:$D$517)>0)*(((COUNTIF($H$6:$H$10,TRUE)=0)+(($H$6*ISNUMBER(SEARCH($G$6,'📋 Inventaire Complet'!$L$3:$L$517)))+($H$7*ISNUMBER(SEARCH($G$7,'📋 Inventaire Complet'!$L$3:$L$517)))+($H$8*ISNUMBER(SEARCH($G$8,'📋 Inventaire Complet'!$L$3:$L$517)))+($H$9*ISNUMBER(SEARCH($G$9,'📋 Inventaire Complet'!$L$3:$L$517)))+($H$10*ISNUMBER(SEARCH($G$10,'📋 Inventaire Complet'!$L$3:$L$517))))>0)))} -> 49 | C37: =IFERROR(B37/$B$40,0) -> 0.12531969 | E37: MSN | F37: {=SUMPRODUCT(('📋 Inventaire Complet'!$F$3:$F$517=$E37)*(((COUNTIF($B$6:$B$10,TRUE)=0)+ISNUMBER(IFERROR(MATCH('📋 Inventaire Complet'!$B$3:$B$517,IF($B$6:$B$10,$A$6:$A$10),0),""))>0))*(((COUNTIF($D$6:$D$22,TRUE)=0)+ISNUMBER(IFERROR(MATCH(LEFT('📋 Inventaire Complet'!$J$3:$J$517,4),IF($D$6:$D$22,$C$6:$C$22&""),0),""))>0))*(LEN('📋 Inventaire Complet'!$D$3:$D$517)>0)*(((COUNTIF($H$6:$H$10,TRUE)=0)+(($H$6*ISNUMBER(SEARCH($G$6,'📋 Inventaire Complet'!$L$3:$L$517)))+($H$7*ISNUMBER(SEARCH($G$7,'📋 Inventaire Complet'!$L$3:$L$517)))+($H$8*ISNUMBER(SEARCH($G$8,'📋 Inventaire Complet'!$L$3:$L$517)))+($H$9*ISNUMBER(SEARCH($G$9,'📋 Inventaire Complet'!$L$3:$L$517)))+($H$10*ISNUMBER(SEARCH($G$10,'📋 Inventaire Complet'!$L$3:$L$517))))>0)))} -> 32 | G37: =IFERROR(F37/$F$50,0) -> 0.081424936 | I37: 🟡 OMPIC – En cours / Publié | J37: {=SUMPRODUCT((ISNUMBER(SEARCH("OMPIC",'📋 Inventaire Complet'!$L$3:$L$517)))*(((COUNTIF($B$6:$B$10,TRUE)=0)+ISNUMBER(IFERROR(MATCH('📋 Inventaire Complet'!$B$3:$B$517,IF($B$6:$B$10,$A$6:$A$10),0),""))>0))*(((COUNTIF($D$6:$D$22,TRUE)=0)+ISNUMBER(IFERROR(MATCH(LEFT('📋 Inventaire Complet'!$J$3:$J$517,4),IF($D$6:$D$22,$C$6:$C$22&""),0),""))>0))*(((COUNTIF($F$6:$F$20,TRUE)=0)+(ISNUMBER(IFERROR(MATCH('📋 Inventaire Complet'!$F$3:$F$517,IF($F$6:$F$19,$E$6:$E$19),0),""))+($F$20*ISNUMBER(MATCH('📋 Inventaire Complet'!$F$3:$F$517,{"D4R";"CEPH";"ISTI";"COLCOM";"HTMR"},0))))>0))*(LEN('📋 Inventaire Complet'!$D$3:$D$517)>0))} -> 56 | K37: =IFERROR(J37/$A$28,0) -> 0.14249364 | U37: COLCOM | V37: Récupération terres rares, uranium & métaux critiques | W37: {=SUMPRODUCT(('📋 Inventaire Complet'!$C$3:$C$517=$V37)*(((COUNTIF($B$6:$B$10,TRUE)=0)+ISNUMBER(IFERROR(MATCH('📋 Inventaire Complet'!$B$3:$B$517,IF($B$6:$B$10,$A$6:$A$10),0),""))>0))*(((COUNTIF($D$6:$D$22,TRUE)=0)+ISNUMBER(IFERROR(MATCH(LEFT('📋 Inventaire Complet'!$J$3:$J$517,4),IF($D$6:$D$22,$C$6:$C$22&""),0),""))>0))*(((COUNTIF($F$6:$F$20,TRUE)=0)+(ISNUMBER(IFERROR(MATCH('📋 Inventaire Complet'!$F$3:$F$517,IF($F$6:$F$19,$E$6:$E$19),0),""))+($F$20*ISNUMBER(MATCH('📋 Inventaire Complet'!$F$3:$F$517,{"D4R";"CEPH";"ISTI";"COLCOM";"HTMR"},0))))>0))*(LEN('📋 Inventaire Complet'!$D$3:$D$517)>0)*(((COUNTIF($H$6:$H$10,TRUE)=0)+(($H$6*ISNUMBER(SEARCH($G$6,'📋 Inventaire Complet'!$L$3:$L$517)))+($H$7*ISNUMBER(SEARCH($G$7,'📋 Inventaire Complet'!$L$3:$L$517)))+($H$8*ISNUMBER(SEARCH($G$8,'📋 Inventaire Complet'!$L$3:$L$517)))+($H$9*ISNUMBER(SEARCH($G$9,'📋 Inventaire Complet'!$L$3:$L$517)))+($H$10*ISNUMBER(SEARCH($G$10,'📋 Inventaire Complet'!$L$3:$L$517))))>0)))} -> 17 | X37: =W37+ROW()/10000 -> 17.0037 | Y37: BENHIMA REDOUANE ELKADIB ABDELKRIM BOUHFID RACHID WAHBY IMANE MEFTAH KADMIRI ISSAM | Z37: {=IF(Y37="",0,SUMPRODUCT(('📋 Inventaire Complet'!$E$3:$E$517=Y37)*((COUNTIF($B$6:$B$10,TRUE)=0)+ISNUMBER(IFERROR(MATCH('📋 Inventaire Complet'!$B$3:$B$517,IF($B$6:$B$10,$A$6:$A$10),0),""))>0)*((COUNTIF($D$6:$D$22,TRUE)=0)+ISNUMBER(IFERROR(MATCH(LEFT('📋 Inventaire Complet'!$J$3:$J$517,4),IF($D$6:$D$22,$C$6:$C$22&""),0),""))>0)*((COUNTIF($F$6:$F$20,TRUE)=0)+(ISNUMBER(IFERROR(MATCH('📋 Inventaire Complet'!$F$3:$F$517,IF($F$6:$F$19,$E$6:$E$19),0),""))+($F$20*ISNUMBER(MATCH('📋 Inventaire Complet'!$F$3:$F$517,{"D4R";"CEPH";"ISTI";"COLCOM";"HTMR"},0))))>0)*((COUNTIF($H$6:$H$10,TRUE)=0)+(($H$6*ISNUMBER(SEARCH($G$6,'📋 Inventaire Complet'!$L$3:$L$517)))+($H$7*ISNUMBER(SEARCH($G$7,'📋 Inventaire Complet'!$L$3:$L$517)))+($H$8*ISNUMBER(SEARCH($G$8,'📋 Inventaire Complet'!$L$3:$L$517)))+($H$9*ISNUMBER(SEARCH($G$9,'📋 Inventaire Complet'!$L$3:$L$517)))+($H$10*ISNUMBER(SEARCH($G$10,'📋 Inventaire Complet'!$L$3:$L$517))))>0)))} -> 1 | AA37: =IF(Y37="",0,Z37+ROW()/10000) -> 1.0037
A38: Green Agriculture & Biotechnology | B38: {=SUMPRODUCT(('📋 Inventaire Complet'!$B$3:$B$517=$A38)*(((COUNTIF($D$6:$D$22,TRUE)=0)+ISNUMBER(IFERROR(MATCH(LEFT('📋 Inventaire Complet'!$J$3:$J$517,4),IF($D$6:$D$22,$C$6:$C$22&""),0),""))>0))*(((COUNTIF($F$6:$F$20,TRUE)=0)+(ISNUMBER(IFERROR(MATCH('📋 Inventaire Complet'!$F$3:$F$517,IF($F$6:$F$19,$E$6:$E$19),0),""))+($F$20*ISNUMBER(MATCH('📋 Inventaire Complet'!$F$3:$F$517,{"D4R";"CEPH";"ISTI";"COLCOM";"HTMR"},0))))>0))*(LEN('📋 Inventaire Complet'!$D$3:$D$517)>0)*(((COUNTIF($H$6:$H$10,TRUE)=0)+(($H$6*ISNUMBER(SEARCH($G$6,'📋 Inventaire Complet'!$L$3:$L$517)))+($H$7*ISNUMBER(SEARCH($G$7,'📋 Inventaire Complet'!$L$3:$L$517)))+($H$8*ISNUMBER(SEARCH($G$8,'📋 Inventaire Complet'!$L$3:$L$517)))+($H$9*ISNUMBER(SEARCH($G$9,'📋 Inventaire Complet'!$L$3:$L$517)))+($H$10*ISNUMBER(SEARCH($G$10,'📋 Inventaire Complet'!$L$3:$L$517))))>0)))} -> 51 | C38: =IFERROR(B38/$B$40,0) -> 0.13043478 | E38: CERPHOS (historique) | F38: {=SUMPRODUCT(('📋 Inventaire Complet'!$F$3:$F$517=$E38)*(((COUNTIF($B$6:$B$10,TRUE)=0)+ISNUMBER(IFERROR(MATCH('📋 Inventaire Complet'!$B$3:$B$517,IF($B$6:$B$10,$A$6:$A$10),0),""))>0))*(((COUNTIF($D$6:$D$22,TRUE)=0)+ISNUMBER(IFERROR(MATCH(LEFT('📋 Inventaire Complet'!$J$3:$J$517,4),IF($D$6:$D$22,$C$6:$C$22&""),0),""))>0))*(LEN('📋 Inventaire Complet'!$D$3:$D$517)>0)*(((COUNTIF($H$6:$H$10,TRUE)=0)+(($H$6*ISNUMBER(SEARCH($G$6,'📋 Inventaire Complet'!$L$3:$L$517)))+($H$7*ISNUMBER(SEARCH($G$7,'📋 Inventaire Complet'!$L$3:$L$517)))+($H$8*ISNUMBER(SEARCH($G$8,'📋 Inventaire Complet'!$L$3:$L$517)))+($H$9*ISNUMBER(SEARCH($G$9,'📋 Inventaire Complet'!$L$3:$L$517)))+($H$10*ISNUMBER(SEARCH($G$10,'📋 Inventaire Complet'!$L$3:$L$517))))>0)))} -> 24 | G38: =IFERROR(F38/$F$50,0) -> 0.061068702 | I38: 🔴 Abandonné / Inactif | J38: {=SUMPRODUCT((ISNUMBER(SEARCH("Abandonné",'📋 Inventaire Complet'!$L$3:$L$517)))*(((COUNTIF($B$6:$B$10,TRUE)=0)+ISNUMBER(IFERROR(MATCH('📋 Inventaire Complet'!$B$3:$B$517,IF($B$6:$B$10,$A$6:$A$10),0),""))>0))*(((COUNTIF($D$6:$D$22,TRUE)=0)+ISNUMBER(IFERROR(MATCH(LEFT('📋 Inventaire Complet'!$J$3:$J$517,4),IF($D$6:$D$22,$C$6:$C$22&""),0),""))>0))*(((COUNTIF($F$6:$F$20,TRUE)=0)+(ISNUMBER(IFERROR(MATCH('📋 Inventaire Complet'!$F$3:$F$517,IF($F$6:$F$19,$E$6:$E$19),0),""))+($F$20*ISNUMBER(MATCH('📋 Inventaire Complet'!$F$3:$F$517,{"D4R";"CEPH";"ISTI";"COLCOM";"HTMR"},0))))>0))*(LEN('📋 Inventaire Complet'!$D$3:$D$517)>0))} -> 44 | K38: =IFERROR(J38/$A$28,0) -> 0.11195929 | U38: HTMR | V38: Équipements miniers, échantillonnage & séparation solide-liquide | W38: {=SUMPRODUCT(('📋 Inventaire Complet'!$C$3:$C$517=$V38)*(((COUNTIF($B$6:$B$10,TRUE)=0)+ISNUMBER(IFERROR(MATCH('📋 Inventaire Complet'!$B$3:$B$517,IF($B$6:$B$10,$A$6:$A$10),0),""))>0))*(((COUNTIF($D$6:$D$22,TRUE)=0)+ISNUMBER(IFERROR(MATCH(LEFT('📋 Inventaire Complet'!$J$3:$J$517,4),IF($D$6:$D$22,$C$6:$C$22&""),0),""))>0))*(((COUNTIF($F$6:$F$20,TRUE)=0)+(ISNUMBER(IFERROR(MATCH('📋 Inventaire Complet'!$F$3:$F$517,IF($F$6:$F$19,$E$6:$E$19),0),""))+($F$20*ISNUMBER(MATCH('📋 Inventaire Complet'!$F$3:$F$517,{"D4R";"CEPH";"ISTI";"COLCOM";"HTMR"},0))))>0))*(LEN('📋 Inventaire Complet'!$D$3:$D$517)>0)*(((COUNTIF($H$6:$H$10,TRUE)=0)+(($H$6*ISNUMBER(SEARCH($G$6,'📋 Inventaire Complet'!$L$3:$L$517)))+($H$7*ISNUMBER(SEARCH($G$7,'📋 Inventaire Complet'!$L$3:$L$517)))+($H$8*ISNUMBER(SEARCH($G$8,'📋 Inventaire Complet'!$L$3:$L$517)))+($H$9*ISNUMBER(SEARCH($G$9,'📋 Inventaire Complet'!$L$3:$L$517)))+($H$10*ISNUMBER(SEARCH($G$10,'📋 Inventaire Complet'!$L$3:$L$517))))>0)))} -> 4 | X38: =W38+ROW()/10000 -> 4.0038 | Y38: ESSAMLALI YOUNES; AMADINE OTHMANE; ZAHOUILY MOHAMED; DARDARI OTHMANE; SAIR SAID | Z38: {=IF(Y38="",0,SUMPRODUCT(('📋 Inventaire Complet'!$E$3:$E$517=Y38)*((COUNTIF($B$6:$B$10,TRUE)=0)+ISNUMBER(IFERROR(MATCH('📋 Inventaire Complet'!$B$3:$B$517,IF($B$6:$B$10,$A$6:$A$10),0),""))>0)*((COUNTIF($D$6:$D$22,TRUE)=0)+ISNUMBER(IFERROR(MATCH(LEFT('📋 Inventaire Complet'!$J$3:$J$517,4),IF($D$6:$D$22,$C$6:$C$22&""),0),""))>0)*((COUNTIF($F$6:$F$20,TRUE)=0)+(ISNUMBER(IFERROR(MATCH('📋 Inventaire Complet'!$F$3:$F$517,IF($F$6:$F$19,$E$6:$E$19),0),""))+($F$20*ISNUMBER(MATCH('📋 Inventaire Complet'!$F$3:$F$517,{"D4R";"CEPH";"ISTI";"COLCOM";"HTMR"},0))))>0)*((COUNTIF($H$6:$H$10,TRUE)=0)+(($H$6*ISNUMBER(SEARCH($G$6,'📋 Inventaire Complet'!$L$3:$L$517)))+($H$7*ISNUMBER(SEARCH($G$7,'📋 Inventaire Complet'!$L$3:$L$517)))+($H$8*ISNUMBER(SEARCH($G$8,'📋 Inventaire Complet'!$L$3:$L$517)))+($H$9*ISNUMBER(SEARCH($G$9,'📋 Inventaire Complet'!$L$3:$L$517)))+($H$10*ISNUMBER(SEARCH($G$10,'📋 Inventaire Complet'!$L$3:$L$517))))>0)))} -> 1 | AA38: =IF(Y38="",0,Z38+ROW()/10000) -> 1.0038
A39: Sustainable Energy Storage & Management | B39: {=SUMPRODUCT(('📋 Inventaire Complet'!$B$3:$B$517=$A39)*(((COUNTIF($D$6:$D$22,TRUE)=0)+ISNUMBER(IFERROR(MATCH(LEFT('📋 Inventaire Complet'!$J$3:$J$517,4),IF($D$6:$D$22,$C$6:$C$22&""),0),""))>0))*(((COUNTIF($F$6:$F$20,TRUE)=0)+(ISNUMBER(IFERROR(MATCH('📋 Inventaire Complet'!$F$3:$F$517,IF($F$6:$F$19,$E$6:$E$19),0),""))+($F$20*ISNUMBER(MATCH('📋 Inventaire Complet'!$F$3:$F$517,{"D4R";"CEPH";"ISTI";"COLCOM";"HTMR"},0))))>0))*(LEN('📋 Inventaire Complet'!$D$3:$D$517)>0)*(((COUNTIF($H$6:$H$10,TRUE)=0)+(($H$6*ISNUMBER(SEARCH($G$6,'📋 Inventaire Complet'!$L$3:$L$517)))+($H$7*ISNUMBER(SEARCH($G$7,'📋 Inventaire Complet'!$L$3:$L$517)))+($H$8*ISNUMBER(SEARCH($G$8,'📋 Inventaire Complet'!$L$3:$L$517)))+($H$9*ISNUMBER(SEARCH($G$9,'📋 Inventaire Complet'!$L$3:$L$517)))+($H$10*ISNUMBER(SEARCH($G$10,'📋 Inventaire Complet'!$L$3:$L$517))))>0)))} -> 29 | C39: =IFERROR(B39/$B$40,0) -> 0.074168798 | E39: ACER CoE | F39: {=SUMPRODUCT(('📋 Inventaire Complet'!$F$3:$F$517=$E39)*(((COUNTIF($B$6:$B$10,TRUE)=0)+ISNUMBER(IFERROR(MATCH('📋 Inventaire Complet'!$B$3:$B$517,IF($B$6:$B$10,$A$6:$A$10),0),""))>0))*(((COUNTIF($D$6:$D$22,TRUE)=0)+ISNUMBER(IFERROR(MATCH(LEFT('📋 Inventaire Complet'!$J$3:$J$517,4),IF($D$6:$D$22,$C$6:$C$22&""),0),""))>0))*(LEN('📋 Inventaire Complet'!$D$3:$D$517)>0)*(((COUNTIF($H$6:$H$10,TRUE)=0)+(($H$6*ISNUMBER(SEARCH($G$6,'📋 Inventaire Complet'!$L$3:$L$517)))+($H$7*ISNUMBER(SEARCH($G$7,'📋 Inventaire Complet'!$L$3:$L$517)))+($H$8*ISNUMBER(SEARCH($G$8,'📋 Inventaire Complet'!$L$3:$L$517)))+($H$9*ISNUMBER(SEARCH($G$9,'📋 Inventaire Complet'!$L$3:$L$517)))+($H$10*ISNUMBER(SEARCH($G$10,'📋 Inventaire Complet'!$L$3:$L$517))))>0)))} -> 11 | G39: =IFERROR(F39/$F$50,0) -> 0.027989822 | I39: 🌐 PCT international | J39: {=SUMPRODUCT((ISNUMBER(SEARCH("PCT",'📋 Inventaire Complet'!$L$3:$L$517)))*(((COUNTIF($B$6:$B$10,TRUE)=0)+ISNUMBER(IFERROR(MATCH('📋 Inventaire Complet'!$B$3:$B$517,IF($B$6:$B$10,$A$6:$A$10),0),""))>0))*(((COUNTIF($D$6:$D$22,TRUE)=0)+ISNUMBER(IFERROR(MATCH(LEFT('📋 Inventaire Complet'!$J$3:$J$517,4),IF($D$6:$D$22,$C$6:$C$22&""),0),""))>0))*(((COUNTIF($F$6:$F$20,TRUE)=0)+(ISNUMBER(IFERROR(MATCH('📋 Inventaire Complet'!$F$3:$F$517,IF($F$6:$F$19,$E$6:$E$19),0),""))+($F$20*ISNUMBER(MATCH('📋 Inventaire Complet'!$F$3:$F$517,{"D4R";"CEPH";"ISTI";"COLCOM";"HTMR"},0))))>0))*(LEN('📋 Inventaire Complet'!$D$3:$D$517)>0))} -> 26 | K39: =IFERROR(J39/$A$28,0) -> 0.066157761 | V39: Biomasse, biopolymères & matériaux biosourcés | W39: {=SUMPRODUCT(('📋 Inventaire Complet'!$C$3:$C$517=$V39)*(((COUNTIF($B$6:$B$10,TRUE)=0)+ISNUMBER(IFERROR(MATCH('📋 Inventaire Complet'!$B$3:$B$517,IF($B$6:$B$10,$A$6:$A$10),0),""))>0))*(((COUNTIF($D$6:$D$22,TRUE)=0)+ISNUMBER(IFERROR(MATCH(LEFT('📋 Inventaire Complet'!$J$3:$J$517,4),IF($D$6:$D$22,$C$6:$C$22&""),0),""))>0))*(((COUNTIF($F$6:$F$20,TRUE)=0)+(ISNUMBER(IFERROR(MATCH('📋 Inventaire Complet'!$F$3:$F$517,IF($F$6:$F$19,$E$6:$E$19),0),""))+($F$20*ISNUMBER(MATCH('📋 Inventaire Complet'!$F$3:$F$517,{"D4R";"CEPH";"ISTI";"COLCOM";"HTMR"},0))))>0))*(LEN('📋 Inventaire Complet'!$D$3:$D$517)>0)*(((COUNTIF($H$6:$H$10,TRUE)=0)+(($H$6*ISNUMBER(SEARCH($G$6,'📋 Inventaire Complet'!$L$3:$L$517)))+($H$7*ISNUMBER(SEARCH($G$7,'📋 Inventaire Complet'!$L$3:$L$517)))+($H$8*ISNUMBER(SEARCH($G$8,'📋 Inventaire Complet'!$L$3:$L$517)))+($H$9*ISNUMBER(SEARCH($G$9,'📋 Inventaire Complet'!$L$3:$L$517)))+($H$10*ISNUMBER(SEARCH($G$10,'📋 Inventaire Complet'!$L$3:$L$517))))>0)))} -> 13 | X39: =W39+ROW()/10000 -> 13.0039 | Y39: BRICHE SAMIR; AGZENAI BEN SALEM YAHYA | Z39: {=IF(Y39="",0,SUMPRODUCT(('📋 Inventaire Complet'!$E$3:$E$517=Y39)*((COUNTIF($B$6:$B$10,TRUE)=0)+ISNUMBER(IFERROR(MATCH('📋 Inventaire Complet'!$B$3:$B$517,IF($B$6:$B$10,$A$6:$A$10),0),""))>0)*((COUNTIF($D$6:$D$22,TRUE)=0)+ISNUMBER(IFERROR(MATCH(LEFT('📋 Inventaire Complet'!$J$3:$J$517,4),IF($D$6:$D$22,$C$6:$C$22&""),0),""))>0)*((COUNTIF($F$6:$F$20,TRUE)=0)+(ISNUMBER(IFERROR(MATCH('📋 Inventaire Complet'!$F$3:$F$517,IF($F$6:$F$19,$E$6:$E$19),0),""))+($F$20*ISNUMBER(MATCH('📋 Inventaire Complet'!$F$3:$F$517,{"D4R";"CEPH";"ISTI";"COLCOM";"HTMR"},0))))>0)*((COUNTIF($H$6:$H$10,TRUE)=0)+(($H$6*ISNUMBER(SEARCH($G$6,'📋 Inventaire Complet'!$L$3:$L$517)))+($H$7*ISNUMBER(SEARCH($G$7,'📋 Inventaire Complet'!$L$3:$L$517)))+($H$8*ISNUMBER(SEARCH($G$8,'📋 Inventaire Complet'!$L$3:$L$517)))+($H$9*ISNUMBER(SEARCH($G$9,'📋 Inventaire Complet'!$L$3:$L$517)))+($H$10*ISNUMBER(SEARCH($G$10,'📋 Inventaire Complet'!$L$3:$L$517))))>0)))} -> 1 | AA39: =IF(Y39="",0,Z39+ROW()/10000) -> 1.0039
A40: TOTAL | B40: =SUM(B35:B39) -> 391 | C40: =SUM(C35:C39) -> 1 | E40: CBS | F40: {=SUMPRODUCT(('📋 Inventaire Complet'!$F$3:$F$517=$E40)*(((COUNTIF($B$6:$B$10,TRUE)=0)+ISNUMBER(IFERROR(MATCH('📋 Inventaire Complet'!$B$3:$B$517,IF($B$6:$B$10,$A$6:$A$10),0),""))>0))*(((COUNTIF($D$6:$D$22,TRUE)=0)+ISNUMBER(IFERROR(MATCH(LEFT('📋 Inventaire Complet'!$J$3:$J$517,4),IF($D$6:$D$22,$C$6:$C$22&""),0),""))>0))*(LEN('📋 Inventaire Complet'!$D$3:$D$517)>0)*(((COUNTIF($H$6:$H$10,TRUE)=0)+(($H$6*ISNUMBER(SEARCH($G$6,'📋 Inventaire Complet'!$L$3:$L$517)))+($H$7*ISNUMBER(SEARCH($G$7,'📋 Inventaire Complet'!$L$3:$L$517)))+($H$8*ISNUMBER(SEARCH($G$8,'📋 Inventaire Complet'!$L$3:$L$517)))+($H$9*ISNUMBER(SEARCH($G$9,'📋 Inventaire Complet'!$L$3:$L$517)))+($H$10*ISNUMBER(SEARCH($G$10,'📋 Inventaire Complet'!$L$3:$L$517))))>0)))} -> 7 | G40: =IFERROR(F40/$F$50,0) -> 0.017811705 | I40: ⚫ Expiré | J40: {=SUMPRODUCT((ISNUMBER(SEARCH("Expiré",'📋 Inventaire Complet'!$L$3:$L$517)))*(((COUNTIF($B$6:$B$10,TRUE)=0)+ISNUMBER(IFERROR(MATCH('📋 Inventaire Complet'!$B$3:$B$517,IF($B$6:$B$10,$A$6:$A$10),0),""))>0))*(((COUNTIF($D$6:$D$22,TRUE)=0)+ISNUMBER(IFERROR(MATCH(LEFT('📋 Inventaire Complet'!$J$3:$J$517,4),IF($D$6:$D$22,$C$6:$C$22&""),0),""))>0))*(((COUNTIF($F$6:$F$20,TRUE)=0)+(ISNUMBER(IFERROR(MATCH('📋 Inventaire Complet'!$F$3:$F$517,IF($F$6:$F$19,$E$6:$E$19),0),""))+($F$20*ISNUMBER(MATCH('📋 Inventaire Complet'!$F$3:$F$517,{"D4R";"CEPH";"ISTI";"COLCOM";"HTMR"},0))))>0))*(LEN('📋 Inventaire Complet'!$D$3:$D$517)>0))} -> 13 | K40: =IFERROR(J40/$A$28,0) -> 0.03307888 | V40: Bioénergie, pyrolyse & carbones | W40: {=SUMPRODUCT(('📋 Inventaire Complet'!$C$3:$C$517=$V40)*(((COUNTIF($B$6:$B$10,TRUE)=0)+ISNUMBER(IFERROR(MATCH('📋 Inventaire Complet'!$B$3:$B$517,IF($B$6:$B$10,$A$6:$A$10),0),""))>0))*(((COUNTIF($D$6:$D$22,TRUE)=0)+ISNUMBER(IFERROR(MATCH(LEFT('📋 Inventaire Complet'!$J$3:$J$517,4),IF($D$6:$D$22,$C$6:$C$22&""),0),""))>0))*(((COUNTIF($F$6:$F$20,TRUE)=0)+(ISNUMBER(IFERROR(MATCH('📋 Inventaire Complet'!$F$3:$F$517,IF($F$6:$F$19,$E$6:$E$19),0),""))+($F$20*ISNUMBER(MATCH('📋 Inventaire Complet'!$F$3:$F$517,{"D4R";"CEPH";"ISTI";"COLCOM";"HTMR"},0))))>0))*(LEN('📋 Inventaire Complet'!$D$3:$D$517)>0)*(((COUNTIF($H$6:$H$10,TRUE)=0)+(($H$6*ISNUMBER(SEARCH($G$6,'📋 Inventaire Complet'!$L$3:$L$517)))+($H$7*ISNUMBER(SEARCH($G$7,'📋 Inventaire Complet'!$L$3:$L$517)))+($H$8*ISNUMBER(SEARCH($G$8,'📋 Inventaire Complet'!$L$3:$L$517)))+($H$9*ISNUMBER(SEARCH($G$9,'📋 Inventaire Complet'!$L$3:$L$517)))+($H$10*ISNUMBER(SEARCH($G$10,'📋 Inventaire Complet'!$L$3:$L$517))))>0)))} -> 2 | X40: =W40+ROW()/10000 -> 2.004 | Y40: Fardioui, Qaiss, Bouhfid | Z40: {=IF(Y40="",0,SUMPRODUCT(('📋 Inventaire Complet'!$E$3:$E$517=Y40)*((COUNTIF($B$6:$B$10,TRUE)=0)+ISNUMBER(IFERROR(MATCH('📋 Inventaire Complet'!$B$3:$B$517,IF($B$6:$B$10,$A$6:$A$10),0),""))>0)*((COUNTIF($D$6:$D$22,TRUE)=0)+ISNUMBER(IFERROR(MATCH(LEFT('📋 Inventaire Complet'!$J$3:$J$517,4),IF($D$6:$D$22,$C$6:$C$22&""),0),""))>0)*((COUNTIF($F$6:$F$20,TRUE)=0)+(ISNUMBER(IFERROR(MATCH('📋 Inventaire Complet'!$F$3:$F$517,IF($F$6:$F$19,$E$6:$E$19),0),""))+($F$20*ISNUMBER(MATCH('📋 Inventaire Complet'!$F$3:$F$517,{"D4R";"CEPH";"ISTI";"COLCOM";"HTMR"},0))))>0)*((COUNTIF($H$6:$H$10,TRUE)=0)+(($H$6*ISNUMBER(SEARCH($G$6,'📋 Inventaire Complet'!$L$3:$L$517)))+($H$7*ISNUMBER(SEARCH($G$7,'📋 Inventaire Complet'!$L$3:$L$517)))+($H$8*ISNUMBER(SEARCH($G$8,'📋 Inventaire Complet'!$L$3:$L$517)))+($H$9*ISNUMBER(SEARCH($G$9,'📋 Inventaire Complet'!$L$3:$L$517)))+($H$10*ISNUMBER(SEARCH($G$10,'📋 Inventaire Complet'!$L$3:$L$517))))>0)))} -> 1 | AA40: =IF(Y40="",0,Z40+ROW()/10000) -> 1.004
E41: ASARI | F41: {=SUMPRODUCT(('📋 Inventaire Complet'!$F$3:$F$517=$E41)*(((COUNTIF($B$6:$B$10,TRUE)=0)+ISNUMBER(IFERROR(MATCH('📋 Inventaire Complet'!$B$3:$B$517,IF($B$6:$B$10,$A$6:$A$10),0),""))>0))*(((COUNTIF($D$6:$D$22,TRUE)=0)+ISNUMBER(IFERROR(MATCH(LEFT('📋 Inventaire Complet'!$J$3:$J$517,4),IF($D$6:$D$22,$C$6:$C$22&""),0),""))>0))*(LEN('📋 Inventaire Complet'!$D$3:$D$517)>0)*(((COUNTIF($H$6:$H$10,TRUE)=0)+(($H$6*ISNUMBER(SEARCH($G$6,'📋 Inventaire Complet'!$L$3:$L$517)))+($H$7*ISNUMBER(SEARCH($G$7,'📋 Inventaire Complet'!$L$3:$L$517)))+($H$8*ISNUMBER(SEARCH($G$8,'📋 Inventaire Complet'!$L$3:$L$517)))+($H$9*ISNUMBER(SEARCH($G$9,'📋 Inventaire Complet'!$L$3:$L$517)))+($H$10*ISNUMBER(SEARCH($G$10,'📋 Inventaire Complet'!$L$3:$L$517))))>0)))} -> 7 | G41: =IFERROR(F41/$F$50,0) -> 0.017811705 | I41: ⚪ Non renseigné | J41: {=SUMPRODUCT((ISNUMBER(SEARCH("Non renseigné",'📋 Inventaire Complet'!$L$3:$L$517)))*(((COUNTIF($B$6:$B$10,TRUE)=0)+ISNUMBER(IFERROR(MATCH('📋 Inventaire Complet'!$B$3:$B$517,IF($B$6:$B$10,$A$6:$A$10),0),""))>0))*(((COUNTIF($D$6:$D$22,TRUE)=0)+ISNUMBER(IFERROR(MATCH(LEFT('📋 Inventaire Complet'!$J$3:$J$517,4),IF($D$6:$D$22,$C$6:$C$22&""),0),""))>0))*(((COUNTIF($F$6:$F$20,TRUE)=0)+(ISNUMBER(IFERROR(MATCH('📋 Inventaire Complet'!$F$3:$F$517,IF($F$6:$F$19,$E$6:$E$19),0),""))+($F$20*ISNUMBER(MATCH('📋 Inventaire Complet'!$F$3:$F$517,{"D4R";"CEPH";"ISTI";"COLCOM";"HTMR"},0))))>0))*(LEN('📋 Inventaire Complet'!$D$3:$D$517)>0))} -> 70 | K41: =IFERROR(J41/$A$28,0) -> 0.17811705 | V41: Composites recyclés, plastiques & pneus | W41: {=SUMPRODUCT(('📋 Inventaire Complet'!$C$3:$C$517=$V41)*(((COUNTIF($B$6:$B$10,TRUE)=0)+ISNUMBER(IFERROR(MATCH('📋 Inventaire Complet'!$B$3:$B$517,IF($B$6:$B$10,$A$6:$A$10),0),""))>0))*(((COUNTIF($D$6:$D$22,TRUE)=0)+ISNUMBER(IFERROR(MATCH(LEFT('📋 Inventaire Complet'!$J$3:$J$517,4),IF($D$6:$D$22,$C$6:$C$22&""),0),""))>0))*(((COUNTIF($F$6:$F$20,TRUE)=0)+(ISNUMBER(IFERROR(MATCH('📋 Inventaire Complet'!$F$3:$F$517,IF($F$6:$F$19,$E$6:$E$19),0),""))+($F$20*ISNUMBER(MATCH('📋 Inventaire Complet'!$F$3:$F$517,{"D4R";"CEPH";"ISTI";"COLCOM";"HTMR"},0))))>0))*(LEN('📋 Inventaire Complet'!$D$3:$D$517)>0)*(((COUNTIF($H$6:$H$10,TRUE)=0)+(($H$6*ISNUMBER(SEARCH($G$6,'📋 Inventaire Complet'!$L$3:$L$517)))+($H$7*ISNUMBER(SEARCH($G$7,'📋 Inventaire Complet'!$L$3:$L$517)))+($H$8*ISNUMBER(SEARCH($G$8,'📋 Inventaire Complet'!$L$3:$L$517)))+($H$9*ISNUMBER(SEARCH($G$9,'📋 Inventaire Complet'!$L$3:$L$517)))+($H$10*ISNUMBER(SEARCH($G$10,'📋 Inventaire Complet'!$L$3:$L$517))))>0)))} -> 7 | X41: =W41+ROW()/10000 -> 7.0041 | Y41: BELAICHE, BRICHE, REDOUANY, MOUHIB | Z41: {=IF(Y41="",0,SUMPRODUCT(('📋 Inventaire Complet'!$E$3:$E$517=Y41)*((COUNTIF($B$6:$B$10,TRUE)=0)+ISNUMBER(IFERROR(MATCH('📋 Inventaire Complet'!$B$3:$B$517,IF($B$6:$B$10,$A$6:$A$10),0),""))>0)*((COUNTIF($D$6:$D$22,TRUE)=0)+ISNUMBER(IFERROR(MATCH(LEFT('📋 Inventaire Complet'!$J$3:$J$517,4),IF($D$6:$D$22,$C$6:$C$22&""),0),""))>0)*((COUNTIF($F$6:$F$20,TRUE)=0)+(ISNUMBER(IFERROR(MATCH('📋 Inventaire Complet'!$F$3:$F$517,IF($F$6:$F$19,$E$6:$E$19),0),""))+($F$20*ISNUMBER(MATCH('📋 Inventaire Complet'!$F$3:$F$517,{"D4R";"CEPH";"ISTI";"COLCOM";"HTMR"},0))))>0)*((COUNTIF($H$6:$H$10,TRUE)=0)+(($H$6*ISNUMBER(SEARCH($G$6,'📋 Inventaire Complet'!$L$3:$L$517)))+($H$7*ISNUMBER(SEARCH($G$7,'📋 Inventaire Complet'!$L$3:$L$517)))+($H$8*ISNUMBER(SEARCH($G$8,'📋 Inventaire Complet'!$L$3:$L$517)))+($H$9*ISNUMBER(SEARCH($G$9,'📋 Inventaire Complet'!$L$3:$L$517)))+($H$10*ISNUMBER(SEARCH($G$10,'📋 Inventaire Complet'!$L$3:$L$517))))>0)))} -> 6 | AA41: =IF(Y41="",0,Z41+ROW()/10000) -> 6.0041
E42: GTI | F42: {=SUMPRODUCT(('📋 Inventaire Complet'!$F$3:$F$517=$E42)*(((COUNTIF($B$6:$B$10,TRUE)=0)+ISNUMBER(IFERROR(MATCH('📋 Inventaire Complet'!$B$3:$B$517,IF($B$6:$B$10,$A$6:$A$10),0),""))>0))*(((COUNTIF($D$6:$D$22,TRUE)=0)+ISNUMBER(IFERROR(MATCH(LEFT('📋 Inventaire Complet'!$J$3:$J$517,4),IF($D$6:$D$22,$C$6:$C$22&""),0),""))>0))*(LEN('📋 Inventaire Complet'!$D$3:$D$517)>0)*(((COUNTIF($H$6:$H$10,TRUE)=0)+(($H$6*ISNUMBER(SEARCH($G$6,'📋 Inventaire Complet'!$L$3:$L$517)))+($H$7*ISNUMBER(SEARCH($G$7,'📋 Inventaire Complet'!$L$3:$L$517)))+($H$8*ISNUMBER(SEARCH($G$8,'📋 Inventaire Complet'!$L$3:$L$517)))+($H$9*ISNUMBER(SEARCH($G$9,'📋 Inventaire Complet'!$L$3:$L$517)))+($H$10*ISNUMBER(SEARCH($G$10,'📋 Inventaire Complet'!$L$3:$L$517))))>0)))} -> 4 | G42: =IFERROR(F42/$F$50,0) -> 0.010178117 | I42: Autres (Rejeté / Examen / À vérifier) | J42: =A28-SUM(J35:J41) -> 12 | K42: =IFERROR(J42/$A$28,0) -> 0.030534351 | V42: Dépollution, eau & procédés environnementaux | W42: {=SUMPRODUCT(('📋 Inventaire Complet'!$C$3:$C$517=$V42)*(((COUNTIF($B$6:$B$10,TRUE)=0)+ISNUMBER(IFERROR(MATCH('📋 Inventaire Complet'!$B$3:$B$517,IF($B$6:$B$10,$A$6:$A$10),0),""))>0))*(((COUNTIF($D$6:$D$22,TRUE)=0)+ISNUMBER(IFERROR(MATCH(LEFT('📋 Inventaire Complet'!$J$3:$J$517,4),IF($D$6:$D$22,$C$6:$C$22&""),0),""))>0))*(((COUNTIF($F$6:$F$20,TRUE)=0)+(ISNUMBER(IFERROR(MATCH('📋 Inventaire Complet'!$F$3:$F$517,IF($F$6:$F$19,$E$6:$E$19),0),""))+($F$20*ISNUMBER(MATCH('📋 Inventaire Complet'!$F$3:$F$517,{"D4R";"CEPH";"ISTI";"COLCOM";"HTMR"},0))))>0))*(LEN('📋 Inventaire Complet'!$D$3:$D$517)>0)*(((COUNTIF($H$6:$H$10,TRUE)=0)+(($H$6*ISNUMBER(SEARCH($G$6,'📋 Inventaire Complet'!$L$3:$L$517)))+($H$7*ISNUMBER(SEARCH($G$7,'📋 Inventaire Complet'!$L$3:$L$517)))+($H$8*ISNUMBER(SEARCH($G$8,'📋 Inventaire Complet'!$L$3:$L$517)))+($H$9*ISNUMBER(SEARCH($G$9,'📋 Inventaire Complet'!$L$3:$L$517)))+($H$10*ISNUMBER(SEARCH($G$10,'📋 Inventaire Complet'!$L$3:$L$517))))>0)))} -> 3 | X42: =W42+ROW()/10000 -> 3.0042 | Y42: ELMOUSSAOUI,MOUNKACHI, BENALI, ELMAALAM, HAMEDOUN, BENYOUSSEF | Z42: {=IF(Y42="",0,SUMPRODUCT(('📋 Inventaire Complet'!$E$3:$E$517=Y42)*((COUNTIF($B$6:$B$10,TRUE)=0)+ISNUMBER(IFERROR(MATCH('📋 Inventaire Complet'!$B$3:$B$517,IF($B$6:$B$10,$A$6:$A$10),0),""))>0)*((COUNTIF($D$6:$D$22,TRUE)=0)+ISNUMBER(IFERROR(MATCH(LEFT('📋 Inventaire Complet'!$J$3:$J$517,4),IF($D$6:$D$22,$C$6:$C$22&""),0),""))>0)*((COUNTIF($F$6:$F$20,TRUE)=0)+(ISNUMBER(IFERROR(MATCH('📋 Inventaire Complet'!$F$3:$F$517,IF($F$6:$F$19,$E$6:$E$19),0),""))+($F$20*ISNUMBER(MATCH('📋 Inventaire Complet'!$F$3:$F$517,{"D4R";"CEPH";"ISTI";"COLCOM";"HTMR"},0))))>0)*((COUNTIF($H$6:$H$10,TRUE)=0)+(($H$6*ISNUMBER(SEARCH($G$6,'📋 Inventaire Complet'!$L$3:$L$517)))+($H$7*ISNUMBER(SEARCH($G$7,'📋 Inventaire Complet'!$L$3:$L$517)))+($H$8*ISNUMBER(SEARCH($G$8,'📋 Inventaire Complet'!$L$3:$L$517)))+($H$9*ISNUMBER(SEARCH($G$9,'📋 Inventaire Complet'!$L$3:$L$517)))+($H$10*ISNUMBER(SEARCH($G$10,'📋 Inventaire Complet'!$L$3:$L$517))))>0)))} -> 1 | AA42: =IF(Y42="",0,Z42+ROW()/10000) -> 1.0042
E43: GSMI | F43: {=SUMPRODUCT(('📋 Inventaire Complet'!$F$3:$F$517=$E43)*(((COUNTIF($B$6:$B$10,TRUE)=0)+ISNUMBER(IFERROR(MATCH('📋 Inventaire Complet'!$B$3:$B$517,IF($B$6:$B$10,$A$6:$A$10),0),""))>0))*(((COUNTIF($D$6:$D$22,TRUE)=0)+ISNUMBER(IFERROR(MATCH(LEFT('📋 Inventaire Complet'!$J$3:$J$517,4),IF($D$6:$D$22,$C$6:$C$22&""),0),""))>0))*(LEN('📋 Inventaire Complet'!$D$3:$D$517)>0)*(((COUNTIF($H$6:$H$10,TRUE)=0)+(($H$6*ISNUMBER(SEARCH($G$6,'📋 Inventaire Complet'!$L$3:$L$517)))+($H$7*ISNUMBER(SEARCH($G$7,'📋 Inventaire Complet'!$L$3:$L$517)))+($H$8*ISNUMBER(SEARCH($G$8,'📋 Inventaire Complet'!$L$3:$L$517)))+($H$9*ISNUMBER(SEARCH($G$9,'📋 Inventaire Complet'!$L$3:$L$517)))+($H$10*ISNUMBER(SEARCH($G$10,'📋 Inventaire Complet'!$L$3:$L$517))))>0)))} -> 4 | G43: =IFERROR(F43/$F$50,0) -> 0.010178117 | I43: TOTAL | J43: =SUM(J35:J42) -> 393 | K43: =SUM(K35:K42) -> 1 | V43: Géopolymères, ciment & matériaux de construction | W43: {=SUMPRODUCT(('📋 Inventaire Complet'!$C$3:$C$517=$V43)*(((COUNTIF($B$6:$B$10,TRUE)=0)+ISNUMBER(IFERROR(MATCH('📋 Inventaire Complet'!$B$3:$B$517,IF($B$6:$B$10,$A$6:$A$10),0),""))>0))*(((COUNTIF($D$6:$D$22,TRUE)=0)+ISNUMBER(IFERROR(MATCH(LEFT('📋 Inventaire Complet'!$J$3:$J$517,4),IF($D$6:$D$22,$C$6:$C$22&""),0),""))>0))*(((COUNTIF($F$6:$F$20,TRUE)=0)+(ISNUMBER(IFERROR(MATCH('📋 Inventaire Complet'!$F$3:$F$517,IF($F$6:$F$19,$E$6:$E$19),0),""))+($F$20*ISNUMBER(MATCH('📋 Inventaire Complet'!$F$3:$F$517,{"D4R";"CEPH";"ISTI";"COLCOM";"HTMR"},0))))>0))*(LEN('📋 Inventaire Complet'!$D$3:$D$517)>0)*(((COUNTIF($H$6:$H$10,TRUE)=0)+(($H$6*ISNUMBER(SEARCH($G$6,'📋 Inventaire Complet'!$L$3:$L$517)))+($H$7*ISNUMBER(SEARCH($G$7,'📋 Inventaire Complet'!$L$3:$L$517)))+($H$8*ISNUMBER(SEARCH($G$8,'📋 Inventaire Complet'!$L$3:$L$517)))+($H$9*ISNUMBER(SEARCH($G$9,'📋 Inventaire Complet'!$L$3:$L$517)))+($H$10*ISNUMBER(SEARCH($G$10,'📋 Inventaire Complet'!$L$3:$L$517))))>0)))} -> 3 | X43: =W43+ROW()/10000 -> 3.0043 | Y43: Qaiss, Bouhfid, Essabir | Z43: {=IF(Y43="",0,SUMPRODUCT(('📋 Inventaire Complet'!$E$3:$E$517=Y43)*((COUNTIF($B$6:$B$10,TRUE)=0)+ISNUMBER(IFERROR(MATCH('📋 Inventaire Complet'!$B$3:$B$517,IF($B$6:$B$10,$A$6:$A$10),0),""))>0)*((COUNTIF($D$6:$D$22,TRUE)=0)+ISNUMBER(IFERROR(MATCH(LEFT('📋 Inventaire Complet'!$J$3:$J$517,4),IF($D$6:$D$22,$C$6:$C$22&""),0),""))>0)*((COUNTIF($F$6:$F$20,TRUE)=0)+(ISNUMBER(IFERROR(MATCH('📋 Inventaire Complet'!$F$3:$F$517,IF($F$6:$F$19,$E$6:$E$19),0),""))+($F$20*ISNUMBER(MATCH('📋 Inventaire Complet'!$F$3:$F$517,{"D4R";"CEPH";"ISTI";"COLCOM";"HTMR"},0))))>0)*((COUNTIF($H$6:$H$10,TRUE)=0)+(($H$6*ISNUMBER(SEARCH($G$6,'📋 Inventaire Complet'!$L$3:$L$517)))+($H$7*ISNUMBER(SEARCH($G$7,'📋 Inventaire Complet'!$L$3:$L$517)))+($H$8*ISNUMBER(SEARCH($G$8,'📋 Inventaire Complet'!$L$3:$L$517)))+($H$9*ISNUMBER(SEARCH($G$9,'📋 Inventaire Complet'!$L$3:$L$517)))+($H$10*ISNUMBER(SEARCH($G$10,'📋 Inventaire Complet'!$L$3:$L$517))))>0)))} -> 1 | AA43: =IF(Y43="",0,Z43+ROW()/10000) -> 1.0043
E44: LIMSET | F44: {=SUMPRODUCT(('📋 Inventaire Complet'!$F$3:$F$517=$E44)*(((COUNTIF($B$6:$B$10,TRUE)=0)+ISNUMBER(IFERROR(MATCH('📋 Inventaire Complet'!$B$3:$B$517,IF($B$6:$B$10,$A$6:$A$10),0),""))>0))*(((COUNTIF($D$6:$D$22,TRUE)=0)+ISNUMBER(IFERROR(MATCH(LEFT('📋 Inventaire Complet'!$J$3:$J$517,4),IF($D$6:$D$22,$C$6:$C$22&""),0),""))>0))*(LEN('📋 Inventaire Complet'!$D$3:$D$517)>0)*(((COUNTIF($H$6:$H$10,TRUE)=0)+(($H$6*ISNUMBER(SEARCH($G$6,'📋 Inventaire Complet'!$L$3:$L$517)))+($H$7*ISNUMBER(SEARCH($G$7,'📋 Inventaire Complet'!$L$3:$L$517)))+($H$8*ISNUMBER(SEARCH($G$8,'📋 Inventaire Complet'!$L$3:$L$517)))+($H$9*ISNUMBER(SEARCH($G$9,'📋 Inventaire Complet'!$L$3:$L$517)))+($H$10*ISNUMBER(SEARCH($G$10,'📋 Inventaire Complet'!$L$3:$L$517))))>0)))} -> 4 | G44: =IFERROR(F44/$F$50,0) -> 0.010178117 | V44: Produits chimiques issus de co-produits phosphatés | W44: {=SUMPRODUCT(('📋 Inventaire Complet'!$C$3:$C$517=$V44)*(((COUNTIF($B$6:$B$10,TRUE)=0)+ISNUMBER(IFERROR(MATCH('📋 Inventaire Complet'!$B$3:$B$517,IF($B$6:$B$10,$A$6:$A$10),0),""))>0))*(((COUNTIF($D$6:$D$22,TRUE)=0)+ISNUMBER(IFERROR(MATCH(LEFT('📋 Inventaire Complet'!$J$3:$J$517,4),IF($D$6:$D$22,$C$6:$C$22&""),0),""))>0))*(((COUNTIF($F$6:$F$20,TRUE)=0)+(ISNUMBER(IFERROR(MATCH('📋 Inventaire Complet'!$F$3:$F$517,IF($F$6:$F$19,$E$6:$E$19),0),""))+($F$20*ISNUMBER(MATCH('📋 Inventaire Complet'!$F$3:$F$517,{"D4R";"CEPH";"ISTI";"COLCOM";"HTMR"},0))))>0))*(LEN('📋 Inventaire Complet'!$D$3:$D$517)>0)*(((COUNTIF($H$6:$H$10,TRUE)=0)+(($H$6*ISNUMBER(SEARCH($G$6,'📋 Inventaire Complet'!$L$3:$L$517)))+($H$7*ISNUMBER(SEARCH($G$7,'📋 Inventaire Complet'!$L$3:$L$517)))+($H$8*ISNUMBER(SEARCH($G$8,'📋 Inventaire Complet'!$L$3:$L$517)))+($H$9*ISNUMBER(SEARCH($G$9,'📋 Inventaire Complet'!$L$3:$L$517)))+($H$10*ISNUMBER(SEARCH($G$10,'📋 Inventaire Complet'!$L$3:$L$517))))>0)))} -> 2 | X44: =W44+ROW()/10000 -> 2.0044 | Y44: ELMOUSSAOUI HASSAN TILSAGHANI Chakib MAHFOUD tarik HAMEDOUN Mohamed BENYOUSSEF ABDEL-ILAH | Z44: {=IF(Y44="",0,SUMPRODUCT(('📋 Inventaire Complet'!$E$3:$E$517=Y44)*((COUNTIF($B$6:$B$10,TRUE)=0)+ISNUMBER(IFERROR(MATCH('📋 Inventaire Complet'!$B$3:$B$517,IF($B$6:$B$10,$A$6:$A$10),0),""))>0)*((COUNTIF($D$6:$D$22,TRUE)=0)+ISNUMBER(IFERROR(MATCH(LEFT('📋 Inventaire Complet'!$J$3:$J$517,4),IF($D$6:$D$22,$C$6:$C$22&""),0),""))>0)*((COUNTIF($F$6:$F$20,TRUE)=0)+(ISNUMBER(IFERROR(MATCH('📋 Inventaire Complet'!$F$3:$F$517,IF($F$6:$F$19,$E$6:$E$19),0),""))+($F$20*ISNUMBER(MATCH('📋 Inventaire Complet'!$F$3:$F$517,{"D4R";"CEPH";"ISTI";"COLCOM";"HTMR"},0))))>0)*((COUNTIF($H$6:$H$10,TRUE)=0)+(($H$6*ISNUMBER(SEARCH($G$6,'📋 Inventaire Complet'!$L$3:$L$517)))+($H$7*ISNUMBER(SEARCH($G$7,'📋 Inventaire Complet'!$L$3:$L$517)))+($H$8*ISNUMBER(SEARCH($G$8,'📋 Inventaire Complet'!$L$3:$L$517)))+($H$9*ISNUMBER(SEARCH($G$9,'📋 Inventaire Complet'!$L$3:$L$517)))+($H$10*ISNUMBER(SEARCH($G$10,'📋 Inventaire Complet'!$L$3:$L$517))))>0)))} -> 1 | AA44: =IF(Y44="",0,Z44+ROW()/10000) -> 1.0044
E45: DICE | F45: {=SUMPRODUCT(('📋 Inventaire Complet'!$F$3:$F$517=$E45)*(((COUNTIF($B$6:$B$10,TRUE)=0)+ISNUMBER(IFERROR(MATCH('📋 Inventaire Complet'!$B$3:$B$517,IF($B$6:$B$10,$A$6:$A$10),0),""))>0))*(((COUNTIF($D$6:$D$22,TRUE)=0)+ISNUMBER(IFERROR(MATCH(LEFT('📋 Inventaire Complet'!$J$3:$J$517,4),IF($D$6:$D$22,$C$6:$C$22&""),0),""))>0))*(LEN('📋 Inventaire Complet'!$D$3:$D$517)>0)*(((COUNTIF($H$6:$H$10,TRUE)=0)+(($H$6*ISNUMBER(SEARCH($G$6,'📋 Inventaire Complet'!$L$3:$L$517)))+($H$7*ISNUMBER(SEARCH($G$7,'📋 Inventaire Complet'!$L$3:$L$517)))+($H$8*ISNUMBER(SEARCH($G$8,'📋 Inventaire Complet'!$L$3:$L$517)))+($H$9*ISNUMBER(SEARCH($G$9,'📋 Inventaire Complet'!$L$3:$L$517)))+($H$10*ISNUMBER(SEARCH($G$10,'📋 Inventaire Complet'!$L$3:$L$517))))>0)))} -> 3 | G45: =IFERROR(F45/$F$50,0) -> 0.0076335878 | V45: Récupération de métaux, terres rares & co-produits | W45: {=SUMPRODUCT(('📋 Inventaire Complet'!$C$3:$C$517=$V45)*(((COUNTIF($B$6:$B$10,TRUE)=0)+ISNUMBER(IFERROR(MATCH('📋 Inventaire Complet'!$B$3:$B$517,IF($B$6:$B$10,$A$6:$A$10),0),""))>0))*(((COUNTIF($D$6:$D$22,TRUE)=0)+ISNUMBER(IFERROR(MATCH(LEFT('📋 Inventaire Complet'!$J$3:$J$517,4),IF($D$6:$D$22,$C$6:$C$22&""),0),""))>0))*(((COUNTIF($F$6:$F$20,TRUE)=0)+(ISNUMBER(IFERROR(MATCH('📋 Inventaire Complet'!$F$3:$F$517,IF($F$6:$F$19,$E$6:$E$19),0),""))+($F$20*ISNUMBER(MATCH('📋 Inventaire Complet'!$F$3:$F$517,{"D4R";"CEPH";"ISTI";"COLCOM";"HTMR"},0))))>0))*(LEN('📋 Inventaire Complet'!$D$3:$D$517)>0)*(((COUNTIF($H$6:$H$10,TRUE)=0)+(($H$6*ISNUMBER(SEARCH($G$6,'📋 Inventaire Complet'!$L$3:$L$517)))+($H$7*ISNUMBER(SEARCH($G$7,'📋 Inventaire Complet'!$L$3:$L$517)))+($H$8*ISNUMBER(SEARCH($G$8,'📋 Inventaire Complet'!$L$3:$L$517)))+($H$9*ISNUMBER(SEARCH($G$9,'📋 Inventaire Complet'!$L$3:$L$517)))+($H$10*ISNUMBER(SEARCH($G$10,'📋 Inventaire Complet'!$L$3:$L$517))))>0)))} -> 1 | X45: =W45+ROW()/10000 -> 1.0045 | Y45: BOUHFID Rachid; ABOU EL KACEM Qaiss | Z45: {=IF(Y45="",0,SUMPRODUCT(('📋 Inventaire Complet'!$E$3:$E$517=Y45)*((COUNTIF($B$6:$B$10,TRUE)=0)+ISNUMBER(IFERROR(MATCH('📋 Inventaire Complet'!$B$3:$B$517,IF($B$6:$B$10,$A$6:$A$10),0),""))>0)*((COUNTIF($D$6:$D$22,TRUE)=0)+ISNUMBER(IFERROR(MATCH(LEFT('📋 Inventaire Complet'!$J$3:$J$517,4),IF($D$6:$D$22,$C$6:$C$22&""),0),""))>0)*((COUNTIF($F$6:$F$20,TRUE)=0)+(ISNUMBER(IFERROR(MATCH('📋 Inventaire Complet'!$F$3:$F$517,IF($F$6:$F$19,$E$6:$E$19),0),""))+($F$20*ISNUMBER(MATCH('📋 Inventaire Complet'!$F$3:$F$517,{"D4R";"CEPH";"ISTI";"COLCOM";"HTMR"},0))))>0)*((COUNTIF($H$6:$H$10,TRUE)=0)+(($H$6*ISNUMBER(SEARCH($G$6,'📋 Inventaire Complet'!$L$3:$L$517)))+($H$7*ISNUMBER(SEARCH($G$7,'📋 Inventaire Complet'!$L$3:$L$517)))+($H$8*ISNUMBER(SEARCH($G$8,'📋 Inventaire Complet'!$L$3:$L$517)))+($H$9*ISNUMBER(SEARCH($G$9,'📋 Inventaire Complet'!$L$3:$L$517)))+($H$10*ISNUMBER(SEARCH($G$10,'📋 Inventaire Complet'!$L$3:$L$517))))>0)))} -> 1 | AA45: =IF(Y45="",0,Z45+ROW()/10000) -> 1.0045
E46: TechCell | F46: {=SUMPRODUCT(('📋 Inventaire Complet'!$F$3:$F$517=$E46)*(((COUNTIF($B$6:$B$10,TRUE)=0)+ISNUMBER(IFERROR(MATCH('📋 Inventaire Complet'!$B$3:$B$517,IF($B$6:$B$10,$A$6:$A$10),0),""))>0))*(((COUNTIF($D$6:$D$22,TRUE)=0)+ISNUMBER(IFERROR(MATCH(LEFT('📋 Inventaire Complet'!$J$3:$J$517,4),IF($D$6:$D$22,$C$6:$C$22&""),0),""))>0))*(LEN('📋 Inventaire Complet'!$D$3:$D$517)>0)*(((COUNTIF($H$6:$H$10,TRUE)=0)+(($H$6*ISNUMBER(SEARCH($G$6,'📋 Inventaire Complet'!$L$3:$L$517)))+($H$7*ISNUMBER(SEARCH($G$7,'📋 Inventaire Complet'!$L$3:$L$517)))+($H$8*ISNUMBER(SEARCH($G$8,'📋 Inventaire Complet'!$L$3:$L$517)))+($H$9*ISNUMBER(SEARCH($G$9,'📋 Inventaire Complet'!$L$3:$L$517)))+($H$10*ISNUMBER(SEARCH($G$10,'📋 Inventaire Complet'!$L$3:$L$517))))>0)))} -> 3 | G46: =IFERROR(F46/$F$50,0) -> 0.0076335878 | V46: Valorisation du phosphogypse | W46: {=SUMPRODUCT(('📋 Inventaire Complet'!$C$3:$C$517=$V46)*(((COUNTIF($B$6:$B$10,TRUE)=0)+ISNUMBER(IFERROR(MATCH('📋 Inventaire Complet'!$B$3:$B$517,IF($B$6:$B$10,$A$6:$A$10),0),""))>0))*(((COUNTIF($D$6:$D$22,TRUE)=0)+ISNUMBER(IFERROR(MATCH(LEFT('📋 Inventaire Complet'!$J$3:$J$517,4),IF($D$6:$D$22,$C$6:$C$22&""),0),""))>0))*(((COUNTIF($F$6:$F$20,TRUE)=0)+(ISNUMBER(IFERROR(MATCH('📋 Inventaire Complet'!$F$3:$F$517,IF($F$6:$F$19,$E$6:$E$19),0),""))+($F$20*ISNUMBER(MATCH('📋 Inventaire Complet'!$F$3:$F$517,{"D4R";"CEPH";"ISTI";"COLCOM";"HTMR"},0))))>0))*(LEN('📋 Inventaire Complet'!$D$3:$D$517)>0)*(((COUNTIF($H$6:$H$10,TRUE)=0)+(($H$6*ISNUMBER(SEARCH($G$6,'📋 Inventaire Complet'!$L$3:$L$517)))+($H$7*ISNUMBER(SEARCH($G$7,'📋 Inventaire Complet'!$L$3:$L$517)))+($H$8*ISNUMBER(SEARCH($G$8,'📋 Inventaire Complet'!$L$3:$L$517)))+($H$9*ISNUMBER(SEARCH($G$9,'📋 Inventaire Complet'!$L$3:$L$517)))+($H$10*ISNUMBER(SEARCH($G$10,'📋 Inventaire Complet'!$L$3:$L$517))))>0)))} -> 18 | X46: =W46+ROW()/10000 -> 18.0046 | Y46: KLILOU Abdessamad BOURZEIX François NAGGAR Othmane | Z46: {=IF(Y46="",0,SUMPRODUCT(('📋 Inventaire Complet'!$E$3:$E$517=Y46)*((COUNTIF($B$6:$B$10,TRUE)=0)+ISNUMBER(IFERROR(MATCH('📋 Inventaire Complet'!$B$3:$B$517,IF($B$6:$B$10,$A$6:$A$10),0),""))>0)*((COUNTIF($D$6:$D$22,TRUE)=0)+ISNUMBER(IFERROR(MATCH(LEFT('📋 Inventaire Complet'!$J$3:$J$517,4),IF($D$6:$D$22,$C$6:$C$22&""),0),""))>0)*((COUNTIF($F$6:$F$20,TRUE)=0)+(ISNUMBER(IFERROR(MATCH('📋 Inventaire Complet'!$F$3:$F$517,IF($F$6:$F$19,$E$6:$E$19),0),""))+($F$20*ISNUMBER(MATCH('📋 Inventaire Complet'!$F$3:$F$517,{"D4R";"CEPH";"ISTI";"COLCOM";"HTMR"},0))))>0)*((COUNTIF($H$6:$H$10,TRUE)=0)+(($H$6*ISNUMBER(SEARCH($G$6,'📋 Inventaire Complet'!$L$3:$L$517)))+($H$7*ISNUMBER(SEARCH($G$7,'📋 Inventaire Complet'!$L$3:$L$517)))+($H$8*ISNUMBER(SEARCH($G$8,'📋 Inventaire Complet'!$L$3:$L$517)))+($H$9*ISNUMBER(SEARCH($G$9,'📋 Inventaire Complet'!$L$3:$L$517)))+($H$10*ISNUMBER(SEARCH($G$10,'📋 Inventaire Complet'!$L$3:$L$517))))>0)))} -> 1 | AA46: =IF(Y46="",0,Z46+ROW()/10000) -> 1.0046
E47: ILO | F47: {=SUMPRODUCT(('📋 Inventaire Complet'!$F$3:$F$517=$E47)*(((COUNTIF($B$6:$B$10,TRUE)=0)+ISNUMBER(IFERROR(MATCH('📋 Inventaire Complet'!$B$3:$B$517,IF($B$6:$B$10,$A$6:$A$10),0),""))>0))*(((COUNTIF($D$6:$D$22,TRUE)=0)+ISNUMBER(IFERROR(MATCH(LEFT('📋 Inventaire Complet'!$J$3:$J$517,4),IF($D$6:$D$22,$C$6:$C$22&""),0),""))>0))*(LEN('📋 Inventaire Complet'!$D$3:$D$517)>0))} -> 2 | G47: =IFERROR(F47/$F$50,0) -> 0.0050890585 | V47: Biocontrôle, stress végétal & hydroponie | W47: {=SUMPRODUCT(('📋 Inventaire Complet'!$C$3:$C$517=$V47)*(((COUNTIF($B$6:$B$10,TRUE)=0)+ISNUMBER(IFERROR(MATCH('📋 Inventaire Complet'!$B$3:$B$517,IF($B$6:$B$10,$A$6:$A$10),0),""))>0))*(((COUNTIF($D$6:$D$22,TRUE)=0)+ISNUMBER(IFERROR(MATCH(LEFT('📋 Inventaire Complet'!$J$3:$J$517,4),IF($D$6:$D$22,$C$6:$C$22&""),0),""))>0))*(((COUNTIF($F$6:$F$20,TRUE)=0)+(ISNUMBER(IFERROR(MATCH('📋 Inventaire Complet'!$F$3:$F$517,IF($F$6:$F$19,$E$6:$E$19),0),""))+($F$20*ISNUMBER(MATCH('📋 Inventaire Complet'!$F$3:$F$517,{"D4R";"CEPH";"ISTI";"COLCOM";"HTMR"},0))))>0))*(LEN('📋 Inventaire Complet'!$D$3:$D$517)>0)*(((COUNTIF($H$6:$H$10,TRUE)=0)+(($H$6*ISNUMBER(SEARCH($G$6,'📋 Inventaire Complet'!$L$3:$L$517)))+($H$7*ISNUMBER(SEARCH($G$7,'📋 Inventaire Complet'!$L$3:$L$517)))+($H$8*ISNUMBER(SEARCH($G$8,'📋 Inventaire Complet'!$L$3:$L$517)))+($H$9*ISNUMBER(SEARCH($G$9,'📋 Inventaire Complet'!$L$3:$L$517)))+($H$10*ISNUMBER(SEARCH($G$10,'📋 Inventaire Complet'!$L$3:$L$517))))>0)))} -> 2 | X47: =W47+ROW()/10000 -> 2.0047 | Y47: BENNANI Rachid; BENSALAH Mouad; STIRI Souhaima; LOUDARI Chaimae; LABRAHMI Mourad | Z47: {=IF(Y47="",0,SUMPRODUCT(('📋 Inventaire Complet'!$E$3:$E$517=Y47)*((COUNTIF($B$6:$B$10,TRUE)=0)+ISNUMBER(IFERROR(MATCH('📋 Inventaire Complet'!$B$3:$B$517,IF($B$6:$B$10,$A$6:$A$10),0),""))>0)*((COUNTIF($D$6:$D$22,TRUE)=0)+ISNUMBER(IFERROR(MATCH(LEFT('📋 Inventaire Complet'!$J$3:$J$517,4),IF($D$6:$D$22,$C$6:$C$22&""),0),""))>0)*((COUNTIF($F$6:$F$20,TRUE)=0)+(ISNUMBER(IFERROR(MATCH('📋 Inventaire Complet'!$F$3:$F$517,IF($F$6:$F$19,$E$6:$E$19),0),""))+($F$20*ISNUMBER(MATCH('📋 Inventaire Complet'!$F$3:$F$517,{"D4R";"CEPH";"ISTI";"COLCOM";"HTMR"},0))))>0)*((COUNTIF($H$6:$H$10,TRUE)=0)+(($H$6*ISNUMBER(SEARCH($G$6,'📋 Inventaire Complet'!$L$3:$L$517)))+($H$7*ISNUMBER(SEARCH($G$7,'📋 Inventaire Complet'!$L$3:$L$517)))+($H$8*ISNUMBER(SEARCH($G$8,'📋 Inventaire Complet'!$L$3:$L$517)))+($H$9*ISNUMBER(SEARCH($G$9,'📋 Inventaire Complet'!$L$3:$L$517)))+($H$10*ISNUMBER(SEARCH($G$10,'📋 Inventaire Complet'!$L$3:$L$517))))>0)))} -> 1 | AA47: =IF(Y47="",0,Z47+ROW()/10000) -> 1.0047
E48: Al-Moutmir | F48: {=SUMPRODUCT(('📋 Inventaire Complet'!$F$3:$F$517=$E48)*(((COUNTIF($B$6:$B$10,TRUE)=0)+ISNUMBER(IFERROR(MATCH('📋 Inventaire Complet'!$B$3:$B$517,IF($B$6:$B$10,$A$6:$A$10),0),""))>0))*(((COUNTIF($D$6:$D$22,TRUE)=0)+ISNUMBER(IFERROR(MATCH(LEFT('📋 Inventaire Complet'!$J$3:$J$517,4),IF($D$6:$D$22,$C$6:$C$22&""),0),""))>0))*(LEN('📋 Inventaire Complet'!$D$3:$D$517)>0))} -> 2 | G48: =IFERROR(F48/$F$50,0) -> 0.0050890585 | V48: Biofertilisants, biostimulants & enrobage d’engrais | W48: {=SUMPRODUCT(('📋 Inventaire Complet'!$C$3:$C$517=$V48)*(((COUNTIF($B$6:$B$10,TRUE)=0)+ISNUMBER(IFERROR(MATCH('📋 Inventaire Complet'!$B$3:$B$517,IF($B$6:$B$10,$A$6:$A$10),0),""))>0))*(((COUNTIF($D$6:$D$22,TRUE)=0)+ISNUMBER(IFERROR(MATCH(LEFT('📋 Inventaire Complet'!$J$3:$J$517,4),IF($D$6:$D$22,$C$6:$C$22&""),0),""))>0))*(((COUNTIF($F$6:$F$20,TRUE)=0)+(ISNUMBER(IFERROR(MATCH('📋 Inventaire Complet'!$F$3:$F$517,IF($F$6:$F$19,$E$6:$E$19),0),""))+($F$20*ISNUMBER(MATCH('📋 Inventaire Complet'!$F$3:$F$517,{"D4R";"CEPH";"ISTI";"COLCOM";"HTMR"},0))))>0))*(LEN('📋 Inventaire Complet'!$D$3:$D$517)>0)*(((COUNTIF($H$6:$H$10,TRUE)=0)+(($H$6*ISNUMBER(SEARCH($G$6,'📋 Inventaire Complet'!$L$3:$L$517)))+($H$7*ISNUMBER(SEARCH($G$7,'📋 Inventaire Complet'!$L$3:$L$517)))+($H$8*ISNUMBER(SEARCH($G$8,'📋 Inventaire Complet'!$L$3:$L$517)))+($H$9*ISNUMBER(SEARCH($G$9,'📋 Inventaire Complet'!$L$3:$L$517)))+($H$10*ISNUMBER(SEARCH($G$10,'📋 Inventaire Complet'!$L$3:$L$517))))>0)))} -> 10 | X48: =W48+ROW()/10000 -> 10.0048 | Y48: mounkachi, Hamedoun, Benyoussef, | Z48: {=IF(Y48="",0,SUMPRODUCT(('📋 Inventaire Complet'!$E$3:$E$517=Y48)*((COUNTIF($B$6:$B$10,TRUE)=0)+ISNUMBER(IFERROR(MATCH('📋 Inventaire Complet'!$B$3:$B$517,IF($B$6:$B$10,$A$6:$A$10),0),""))>0)*((COUNTIF($D$6:$D$22,TRUE)=0)+ISNUMBER(IFERROR(MATCH(LEFT('📋 Inventaire Complet'!$J$3:$J$517,4),IF($D$6:$D$22,$C$6:$C$22&""),0),""))>0)*((COUNTIF($F$6:$F$20,TRUE)=0)+(ISNUMBER(IFERROR(MATCH('📋 Inventaire Complet'!$F$3:$F$517,IF($F$6:$F$19,$E$6:$E$19),0),""))+($F$20*ISNUMBER(MATCH('📋 Inventaire Complet'!$F$3:$F$517,{"D4R";"CEPH";"ISTI";"COLCOM";"HTMR"},0))))>0)*((COUNTIF($H$6:$H$10,TRUE)=0)+(($H$6*ISNUMBER(SEARCH($G$6,'📋 Inventaire Complet'!$L$3:$L$517)))+($H$7*ISNUMBER(SEARCH($G$7,'📋 Inventaire Complet'!$L$3:$L$517)))+($H$8*ISNUMBER(SEARCH($G$8,'📋 Inventaire Complet'!$L$3:$L$517)))+($H$9*ISNUMBER(SEARCH($G$9,'📋 Inventaire Complet'!$L$3:$L$517)))+($H$10*ISNUMBER(SEARCH($G$10,'📋 Inventaire Complet'!$L$3:$L$517))))>0)))} -> 1 | AA48: =IF(Y48="",0,Z48+ROW()/10000) -> 1.0048
E49: Autres (D4R/CEPH/ISTI/COLCOM/HTMR) | F49: {=SUMPRODUCT(((('📋 Inventaire Complet'!$F$3:$F$517="D4R")+('📋 Inventaire Complet'!$F$3:$F$517="CEPH")+('📋 Inventaire Complet'!$F$3:$F$517="ISTI")+('📋 Inventaire Complet'!$F$3:$F$517="COLCOM")+('📋 Inventaire Complet'!$F$3:$F$517="HTMR"))>0)*(((COUNTIF($B$6:$B$10,TRUE)=0)+ISNUMBER(IFERROR(MATCH('📋 Inventaire Complet'!$B$3:$B$517,IF($B$6:$B$10,$A$6:$A$10),0),""))>0))*(((COUNTIF($D$6:$D$22,TRUE)=0)+ISNUMBER(IFERROR(MATCH(LEFT('📋 Inventaire Complet'!$J$3:$J$517,4),IF($D$6:$D$22,$C$6:$C$22&""),0),""))>0))*(LEN('📋 Inventaire Complet'!$D$3:$D$517)>0))} -> 5 | G49: =IFERROR(F49/$F$50,0) -> 0.012722646 | V49: Capteurs, électronique & systèmes intelligents | W49: {=SUMPRODUCT(('📋 Inventaire Complet'!$C$3:$C$517=$V49)*(((COUNTIF($B$6:$B$10,TRUE)=0)+ISNUMBER(IFERROR(MATCH('📋 Inventaire Complet'!$B$3:$B$517,IF($B$6:$B$10,$A$6:$A$10),0),""))>0))*(((COUNTIF($D$6:$D$22,TRUE)=0)+ISNUMBER(IFERROR(MATCH(LEFT('📋 Inventaire Complet'!$J$3:$J$517,4),IF($D$6:$D$22,$C$6:$C$22&""),0),""))>0))*(((COUNTIF($F$6:$F$20,TRUE)=0)+(ISNUMBER(IFERROR(MATCH('📋 Inventaire Complet'!$F$3:$F$517,IF($F$6:$F$19,$E$6:$E$19),0),""))+($F$20*ISNUMBER(MATCH('📋 Inventaire Complet'!$F$3:$F$517,{"D4R";"CEPH";"ISTI";"COLCOM";"HTMR"},0))))>0))*(LEN('📋 Inventaire Complet'!$D$3:$D$517)>0)*(((COUNTIF($H$6:$H$10,TRUE)=0)+(($H$6*ISNUMBER(SEARCH($G$6,'📋 Inventaire Complet'!$L$3:$L$517)))+($H$7*ISNUMBER(SEARCH($G$7,'📋 Inventaire Complet'!$L$3:$L$517)))+($H$8*ISNUMBER(SEARCH($G$8,'📋 Inventaire Complet'!$L$3:$L$517)))+($H$9*ISNUMBER(SEARCH($G$9,'📋 Inventaire Complet'!$L$3:$L$517)))+($H$10*ISNUMBER(SEARCH($G$10,'📋 Inventaire Complet'!$L$3:$L$517))))>0)))} -> 5 | X49: =W49+ROW()/10000 -> 5.0049 | Y49: BRICHE SAMIR; BOUTAMART Mustapha | Z49: {=IF(Y49="",0,SUMPRODUCT(('📋 Inventaire Complet'!$E$3:$E$517=Y49)*((COUNTIF($B$6:$B$10,TRUE)=0)+ISNUMBER(IFERROR(MATCH('📋 Inventaire Complet'!$B$3:$B$517,IF($B$6:$B$10,$A$6:$A$10),0),""))>0)*((COUNTIF($D$6:$D$22,TRUE)=0)+ISNUMBER(IFERROR(MATCH(LEFT('📋 Inventaire Complet'!$J$3:$J$517,4),IF($D$6:$D$22,$C$6:$C$22&""),0),""))>0)*((COUNTIF($F$6:$F$20,TRUE)=0)+(ISNUMBER(IFERROR(MATCH('📋 Inventaire Complet'!$F$3:$F$517,IF($F$6:$F$19,$E$6:$E$19),0),""))+($F$20*ISNUMBER(MATCH('📋 Inventaire Complet'!$F$3:$F$517,{"D4R";"CEPH";"ISTI";"COLCOM";"HTMR"},0))))>0)*((COUNTIF($H$6:$H$10,TRUE)=0)+(($H$6*ISNUMBER(SEARCH($G$6,'📋 Inventaire Complet'!$L$3:$L$517)))+($H$7*ISNUMBER(SEARCH($G$7,'📋 Inventaire Complet'!$L$3:$L$517)))+($H$8*ISNUMBER(SEARCH($G$8,'📋 Inventaire Complet'!$L$3:$L$517)))+($H$9*ISNUMBER(SEARCH($G$9,'📋 Inventaire Complet'!$L$3:$L$517)))+($H$10*ISNUMBER(SEARCH($G$10,'📋 Inventaire Complet'!$L$3:$L$517))))>0)))} -> 1 | AA49: =IF(Y49="",0,Z49+ROW()/10000) -> 1.0049
E50: TOTAL | F50: =SUM(F35:F49) -> 393 | G50: =SUM(G35:G49) -> 1 | V50: Diagnostic moléculaire & kits qPCR/LAMP | W50: {=SUMPRODUCT(('📋 Inventaire Complet'!$C$3:$C$517=$V50)*(((COUNTIF($B$6:$B$10,TRUE)=0)+ISNUMBER(IFERROR(MATCH('📋 Inventaire Complet'!$B$3:$B$517,IF($B$6:$B$10,$A$6:$A$10),0),""))>0))*(((COUNTIF($D$6:$D$22,TRUE)=0)+ISNUMBER(IFERROR(MATCH(LEFT('📋 Inventaire Complet'!$J$3:$J$517,4),IF($D$6:$D$22,$C$6:$C$22&""),0),""))>0))*(((COUNTIF($F$6:$F$20,TRUE)=0)+(ISNUMBER(IFERROR(MATCH('📋 Inventaire Complet'!$F$3:$F$517,IF($F$6:$F$19,$E$6:$E$19),0),""))+($F$20*ISNUMBER(MATCH('📋 Inventaire Complet'!$F$3:$F$517,{"D4R";"CEPH";"ISTI";"COLCOM";"HTMR"},0))))>0))*(LEN('📋 Inventaire Complet'!$D$3:$D$517)>0)*(((COUNTIF($H$6:$H$10,TRUE)=0)+(($H$6*ISNUMBER(SEARCH($G$6,'📋 Inventaire Complet'!$L$3:$L$517)))+($H$7*ISNUMBER(SEARCH($G$7,'📋 Inventaire Complet'!$L$3:$L$517)))+($H$8*ISNUMBER(SEARCH($G$8,'📋 Inventaire Complet'!$L$3:$L$517)))+($H$9*ISNUMBER(SEARCH($G$9,'📋 Inventaire Complet'!$L$3:$L$517)))+($H$10*ISNUMBER(SEARCH($G$10,'📋 Inventaire Complet'!$L$3:$L$517))))>0)))} -> 17 | X50: =W50+ROW()/10000 -> 17.005 | Y50: Zouheir Sekkat Anouar Rahmouni | Z50: {=IF(Y50="",0,SUMPRODUCT(('📋 Inventaire Complet'!$E$3:$E$517=Y50)*((COUNTIF($B$6:$B$10,TRUE)=0)+ISNUMBER(IFERROR(MATCH('📋 Inventaire Complet'!$B$3:$B$517,IF($B$6:$B$10,$A$6:$A$10),0),""))>0)*((COUNTIF($D$6:$D$22,TRUE)=0)+ISNUMBER(IFERROR(MATCH(LEFT('📋 Inventaire Complet'!$J$3:$J$517,4),IF($D$6:$D$22,$C$6:$C$22&""),0),""))>0)*((COUNTIF($F$6:$F$20,TRUE)=0)+(ISNUMBER(IFERROR(MATCH('📋 Inventaire Complet'!$F$3:$F$517,IF($F$6:$F$19,$E$6:$E$19),0),""))+($F$20*ISNUMBER(MATCH('📋 Inventaire Complet'!$F$3:$F$517,{"D4R";"CEPH";"ISTI";"COLCOM";"HTMR"},0))))>0)*((COUNTIF($H$6:$H$10,TRUE)=0)+(($H$6*ISNUMBER(SEARCH($G$6,'📋 Inventaire Complet'!$L$3:$L$517)))+($H$7*ISNUMBER(SEARCH($G$7,'📋 Inventaire Complet'!$L$3:$L$517)))+($H$8*ISNUMBER(SEARCH($G$8,'📋 Inventaire Complet'!$L$3:$L$517)))+($H$9*ISNUMBER(SEARCH($G$9,'📋 Inventaire Complet'!$L$3:$L$517)))+($H$10*ISNUMBER(SEARCH($G$10,'📋 Inventaire Complet'!$L$3:$L$517))))>0)))} -> 1 | AA50: =IF(Y50="",0,Z50+ROW()/10000) -> 1.005
A51: ÉVOLUTION ANNUELLE PAR THÉMATIQUE (données datées uniquement) | V51: Matériaux bioactifs & emballages antibactériens | W51: {=SUMPRODUCT(('📋 Inventaire Complet'!$C$3:$C$517=$V51)*(((COUNTIF($B$6:$B$10,TRUE)=0)+ISNUMBER(IFERROR(MATCH('📋 Inventaire Complet'!$B$3:$B$517,IF($B$6:$B$10,$A$6:$A$10),0),""))>0))*(((COUNTIF($D$6:$D$22,TRUE)=0)+ISNUMBER(IFERROR(MATCH(LEFT('📋 Inventaire Complet'!$J$3:$J$517,4),IF($D$6:$D$22,$C$6:$C$22&""),0),""))>0))*(((COUNTIF($F$6:$F$20,TRUE)=0)+(ISNUMBER(IFERROR(MATCH('📋 Inventaire Complet'!$F$3:$F$517,IF($F$6:$F$19,$E$6:$E$19),0),""))+($F$20*ISNUMBER(MATCH('📋 Inventaire Complet'!$F$3:$F$517,{"D4R";"CEPH";"ISTI";"COLCOM";"HTMR"},0))))>0))*(LEN('📋 Inventaire Complet'!$D$3:$D$517)>0)*(((COUNTIF($H$6:$H$10,TRUE)=0)+(($H$6*ISNUMBER(SEARCH($G$6,'📋 Inventaire Complet'!$L$3:$L$517)))+($H$7*ISNUMBER(SEARCH($G$7,'📋 Inventaire Complet'!$L$3:$L$517)))+($H$8*ISNUMBER(SEARCH($G$8,'📋 Inventaire Complet'!$L$3:$L$517)))+($H$9*ISNUMBER(SEARCH($G$9,'📋 Inventaire Complet'!$L$3:$L$517)))+($H$10*ISNUMBER(SEARCH($G$10,'📋 Inventaire Complet'!$L$3:$L$517))))>0)))} -> 1 | X51: =W51+ROW()/10000 -> 1.0051 | Y51: ANDRONIC | Z51: {=IF(Y51="",0,SUMPRODUCT(('📋 Inventaire Complet'!$E$3:$E$517=Y51)*((COUNTIF($B$6:$B$10,TRUE)=0)+ISNUMBER(IFERROR(MATCH('📋 Inventaire Complet'!$B$3:$B$517,IF($B$6:$B$10,$A$6:$A$10),0),""))>0)*((COUNTIF($D$6:$D$22,TRUE)=0)+ISNUMBER(IFERROR(MATCH(LEFT('📋 Inventaire Complet'!$J$3:$J$517,4),IF($D$6:$D$22,$C$6:$C$22&""),0),""))>0)*((COUNTIF($F$6:$F$20,TRUE)=0)+(ISNUMBER(IFERROR(MATCH('📋 Inventaire Complet'!$F$3:$F$517,IF($F$6:$F$19,$E$6:$E$19),0),""))+($F$20*ISNUMBER(MATCH('📋 Inventaire Complet'!$F$3:$F$517,{"D4R";"CEPH";"ISTI";"COLCOM";"HTMR"},0))))>0)*((COUNTIF($H$6:$H$10,TRUE)=0)+(($H$6*ISNUMBER(SEARCH($G$6,'📋 Inventaire Complet'!$L$3:$L$517)))+($H$7*ISNUMBER(SEARCH($G$7,'📋 Inventaire Complet'!$L$3:$L$517)))+($H$8*ISNUMBER(SEARCH($G$8,'📋 Inventaire Complet'!$L$3:$L$517)))+($H$9*ISNUMBER(SEARCH($G$9,'📋 Inventaire Complet'!$L$3:$L$517)))+($H$10*ISNUMBER(SEARCH($G$10,'📋 Inventaire Complet'!$L$3:$L$517))))>0)))} -> 1 | AA51: =IF(Y51="",0,Z51+ROW()/10000) -> 1.0051
A52: Année | B52: Env. Tech & Digital | C52: Mineral Proc. | D52: Circular Chem. | E52: Green Agri. | F52: Energy Storage | G52: Total | V52: Microalgues, macroalgues & extraits végétaux bioactifs | W52: {=SUMPRODUCT(('📋 Inventaire Complet'!$C$3:$C$517=$V52)*(((COUNTIF($B$6:$B$10,TRUE)=0)+ISNUMBER(IFERROR(MATCH('📋 Inventaire Complet'!$B$3:$B$517,IF($B$6:$B$10,$A$6:$A$10),0),""))>0))*(((COUNTIF($D$6:$D$22,TRUE)=0)+ISNUMBER(IFERROR(MATCH(LEFT('📋 Inventaire Complet'!$J$3:$J$517,4),IF($D$6:$D$22,$C$6:$C$22&""),0),""))>0))*(((COUNTIF($F$6:$F$20,TRUE)=0)+(ISNUMBER(IFERROR(MATCH('📋 Inventaire Complet'!$F$3:$F$517,IF($F$6:$F$19,$E$6:$E$19),0),""))+($F$20*ISNUMBER(MATCH('📋 Inventaire Complet'!$F$3:$F$517,{"D4R";"CEPH";"ISTI";"COLCOM";"HTMR"},0))))>0))*(LEN('📋 Inventaire Complet'!$D$3:$D$517)>0)*(((COUNTIF($H$6:$H$10,TRUE)=0)+(($H$6*ISNUMBER(SEARCH($G$6,'📋 Inventaire Complet'!$L$3:$L$517)))+($H$7*ISNUMBER(SEARCH($G$7,'📋 Inventaire Complet'!$L$3:$L$517)))+($H$8*ISNUMBER(SEARCH($G$8,'📋 Inventaire Complet'!$L$3:$L$517)))+($H$9*ISNUMBER(SEARCH($G$9,'📋 Inventaire Complet'!$L$3:$L$517)))+($H$10*ISNUMBER(SEARCH($G$10,'📋 Inventaire Complet'!$L$3:$L$517))))>0)))} -> 12 | X52: =W52+ROW()/10000 -> 12.0052 | Y52: MAHBOUB OUSSAMA SEKKAT ZOUHEIR RAHMOUNI ANOUAR | Z52: {=IF(Y52="",0,SUMPRODUCT(('📋 Inventaire Complet'!$E$3:$E$517=Y52)*((COUNTIF($B$6:$B$10,TRUE)=0)+ISNUMBER(IFERROR(MATCH('📋 Inventaire Complet'!$B$3:$B$517,IF($B$6:$B$10,$A$6:$A$10),0),""))>0)*((COUNTIF($D$6:$D$22,TRUE)=0)+ISNUMBER(IFERROR(MATCH(LEFT('📋 Inventaire Complet'!$J$3:$J$517,4),IF($D$6:$D$22,$C$6:$C$22&""),0),""))>0)*((COUNTIF($F$6:$F$20,TRUE)=0)+(ISNUMBER(IFERROR(MATCH('📋 Inventaire Complet'!$F$3:$F$517,IF($F$6:$F$19,$E$6:$E$19),0),""))+($F$20*ISNUMBER(MATCH('📋 Inventaire Complet'!$F$3:$F$517,{"D4R";"CEPH";"ISTI";"COLCOM";"HTMR"},0))))>0)*((COUNTIF($H$6:$H$10,TRUE)=0)+(($H$6*ISNUMBER(SEARCH($G$6,'📋 Inventaire Complet'!$L$3:$L$517)))+($H$7*ISNUMBER(SEARCH($G$7,'📋 Inventaire Complet'!$L$3:$L$517)))+($H$8*ISNUMBER(SEARCH($G$8,'📋 Inventaire Complet'!$L$3:$L$517)))+($H$9*ISNUMBER(SEARCH($G$9,'📋 Inventaire Complet'!$L$3:$L$517)))+($H$10*ISNUMBER(SEARCH($G$10,'📋 Inventaire Complet'!$L$3:$L$517))))>0)))} -> 1 | AA52: =IF(Y52="",0,Z52+ROW()/10000) -> 1.0052
A53: 2010 | B53: {=SUMPRODUCT((IFERROR(VALUE(LEFT('📋 Inventaire Complet'!$J$3:$J$517,4)),0)=$A53)*('📋 Inventaire Complet'!$B$3:$B$517="Environmental Tech & Digital Mining")*(((COUNTIF($B$6:$B$10,TRUE)=0)+ISNUMBER(IFERROR(MATCH('📋 Inventaire Complet'!$B$3:$B$517,IF($B$6:$B$10,$A$6:$A$10),0),""))>0))*(((COUNTIF($F$6:$F$20,TRUE)=0)+(ISNUMBER(IFERROR(MATCH('📋 Inventaire Complet'!$F$3:$F$517,IF($F$6:$F$19,$E$6:$E$19),0),""))+($F$20*ISNUMBER(MATCH('📋 Inventaire Complet'!$F$3:$F$517,{"D4R";"CEPH";"ISTI";"COLCOM";"HTMR"},0))))>0))*(LEN('📋 Inventaire Complet'!$D$3:$D$517)>0)*(((COUNTIF($H$6:$H$10,TRUE)=0)+(($H$6*ISNUMBER(SEARCH($G$6,'📋 Inventaire Complet'!$L$3:$L$517)))+($H$7*ISNUMBER(SEARCH($G$7,'📋 Inventaire Complet'!$L$3:$L$517)))+($H$8*ISNUMBER(SEARCH($G$8,'📋 Inventaire Complet'!$L$3:$L$517)))+($H$9*ISNUMBER(SEARCH($G$9,'📋 Inventaire Complet'!$L$3:$L$517)))+($H$10*ISNUMBER(SEARCH($G$10,'📋 Inventaire Complet'!$L$3:$L$517))))>0)))} -> 0 | C53: {=SUMPRODUCT((IFERROR(VALUE(LEFT('📋 Inventaire Complet'!$J$3:$J$517,4)),0)=$A53)*('📋 Inventaire Complet'!$B$3:$B$517="Mineral Processing & Strategic Synthesis")*(((COUNTIF($B$6:$B$10,TRUE)=0)+ISNUMBER(IFERROR(MATCH('📋 Inventaire Complet'!$B$3:$B$517,IF($B$6:$B$10,$A$6:$A$10),0),""))>0))*(((COUNTIF($F$6:$F$20,TRUE)=0)+(ISNUMBER(IFERROR(MATCH('📋 Inventaire Complet'!$F$3:$F$517,IF($F$6:$F$19,$E$6:$E$19),0),""))+($F$20*ISNUMBER(MATCH('📋 Inventaire Complet'!$F$3:$F$517,{"D4R";"CEPH";"ISTI";"COLCOM";"HTMR"},0))))>0))*(LEN('📋 Inventaire Complet'!$D$3:$D$517)>0)*(((COUNTIF($H$6:$H$10,TRUE)=0)+(($H$6*ISNUMBER(SEARCH($G$6,'📋 Inventaire Complet'!$L$3:$L$517)))+($H$7*ISNUMBER(SEARCH($G$7,'📋 Inventaire Complet'!$L$3:$L$517)))+($H$8*ISNUMBER(SEARCH($G$8,'📋 Inventaire Complet'!$L$3:$L$517)))+($H$9*ISNUMBER(SEARCH($G$9,'📋 Inventaire Complet'!$L$3:$L$517)))+($H$10*ISNUMBER(SEARCH($G$10,'📋 Inventaire Complet'!$L$3:$L$517))))>0)))} -> 1 | D53: {=SUMPRODUCT((IFERROR(VALUE(LEFT('📋 Inventaire Complet'!$J$3:$J$517,4)),0)=$A53)*('📋 Inventaire Complet'!$B$3:$B$517="Circular Chemistry & Waste Valorization")*(((COUNTIF($B$6:$B$10,TRUE)=0)+ISNUMBER(IFERROR(MATCH('📋 Inventaire Complet'!$B$3:$B$517,IF($B$6:$B$10,$A$6:$A$10),0),""))>0))*(((COUNTIF($F$6:$F$20,TRUE)=0)+(ISNUMBER(IFERROR(MATCH('📋 Inventaire Complet'!$F$3:$F$517,IF($F$6:$F$19,$E$6:$E$19),0),""))+($F$20*ISNUMBER(MATCH('📋 Inventaire Complet'!$F$3:$F$517,{"D4R";"CEPH";"ISTI";"COLCOM";"HTMR"},0))))>0))*(LEN('📋 Inventaire Complet'!$D$3:$D$517)>0)*(((COUNTIF($H$6:$H$10,TRUE)=0)+(($H$6*ISNUMBER(SEARCH($G$6,'📋 Inventaire Complet'!$L$3:$L$517)))+($H$7*ISNUMBER(SEARCH($G$7,'📋 Inventaire Complet'!$L$3:$L$517)))+($H$8*ISNUMBER(SEARCH($G$8,'📋 Inventaire Complet'!$L$3:$L$517)))+($H$9*ISNUMBER(SEARCH($G$9,'📋 Inventaire Complet'!$L$3:$L$517)))+($H$10*ISNUMBER(SEARCH($G$10,'📋 Inventaire Complet'!$L$3:$L$517))))>0)))} -> 0 | E53: {=SUMPRODUCT((IFERROR(VALUE(LEFT('📋 Inventaire Complet'!$J$3:$J$517,4)),0)=$A53)*('📋 Inventaire Complet'!$B$3:$B$517="Green Agriculture & Biotechnology")*(((COUNTIF($B$6:$B$10,TRUE)=0)+ISNUMBER(IFERROR(MATCH('📋 Inventaire Complet'!$B$3:$B$517,IF($B$6:$B$10,$A$6:$A$10),0),""))>0))*(((COUNTIF($F$6:$F$20,TRUE)=0)+(ISNUMBER(IFERROR(MATCH('📋 Inventaire Complet'!$F$3:$F$517,IF($F$6:$F$19,$E$6:$E$19),0),""))+($F$20*ISNUMBER(MATCH('📋 Inventaire Complet'!$F$3:$F$517,{"D4R";"CEPH";"ISTI";"COLCOM";"HTMR"},0))))>0))*(LEN('📋 Inventaire Complet'!$D$3:$D$517)>0)*(((COUNTIF($H$6:$H$10,TRUE)=0)+(($H$6*ISNUMBER(SEARCH($G$6,'📋 Inventaire Complet'!$L$3:$L$517)))+($H$7*ISNUMBER(SEARCH($G$7,'📋 Inventaire Complet'!$L$3:$L$517)))+($H$8*ISNUMBER(SEARCH($G$8,'📋 Inventaire Complet'!$L$3:$L$517)))+($H$9*ISNUMBER(SEARCH($G$9,'📋 Inventaire Complet'!$L$3:$L$517)))+($H$10*ISNUMBER(SEARCH($G$10,'📋 Inventaire Complet'!$L$3:$L$517))))>0)))} -> 0 | F53: {=SUMPRODUCT((IFERROR(VALUE(LEFT('📋 Inventaire Complet'!$J$3:$J$517,4)),0)=$A53)*('📋 Inventaire Complet'!$B$3:$B$517="Sustainable Energy Storage & Management")*(((COUNTIF($B$6:$B$10,TRUE)=0)+ISNUMBER(IFERROR(MATCH('📋 Inventaire Complet'!$B$3:$B$517,IF($B$6:$B$10,$A$6:$A$10),0),""))>0))*(((COUNTIF($F$6:$F$20,TRUE)=0)+(ISNUMBER(IFERROR(MATCH('📋 Inventaire Complet'!$F$3:$F$517,IF($F$6:$F$19,$E$6:$E$19),0),""))+($F$20*ISNUMBER(MATCH('📋 Inventaire Complet'!$F$3:$F$517,{"D4R";"CEPH";"ISTI";"COLCOM";"HTMR"},0))))>0))*(LEN('📋 Inventaire Complet'!$D$3:$D$517)>0)*(((COUNTIF($H$6:$H$10,TRUE)=0)+(($H$6*ISNUMBER(SEARCH($G$6,'📋 Inventaire Complet'!$L$3:$L$517)))+($H$7*ISNUMBER(SEARCH($G$7,'📋 Inventaire Complet'!$L$3:$L$517)))+($H$8*ISNUMBER(SEARCH($G$8,'📋 Inventaire Complet'!$L$3:$L$517)))+($H$9*ISNUMBER(SEARCH($G$9,'📋 Inventaire Complet'!$L$3:$L$517)))+($H$10*ISNUMBER(SEARCH($G$10,'📋 Inventaire Complet'!$L$3:$L$517))))>0)))} -> 0 | G53: =SUM(B53:F53) -> 1 | V53: Oncologie & molécules thérapeutiques | W53: {=SUMPRODUCT(('📋 Inventaire Complet'!$C$3:$C$517=$V53)*(((COUNTIF($B$6:$B$10,TRUE)=0)+ISNUMBER(IFERROR(MATCH('📋 Inventaire Complet'!$B$3:$B$517,IF($B$6:$B$10,$A$6:$A$10),0),""))>0))*(((COUNTIF($D$6:$D$22,TRUE)=0)+ISNUMBER(IFERROR(MATCH(LEFT('📋 Inventaire Complet'!$J$3:$J$517,4),IF($D$6:$D$22,$C$6:$C$22&""),0),""))>0))*(((COUNTIF($F$6:$F$20,TRUE)=0)+(ISNUMBER(IFERROR(MATCH('📋 Inventaire Complet'!$F$3:$F$517,IF($F$6:$F$19,$E$6:$E$19),0),""))+($F$20*ISNUMBER(MATCH('📋 Inventaire Complet'!$F$3:$F$517,{"D4R";"CEPH";"ISTI";"COLCOM";"HTMR"},0))))>0))*(LEN('📋 Inventaire Complet'!$D$3:$D$517)>0)*(((COUNTIF($H$6:$H$10,TRUE)=0)+(($H$6*ISNUMBER(SEARCH($G$6,'📋 Inventaire Complet'!$L$3:$L$517)))+($H$7*ISNUMBER(SEARCH($G$7,'📋 Inventaire Complet'!$L$3:$L$517)))+($H$8*ISNUMBER(SEARCH($G$8,'📋 Inventaire Complet'!$L$3:$L$517)))+($H$9*ISNUMBER(SEARCH($G$9,'📋 Inventaire Complet'!$L$3:$L$517)))+($H$10*ISNUMBER(SEARCH($G$10,'📋 Inventaire Complet'!$L$3:$L$517))))>0)))} -> 3 | X53: =W53+ROW()/10000 -> 3.0053 | Y53: BOUHFID RACHID QAISS ABOU EL KACEM ZARI NADIA Chkirida Soulaima | Z53: {=IF(Y53="",0,SUMPRODUCT(('📋 Inventaire Complet'!$E$3:$E$517=Y53)*((COUNTIF($B$6:$B$10,TRUE)=0)+ISNUMBER(IFERROR(MATCH('📋 Inventaire Complet'!$B$3:$B$517,IF($B$6:$B$10,$A$6:$A$10),0),""))>0)*((COUNTIF($D$6:$D$22,TRUE)=0)+ISNUMBER(IFERROR(MATCH(LEFT('📋 Inventaire Complet'!$J$3:$J$517,4),IF($D$6:$D$22,$C$6:$C$22&""),0),""))>0)*((COUNTIF($F$6:$F$20,TRUE)=0)+(ISNUMBER(IFERROR(MATCH('📋 Inventaire Complet'!$F$3:$F$517,IF($F$6:$F$19,$E$6:$E$19),0),""))+($F$20*ISNUMBER(MATCH('📋 Inventaire Complet'!$F$3:$F$517,{"D4R";"CEPH";"ISTI";"COLCOM";"HTMR"},0))))>0)*((COUNTIF($H$6:$H$10,TRUE)=0)+(($H$6*ISNUMBER(SEARCH($G$6,'📋 Inventaire Complet'!$L$3:$L$517)))+($H$7*ISNUMBER(SEARCH($G$7,'📋 Inventaire Complet'!$L$3:$L$517)))+($H$8*ISNUMBER(SEARCH($G$8,'📋 Inventaire Complet'!$L$3:$L$517)))+($H$9*ISNUMBER(SEARCH($G$9,'📋 Inventaire Complet'!$L$3:$L$517)))+($H$10*ISNUMBER(SEARCH($G$10,'📋 Inventaire Complet'!$L$3:$L$517))))>0)))} -> 1 | AA53: =IF(Y53="",0,Z53+ROW()/10000) -> 1.0053
A54: 2011 | B54: {=SUMPRODUCT((IFERROR(VALUE(LEFT('📋 Inventaire Complet'!$J$3:$J$517,4)),0)=$A54)*('📋 Inventaire Complet'!$B$3:$B$517="Environmental Tech & Digital Mining")*(((COUNTIF($B$6:$B$10,TRUE)=0)+ISNUMBER(IFERROR(MATCH('📋 Inventaire Complet'!$B$3:$B$517,IF($B$6:$B$10,$A$6:$A$10),0),""))>0))*(((COUNTIF($F$6:$F$20,TRUE)=0)+(ISNUMBER(IFERROR(MATCH('📋 Inventaire Complet'!$F$3:$F$517,IF($F$6:$F$19,$E$6:$E$19),0),""))+($F$20*ISNUMBER(MATCH('📋 Inventaire Complet'!$F$3:$F$517,{"D4R";"CEPH";"ISTI";"COLCOM";"HTMR"},0))))>0))*(LEN('📋 Inventaire Complet'!$D$3:$D$517)>0)*(((COUNTIF($H$6:$H$10,TRUE)=0)+(($H$6*ISNUMBER(SEARCH($G$6,'📋 Inventaire Complet'!$L$3:$L$517)))+($H$7*ISNUMBER(SEARCH($G$7,'📋 Inventaire Complet'!$L$3:$L$517)))+($H$8*ISNUMBER(SEARCH($G$8,'📋 Inventaire Complet'!$L$3:$L$517)))+($H$9*ISNUMBER(SEARCH($G$9,'📋 Inventaire Complet'!$L$3:$L$517)))+($H$10*ISNUMBER(SEARCH($G$10,'📋 Inventaire Complet'!$L$3:$L$517))))>0)))} -> 3 | C54: {=SUMPRODUCT((IFERROR(VALUE(LEFT('📋 Inventaire Complet'!$J$3:$J$517,4)),0)=$A54)*('📋 Inventaire Complet'!$B$3:$B$517="Mineral Processing & Strategic Synthesis")*(((COUNTIF($B$6:$B$10,TRUE)=0)+ISNUMBER(IFERROR(MATCH('📋 Inventaire Complet'!$B$3:$B$517,IF($B$6:$B$10,$A$6:$A$10),0),""))>0))*(((COUNTIF($F$6:$F$20,TRUE)=0)+(ISNUMBER(IFERROR(MATCH('📋 Inventaire Complet'!$F$3:$F$517,IF($F$6:$F$19,$E$6:$E$19),0),""))+($F$20*ISNUMBER(MATCH('📋 Inventaire Complet'!$F$3:$F$517,{"D4R";"CEPH";"ISTI";"COLCOM";"HTMR"},0))))>0))*(LEN('📋 Inventaire Complet'!$D$3:$D$517)>0)*(((COUNTIF($H$6:$H$10,TRUE)=0)+(($H$6*ISNUMBER(SEARCH($G$6,'📋 Inventaire Complet'!$L$3:$L$517)))+($H$7*ISNUMBER(SEARCH($G$7,'📋 Inventaire Complet'!$L$3:$L$517)))+($H$8*ISNUMBER(SEARCH($G$8,'📋 Inventaire Complet'!$L$3:$L$517)))+($H$9*ISNUMBER(SEARCH($G$9,'📋 Inventaire Complet'!$L$3:$L$517)))+($H$10*ISNUMBER(SEARCH($G$10,'📋 Inventaire Complet'!$L$3:$L$517))))>0)))} -> 3 | D54: {=SUMPRODUCT((IFERROR(VALUE(LEFT('📋 Inventaire Complet'!$J$3:$J$517,4)),0)=$A54)*('📋 Inventaire Complet'!$B$3:$B$517="Circular Chemistry & Waste Valorization")*(((COUNTIF($B$6:$B$10,TRUE)=0)+ISNUMBER(IFERROR(MATCH('📋 Inventaire Complet'!$B$3:$B$517,IF($B$6:$B$10,$A$6:$A$10),0),""))>0))*(((COUNTIF($F$6:$F$20,TRUE)=0)+(ISNUMBER(IFERROR(MATCH('📋 Inventaire Complet'!$F$3:$F$517,IF($F$6:$F$19,$E$6:$E$19),0),""))+($F$20*ISNUMBER(MATCH('📋 Inventaire Complet'!$F$3:$F$517,{"D4R";"CEPH";"ISTI";"COLCOM";"HTMR"},0))))>0))*(LEN('📋 Inventaire Complet'!$D$3:$D$517)>0)*(((COUNTIF($H$6:$H$10,TRUE)=0)+(($H$6*ISNUMBER(SEARCH($G$6,'📋 Inventaire Complet'!$L$3:$L$517)))+($H$7*ISNUMBER(SEARCH($G$7,'📋 Inventaire Complet'!$L$3:$L$517)))+($H$8*ISNUMBER(SEARCH($G$8,'📋 Inventaire Complet'!$L$3:$L$517)))+($H$9*ISNUMBER(SEARCH($G$9,'📋 Inventaire Complet'!$L$3:$L$517)))+($H$10*ISNUMBER(SEARCH($G$10,'📋 Inventaire Complet'!$L$3:$L$517))))>0)))} -> 0 | E54: {=SUMPRODUCT((IFERROR(VALUE(LEFT('📋 Inventaire Complet'!$J$3:$J$517,4)),0)=$A54)*('📋 Inventaire Complet'!$B$3:$B$517="Green Agriculture & Biotechnology")*(((COUNTIF($B$6:$B$10,TRUE)=0)+ISNUMBER(IFERROR(MATCH('📋 Inventaire Complet'!$B$3:$B$517,IF($B$6:$B$10,$A$6:$A$10),0),""))>0))*(((COUNTIF($F$6:$F$20,TRUE)=0)+(ISNUMBER(IFERROR(MATCH('📋 Inventaire Complet'!$F$3:$F$517,IF($F$6:$F$19,$E$6:$E$19),0),""))+($F$20*ISNUMBER(MATCH('📋 Inventaire Complet'!$F$3:$F$517,{"D4R";"CEPH";"ISTI";"COLCOM";"HTMR"},0))))>0))*(LEN('📋 Inventaire Complet'!$D$3:$D$517)>0)*(((COUNTIF($H$6:$H$10,TRUE)=0)+(($H$6*ISNUMBER(SEARCH($G$6,'📋 Inventaire Complet'!$L$3:$L$517)))+($H$7*ISNUMBER(SEARCH($G$7,'📋 Inventaire Complet'!$L$3:$L$517)))+($H$8*ISNUMBER(SEARCH($G$8,'📋 Inventaire Complet'!$L$3:$L$517)))+($H$9*ISNUMBER(SEARCH($G$9,'📋 Inventaire Complet'!$L$3:$L$517)))+($H$10*ISNUMBER(SEARCH($G$10,'📋 Inventaire Complet'!$L$3:$L$517))))>0)))} -> 0 | F54: {=SUMPRODUCT((IFERROR(VALUE(LEFT('📋 Inventaire Complet'!$J$3:$J$517,4)),0)=$A54)*('📋 Inventaire Complet'!$B$3:$B$517="Sustainable Energy Storage & Management")*(((COUNTIF($B$6:$B$10,TRUE)=0)+ISNUMBER(IFERROR(MATCH('📋 Inventaire Complet'!$B$3:$B$517,IF($B$6:$B$10,$A$6:$A$10),0),""))>0))*(((COUNTIF($F$6:$F$20,TRUE)=0)+(ISNUMBER(IFERROR(MATCH('📋 Inventaire Complet'!$F$3:$F$517,IF($F$6:$F$19,$E$6:$E$19),0),""))+($F$20*ISNUMBER(MATCH('📋 Inventaire Complet'!$F$3:$F$517,{"D4R";"CEPH";"ISTI";"COLCOM";"HTMR"},0))))>0))*(LEN('📋 Inventaire Complet'!$D$3:$D$517)>0)*(((COUNTIF($H$6:$H$10,TRUE)=0)+(($H$6*ISNUMBER(SEARCH($G$6,'📋 Inventaire Complet'!$L$3:$L$517)))+($H$7*ISNUMBER(SEARCH($G$7,'📋 Inventaire Complet'!$L$3:$L$517)))+($H$8*ISNUMBER(SEARCH($G$8,'📋 Inventaire Complet'!$L$3:$L$517)))+($H$9*ISNUMBER(SEARCH($G$9,'📋 Inventaire Complet'!$L$3:$L$517)))+($H$10*ISNUMBER(SEARCH($G$10,'📋 Inventaire Complet'!$L$3:$L$517))))>0)))} -> 0 | G54: =SUM(B54:F54) -> 6 | V54: Santé animale/alimentaire & procédés agroalimentaires | W54: {=SUMPRODUCT(('📋 Inventaire Complet'!$C$3:$C$517=$V54)*(((COUNTIF($B$6:$B$10,TRUE)=0)+ISNUMBER(IFERROR(MATCH('📋 Inventaire Complet'!$B$3:$B$517,IF($B$6:$B$10,$A$6:$A$10),0),""))>0))*(((COUNTIF($D$6:$D$22,TRUE)=0)+ISNUMBER(IFERROR(MATCH(LEFT('📋 Inventaire Complet'!$J$3:$J$517,4),IF($D$6:$D$22,$C$6:$C$22&""),0),""))>0))*(((COUNTIF($F$6:$F$20,TRUE)=0)+(ISNUMBER(IFERROR(MATCH('📋 Inventaire Complet'!$F$3:$F$517,IF($F$6:$F$19,$E$6:$E$19),0),""))+($F$20*ISNUMBER(MATCH('📋 Inventaire Complet'!$F$3:$F$517,{"D4R";"CEPH";"ISTI";"COLCOM";"HTMR"},0))))>0))*(LEN('📋 Inventaire Complet'!$D$3:$D$517)>0)*(((COUNTIF($H$6:$H$10,TRUE)=0)+(($H$6*ISNUMBER(SEARCH($G$6,'📋 Inventaire Complet'!$L$3:$L$517)))+($H$7*ISNUMBER(SEARCH($G$7,'📋 Inventaire Complet'!$L$3:$L$517)))+($H$8*ISNUMBER(SEARCH($G$8,'📋 Inventaire Complet'!$L$3:$L$517)))+($H$9*ISNUMBER(SEARCH($G$9,'📋 Inventaire Complet'!$L$3:$L$517)))+($H$10*ISNUMBER(SEARCH($G$10,'📋 Inventaire Complet'!$L$3:$L$517))))>0)))} -> 1 | X54: =W54+ROW()/10000 -> 1.0054 | Y54: AIT-DAHI MEHDI; ZARI NADIA; QAISS ABOU EL KACEM; BOUHFID RACHID | Z54: {=IF(Y54="",0,SUMPRODUCT(('📋 Inventaire Complet'!$E$3:$E$517=Y54)*((COUNTIF($B$6:$B$10,TRUE)=0)+ISNUMBER(IFERROR(MATCH('📋 Inventaire Complet'!$B$3:$B$517,IF($B$6:$B$10,$A$6:$A$10),0),""))>0)*((COUNTIF($D$6:$D$22,TRUE)=0)+ISNUMBER(IFERROR(MATCH(LEFT('📋 Inventaire Complet'!$J$3:$J$517,4),IF($D$6:$D$22,$C$6:$C$22&""),0),""))>0)*((COUNTIF($F$6:$F$20,TRUE)=0)+(ISNUMBER(IFERROR(MATCH('📋 Inventaire Complet'!$F$3:$F$517,IF($F$6:$F$19,$E$6:$E$19),0),""))+($F$20*ISNUMBER(MATCH('📋 Inventaire Complet'!$F$3:$F$517,{"D4R";"CEPH";"ISTI";"COLCOM";"HTMR"},0))))>0)*((COUNTIF($H$6:$H$10,TRUE)=0)+(($H$6*ISNUMBER(SEARCH($G$6,'📋 Inventaire Complet'!$L$3:$L$517)))+($H$7*ISNUMBER(SEARCH($G$7,'📋 Inventaire Complet'!$L$3:$L$517)))+($H$8*ISNUMBER(SEARCH($G$8,'📋 Inventaire Complet'!$L$3:$L$517)))+($H$9*ISNUMBER(SEARCH($G$9,'📋 Inventaire Complet'!$L$3:$L$517)))+($H$10*ISNUMBER(SEARCH($G$10,'📋 Inventaire Complet'!$L$3:$L$517))))>0)))} -> 1 | AA54: =IF(Y54="",0,Z54+ROW()/10000) -> 1.0054
A55: 2012 | B55: {=SUMPRODUCT((IFERROR(VALUE(LEFT('📋 Inventaire Complet'!$J$3:$J$517,4)),0)=$A55)*('📋 Inventaire Complet'!$B$3:$B$517="Environmental Tech & Digital Mining")*(((COUNTIF($B$6:$B$10,TRUE)=0)+ISNUMBER(IFERROR(MATCH('📋 Inventaire Complet'!$B$3:$B$517,IF($B$6:$B$10,$A$6:$A$10),0),""))>0))*(((COUNTIF($F$6:$F$20,TRUE)=0)+(ISNUMBER(IFERROR(MATCH('📋 Inventaire Complet'!$F$3:$F$517,IF($F$6:$F$19,$E$6:$E$19),0),""))+($F$20*ISNUMBER(MATCH('📋 Inventaire Complet'!$F$3:$F$517,{"D4R";"CEPH";"ISTI";"COLCOM";"HTMR"},0))))>0))*(LEN('📋 Inventaire Complet'!$D$3:$D$517)>0)*(((COUNTIF($H$6:$H$10,TRUE)=0)+(($H$6*ISNUMBER(SEARCH($G$6,'📋 Inventaire Complet'!$L$3:$L$517)))+($H$7*ISNUMBER(SEARCH($G$7,'📋 Inventaire Complet'!$L$3:$L$517)))+($H$8*ISNUMBER(SEARCH($G$8,'📋 Inventaire Complet'!$L$3:$L$517)))+($H$9*ISNUMBER(SEARCH($G$9,'📋 Inventaire Complet'!$L$3:$L$517)))+($H$10*ISNUMBER(SEARCH($G$10,'📋 Inventaire Complet'!$L$3:$L$517))))>0)))} -> 5 | C55: {=SUMPRODUCT((IFERROR(VALUE(LEFT('📋 Inventaire Complet'!$J$3:$J$517,4)),0)=$A55)*('📋 Inventaire Complet'!$B$3:$B$517="Mineral Processing & Strategic Synthesis")*(((COUNTIF($B$6:$B$10,TRUE)=0)+ISNUMBER(IFERROR(MATCH('📋 Inventaire Complet'!$B$3:$B$517,IF($B$6:$B$10,$A$6:$A$10),0),""))>0))*(((COUNTIF($F$6:$F$20,TRUE)=0)+(ISNUMBER(IFERROR(MATCH('📋 Inventaire Complet'!$F$3:$F$517,IF($F$6:$F$19,$E$6:$E$19),0),""))+($F$20*ISNUMBER(MATCH('📋 Inventaire Complet'!$F$3:$F$517,{"D4R";"CEPH";"ISTI";"COLCOM";"HTMR"},0))))>0))*(LEN('📋 Inventaire Complet'!$D$3:$D$517)>0)*(((COUNTIF($H$6:$H$10,TRUE)=0)+(($H$6*ISNUMBER(SEARCH($G$6,'📋 Inventaire Complet'!$L$3:$L$517)))+($H$7*ISNUMBER(SEARCH($G$7,'📋 Inventaire Complet'!$L$3:$L$517)))+($H$8*ISNUMBER(SEARCH($G$8,'📋 Inventaire Complet'!$L$3:$L$517)))+($H$9*ISNUMBER(SEARCH($G$9,'📋 Inventaire Complet'!$L$3:$L$517)))+($H$10*ISNUMBER(SEARCH($G$10,'📋 Inventaire Complet'!$L$3:$L$517))))>0)))} -> 4 | D55: {=SUMPRODUCT((IFERROR(VALUE(LEFT('📋 Inventaire Complet'!$J$3:$J$517,4)),0)=$A55)*('📋 Inventaire Complet'!$B$3:$B$517="Circular Chemistry & Waste Valorization")*(((COUNTIF($B$6:$B$10,TRUE)=0)+ISNUMBER(IFERROR(MATCH('📋 Inventaire Complet'!$B$3:$B$517,IF($B$6:$B$10,$A$6:$A$10),0),""))>0))*(((COUNTIF($F$6:$F$20,TRUE)=0)+(ISNUMBER(IFERROR(MATCH('📋 Inventaire Complet'!$F$3:$F$517,IF($F$6:$F$19,$E$6:$E$19),0),""))+($F$20*ISNUMBER(MATCH('📋 Inventaire Complet'!$F$3:$F$517,{"D4R";"CEPH";"ISTI";"COLCOM";"HTMR"},0))))>0))*(LEN('📋 Inventaire Complet'!$D$3:$D$517)>0)*(((COUNTIF($H$6:$H$10,TRUE)=0)+(($H$6*ISNUMBER(SEARCH($G$6,'📋 Inventaire Complet'!$L$3:$L$517)))+($H$7*ISNUMBER(SEARCH($G$7,'📋 Inventaire Complet'!$L$3:$L$517)))+($H$8*ISNUMBER(SEARCH($G$8,'📋 Inventaire Complet'!$L$3:$L$517)))+($H$9*ISNUMBER(SEARCH($G$9,'📋 Inventaire Complet'!$L$3:$L$517)))+($H$10*ISNUMBER(SEARCH($G$10,'📋 Inventaire Complet'!$L$3:$L$517))))>0)))} -> 1 | E55: {=SUMPRODUCT((IFERROR(VALUE(LEFT('📋 Inventaire Complet'!$J$3:$J$517,4)),0)=$A55)*('📋 Inventaire Complet'!$B$3:$B$517="Green Agriculture & Biotechnology")*(((COUNTIF($B$6:$B$10,TRUE)=0)+ISNUMBER(IFERROR(MATCH('📋 Inventaire Complet'!$B$3:$B$517,IF($B$6:$B$10,$A$6:$A$10),0),""))>0))*(((COUNTIF($F$6:$F$20,TRUE)=0)+(ISNUMBER(IFERROR(MATCH('📋 Inventaire Complet'!$F$3:$F$517,IF($F$6:$F$19,$E$6:$E$19),0),""))+($F$20*ISNUMBER(MATCH('📋 Inventaire Complet'!$F$3:$F$517,{"D4R";"CEPH";"ISTI";"COLCOM";"HTMR"},0))))>0))*(LEN('📋 Inventaire Complet'!$D$3:$D$517)>0)*(((COUNTIF($H$6:$H$10,TRUE)=0)+(($H$6*ISNUMBER(SEARCH($G$6,'📋 Inventaire Complet'!$L$3:$L$517)))+($H$7*ISNUMBER(SEARCH($G$7,'📋 Inventaire Complet'!$L$3:$L$517)))+($H$8*ISNUMBER(SEARCH($G$8,'📋 Inventaire Complet'!$L$3:$L$517)))+($H$9*ISNUMBER(SEARCH($G$9,'📋 Inventaire Complet'!$L$3:$L$517)))+($H$10*ISNUMBER(SEARCH($G$10,'📋 Inventaire Complet'!$L$3:$L$517))))>0)))} -> 4 | F55: {=SUMPRODUCT((IFERROR(VALUE(LEFT('📋 Inventaire Complet'!$J$3:$J$517,4)),0)=$A55)*('📋 Inventaire Complet'!$B$3:$B$517="Sustainable Energy Storage & Management")*(((COUNTIF($B$6:$B$10,TRUE)=0)+ISNUMBER(IFERROR(MATCH('📋 Inventaire Complet'!$B$3:$B$517,IF($B$6:$B$10,$A$6:$A$10),0),""))>0))*(((COUNTIF($F$6:$F$20,TRUE)=0)+(ISNUMBER(IFERROR(MATCH('📋 Inventaire Complet'!$F$3:$F$517,IF($F$6:$F$19,$E$6:$E$19),0),""))+($F$20*ISNUMBER(MATCH('📋 Inventaire Complet'!$F$3:$F$517,{"D4R";"CEPH";"ISTI";"COLCOM";"HTMR"},0))))>0))*(LEN('📋 Inventaire Complet'!$D$3:$D$517)>0)*(((COUNTIF($H$6:$H$10,TRUE)=0)+(($H$6*ISNUMBER(SEARCH($G$6,'📋 Inventaire Complet'!$L$3:$L$517)))+($H$7*ISNUMBER(SEARCH($G$7,'📋 Inventaire Complet'!$L$3:$L$517)))+($H$8*ISNUMBER(SEARCH($G$8,'📋 Inventaire Complet'!$L$3:$L$517)))+($H$9*ISNUMBER(SEARCH($G$9,'📋 Inventaire Complet'!$L$3:$L$517)))+($H$10*ISNUMBER(SEARCH($G$10,'📋 Inventaire Complet'!$L$3:$L$517))))>0)))} -> 0 | G55: =SUM(B55:F55) -> 14 | V55: Batteries intelligentes, diagnostic & gestion thermique | W55: {=SUMPRODUCT(('📋 Inventaire Complet'!$C$3:$C$517=$V55)*(((COUNTIF($B$6:$B$10,TRUE)=0)+ISNUMBER(IFERROR(MATCH('📋 Inventaire Complet'!$B$3:$B$517,IF($B$6:$B$10,$A$6:$A$10),0),""))>0))*(((COUNTIF($D$6:$D$22,TRUE)=0)+ISNUMBER(IFERROR(MATCH(LEFT('📋 Inventaire Complet'!$J$3:$J$517,4),IF($D$6:$D$22,$C$6:$C$22&""),0),""))>0))*(((COUNTIF($F$6:$F$20,TRUE)=0)+(ISNUMBER(IFERROR(MATCH('📋 Inventaire Complet'!$F$3:$F$517,IF($F$6:$F$19,$E$6:$E$19),0),""))+($F$20*ISNUMBER(MATCH('📋 Inventaire Complet'!$F$3:$F$517,{"D4R";"CEPH";"ISTI";"COLCOM";"HTMR"},0))))>0))*(LEN('📋 Inventaire Complet'!$D$3:$D$517)>0)*(((COUNTIF($H$6:$H$10,TRUE)=0)+(($H$6*ISNUMBER(SEARCH($G$6,'📋 Inventaire Complet'!$L$3:$L$517)))+($H$7*ISNUMBER(SEARCH($G$7,'📋 Inventaire Complet'!$L$3:$L$517)))+($H$8*ISNUMBER(SEARCH($G$8,'📋 Inventaire Complet'!$L$3:$L$517)))+($H$9*ISNUMBER(SEARCH($G$9,'📋 Inventaire Complet'!$L$3:$L$517)))+($H$10*ISNUMBER(SEARCH($G$10,'📋 Inventaire Complet'!$L$3:$L$517))))>0)))} -> 6 | X55: =W55+ROW()/10000 -> 6.0055 | Y55: SAMIR BRICHE, BELAICHE , YAACOUBI | Z55: {=IF(Y55="",0,SUMPRODUCT(('📋 Inventaire Complet'!$E$3:$E$517=Y55)*((COUNTIF($B$6:$B$10,TRUE)=0)+ISNUMBER(IFERROR(MATCH('📋 Inventaire Complet'!$B$3:$B$517,IF($B$6:$B$10,$A$6:$A$10),0),""))>0)*((COUNTIF($D$6:$D$22,TRUE)=0)+ISNUMBER(IFERROR(MATCH(LEFT('📋 Inventaire Complet'!$J$3:$J$517,4),IF($D$6:$D$22,$C$6:$C$22&""),0),""))>0)*((COUNTIF($F$6:$F$20,TRUE)=0)+(ISNUMBER(IFERROR(MATCH('📋 Inventaire Complet'!$F$3:$F$517,IF($F$6:$F$19,$E$6:$E$19),0),""))+($F$20*ISNUMBER(MATCH('📋 Inventaire Complet'!$F$3:$F$517,{"D4R";"CEPH";"ISTI";"COLCOM";"HTMR"},0))))>0)*((COUNTIF($H$6:$H$10,TRUE)=0)+(($H$6*ISNUMBER(SEARCH($G$6,'📋 Inventaire Complet'!$L$3:$L$517)))+($H$7*ISNUMBER(SEARCH($G$7,'📋 Inventaire Complet'!$L$3:$L$517)))+($H$8*ISNUMBER(SEARCH($G$8,'📋 Inventaire Complet'!$L$3:$L$517)))+($H$9*ISNUMBER(SEARCH($G$9,'📋 Inventaire Complet'!$L$3:$L$517)))+($H$10*ISNUMBER(SEARCH($G$10,'📋 Inventaire Complet'!$L$3:$L$517))))>0)))} -> 1 | AA55: =IF(Y55="",0,Z55+ROW()/10000) -> 1.0055
A56: 2013 | B56: {=SUMPRODUCT((IFERROR(VALUE(LEFT('📋 Inventaire Complet'!$J$3:$J$517,4)),0)=$A56)*('📋 Inventaire Complet'!$B$3:$B$517="Environmental Tech & Digital Mining")*(((COUNTIF($B$6:$B$10,TRUE)=0)+ISNUMBER(IFERROR(MATCH('📋 Inventaire Complet'!$B$3:$B$517,IF($B$6:$B$10,$A$6:$A$10),0),""))>0))*(((COUNTIF($F$6:$F$20,TRUE)=0)+(ISNUMBER(IFERROR(MATCH('📋 Inventaire Complet'!$F$3:$F$517,IF($F$6:$F$19,$E$6:$E$19),0),""))+($F$20*ISNUMBER(MATCH('📋 Inventaire Complet'!$F$3:$F$517,{"D4R";"CEPH";"ISTI";"COLCOM";"HTMR"},0))))>0))*(LEN('📋 Inventaire Complet'!$D$3:$D$517)>0)*(((COUNTIF($H$6:$H$10,TRUE)=0)+(($H$6*ISNUMBER(SEARCH($G$6,'📋 Inventaire Complet'!$L$3:$L$517)))+($H$7*ISNUMBER(SEARCH($G$7,'📋 Inventaire Complet'!$L$3:$L$517)))+($H$8*ISNUMBER(SEARCH($G$8,'📋 Inventaire Complet'!$L$3:$L$517)))+($H$9*ISNUMBER(SEARCH($G$9,'📋 Inventaire Complet'!$L$3:$L$517)))+($H$10*ISNUMBER(SEARCH($G$10,'📋 Inventaire Complet'!$L$3:$L$517))))>0)))} -> 10 | C56: {=SUMPRODUCT((IFERROR(VALUE(LEFT('📋 Inventaire Complet'!$J$3:$J$517,4)),0)=$A56)*('📋 Inventaire Complet'!$B$3:$B$517="Mineral Processing & Strategic Synthesis")*(((COUNTIF($B$6:$B$10,TRUE)=0)+ISNUMBER(IFERROR(MATCH('📋 Inventaire Complet'!$B$3:$B$517,IF($B$6:$B$10,$A$6:$A$10),0),""))>0))*(((COUNTIF($F$6:$F$20,TRUE)=0)+(ISNUMBER(IFERROR(MATCH('📋 Inventaire Complet'!$F$3:$F$517,IF($F$6:$F$19,$E$6:$E$19),0),""))+($F$20*ISNUMBER(MATCH('📋 Inventaire Complet'!$F$3:$F$517,{"D4R";"CEPH";"ISTI";"COLCOM";"HTMR"},0))))>0))*(LEN('📋 Inventaire Complet'!$D$3:$D$517)>0)*(((COUNTIF($H$6:$H$10,TRUE)=0)+(($H$6*ISNUMBER(SEARCH($G$6,'📋 Inventaire Complet'!$L$3:$L$517)))+($H$7*ISNUMBER(SEARCH($G$7,'📋 Inventaire Complet'!$L$3:$L$517)))+($H$8*ISNUMBER(SEARCH($G$8,'📋 Inventaire Complet'!$L$3:$L$517)))+($H$9*ISNUMBER(SEARCH($G$9,'📋 Inventaire Complet'!$L$3:$L$517)))+($H$10*ISNUMBER(SEARCH($G$10,'📋 Inventaire Complet'!$L$3:$L$517))))>0)))} -> 5 | D56: {=SUMPRODUCT((IFERROR(VALUE(LEFT('📋 Inventaire Complet'!$J$3:$J$517,4)),0)=$A56)*('📋 Inventaire Complet'!$B$3:$B$517="Circular Chemistry & Waste Valorization")*(((COUNTIF($B$6:$B$10,TRUE)=0)+ISNUMBER(IFERROR(MATCH('📋 Inventaire Complet'!$B$3:$B$517,IF($B$6:$B$10,$A$6:$A$10),0),""))>0))*(((COUNTIF($F$6:$F$20,TRUE)=0)+(ISNUMBER(IFERROR(MATCH('📋 Inventaire Complet'!$F$3:$F$517,IF($F$6:$F$19,$E$6:$E$19),0),""))+($F$20*ISNUMBER(MATCH('📋 Inventaire Complet'!$F$3:$F$517,{"D4R";"CEPH";"ISTI";"COLCOM";"HTMR"},0))))>0))*(LEN('📋 Inventaire Complet'!$D$3:$D$517)>0)*(((COUNTIF($H$6:$H$10,TRUE)=0)+(($H$6*ISNUMBER(SEARCH($G$6,'📋 Inventaire Complet'!$L$3:$L$517)))+($H$7*ISNUMBER(SEARCH($G$7,'📋 Inventaire Complet'!$L$3:$L$517)))+($H$8*ISNUMBER(SEARCH($G$8,'📋 Inventaire Complet'!$L$3:$L$517)))+($H$9*ISNUMBER(SEARCH($G$9,'📋 Inventaire Complet'!$L$3:$L$517)))+($H$10*ISNUMBER(SEARCH($G$10,'📋 Inventaire Complet'!$L$3:$L$517))))>0)))} -> 3 | E56: {=SUMPRODUCT((IFERROR(VALUE(LEFT('📋 Inventaire Complet'!$J$3:$J$517,4)),0)=$A56)*('📋 Inventaire Complet'!$B$3:$B$517="Green Agriculture & Biotechnology")*(((COUNTIF($B$6:$B$10,TRUE)=0)+ISNUMBER(IFERROR(MATCH('📋 Inventaire Complet'!$B$3:$B$517,IF($B$6:$B$10,$A$6:$A$10),0),""))>0))*(((COUNTIF($F$6:$F$20,TRUE)=0)+(ISNUMBER(IFERROR(MATCH('📋 Inventaire Complet'!$F$3:$F$517,IF($F$6:$F$19,$E$6:$E$19),0),""))+($F$20*ISNUMBER(MATCH('📋 Inventaire Complet'!$F$3:$F$517,{"D4R";"CEPH";"ISTI";"COLCOM";"HTMR"},0))))>0))*(LEN('📋 Inventaire Complet'!$D$3:$D$517)>0)*(((COUNTIF($H$6:$H$10,TRUE)=0)+(($H$6*ISNUMBER(SEARCH($G$6,'📋 Inventaire Complet'!$L$3:$L$517)))+($H$7*ISNUMBER(SEARCH($G$7,'📋 Inventaire Complet'!$L$3:$L$517)))+($H$8*ISNUMBER(SEARCH($G$8,'📋 Inventaire Complet'!$L$3:$L$517)))+($H$9*ISNUMBER(SEARCH($G$9,'📋 Inventaire Complet'!$L$3:$L$517)))+($H$10*ISNUMBER(SEARCH($G$10,'📋 Inventaire Complet'!$L$3:$L$517))))>0)))} -> 3 | F56: {=SUMPRODUCT((IFERROR(VALUE(LEFT('📋 Inventaire Complet'!$J$3:$J$517,4)),0)=$A56)*('📋 Inventaire Complet'!$B$3:$B$517="Sustainable Energy Storage & Management")*(((COUNTIF($B$6:$B$10,TRUE)=0)+ISNUMBER(IFERROR(MATCH('📋 Inventaire Complet'!$B$3:$B$517,IF($B$6:$B$10,$A$6:$A$10),0),""))>0))*(((COUNTIF($F$6:$F$20,TRUE)=0)+(ISNUMBER(IFERROR(MATCH('📋 Inventaire Complet'!$F$3:$F$517,IF($F$6:$F$19,$E$6:$E$19),0),""))+($F$20*ISNUMBER(MATCH('📋 Inventaire Complet'!$F$3:$F$517,{"D4R";"CEPH";"ISTI";"COLCOM";"HTMR"},0))))>0))*(LEN('📋 Inventaire Complet'!$D$3:$D$517)>0)*(((COUNTIF($H$6:$H$10,TRUE)=0)+(($H$6*ISNUMBER(SEARCH($G$6,'📋 Inventaire Complet'!$L$3:$L$517)))+($H$7*ISNUMBER(SEARCH($G$7,'📋 Inventaire Complet'!$L$3:$L$517)))+($H$8*ISNUMBER(SEARCH($G$8,'📋 Inventaire Complet'!$L$3:$L$517)))+($H$9*ISNUMBER(SEARCH($G$9,'📋 Inventaire Complet'!$L$3:$L$517)))+($H$10*ISNUMBER(SEARCH($G$10,'📋 Inventaire Complet'!$L$3:$L$517))))>0)))} -> 0 | G56: =SUM(B56:F56) -> 21 | V56: Hydrogène, gaz de synthèse & pyrolyse | W56: {=SUMPRODUCT(('📋 Inventaire Complet'!$C$3:$C$517=$V56)*(((COUNTIF($B$6:$B$10,TRUE)=0)+ISNUMBER(IFERROR(MATCH('📋 Inventaire Complet'!$B$3:$B$517,IF($B$6:$B$10,$A$6:$A$10),0),""))>0))*(((COUNTIF($D$6:$D$22,TRUE)=0)+ISNUMBER(IFERROR(MATCH(LEFT('📋 Inventaire Complet'!$J$3:$J$517,4),IF($D$6:$D$22,$C$6:$C$22&""),0),""))>0))*(((COUNTIF($F$6:$F$20,TRUE)=0)+(ISNUMBER(IFERROR(MATCH('📋 Inventaire Complet'!$F$3:$F$517,IF($F$6:$F$19,$E$6:$E$19),0),""))+($F$20*ISNUMBER(MATCH('📋 Inventaire Complet'!$F$3:$F$517,{"D4R";"CEPH";"ISTI";"COLCOM";"HTMR"},0))))>0))*(LEN('📋 Inventaire Complet'!$D$3:$D$517)>0)*(((COUNTIF($H$6:$H$10,TRUE)=0)+(($H$6*ISNUMBER(SEARCH($G$6,'📋 Inventaire Complet'!$L$3:$L$517)))+($H$7*ISNUMBER(SEARCH($G$7,'📋 Inventaire Complet'!$L$3:$L$517)))+($H$8*ISNUMBER(SEARCH($G$8,'📋 Inventaire Complet'!$L$3:$L$517)))+($H$9*ISNUMBER(SEARCH($G$9,'📋 Inventaire Complet'!$L$3:$L$517)))+($H$10*ISNUMBER(SEARCH($G$10,'📋 Inventaire Complet'!$L$3:$L$517))))>0)))} -> 2 | X56: =W56+ROW()/10000 -> 2.0056 | Y56: ESSASSI EL MOKHTAR ENNAJIH Hamid EL KADIB Abdelkrim BOUHFID Rachid | Z56: {=IF(Y56="",0,SUMPRODUCT(('📋 Inventaire Complet'!$E$3:$E$517=Y56)*((COUNTIF($B$6:$B$10,TRUE)=0)+ISNUMBER(IFERROR(MATCH('📋 Inventaire Complet'!$B$3:$B$517,IF($B$6:$B$10,$A$6:$A$10),0),""))>0)*((COUNTIF($D$6:$D$22,TRUE)=0)+ISNUMBER(IFERROR(MATCH(LEFT('📋 Inventaire Complet'!$J$3:$J$517,4),IF($D$6:$D$22,$C$6:$C$22&""),0),""))>0)*((COUNTIF($F$6:$F$20,TRUE)=0)+(ISNUMBER(IFERROR(MATCH('📋 Inventaire Complet'!$F$3:$F$517,IF($F$6:$F$19,$E$6:$E$19),0),""))+($F$20*ISNUMBER(MATCH('📋 Inventaire Complet'!$F$3:$F$517,{"D4R";"CEPH";"ISTI";"COLCOM";"HTMR"},0))))>0)*((COUNTIF($H$6:$H$10,TRUE)=0)+(($H$6*ISNUMBER(SEARCH($G$6,'📋 Inventaire Complet'!$L$3:$L$517)))+($H$7*ISNUMBER(SEARCH($G$7,'📋 Inventaire Complet'!$L$3:$L$517)))+($H$8*ISNUMBER(SEARCH($G$8,'📋 Inventaire Complet'!$L$3:$L$517)))+($H$9*ISNUMBER(SEARCH($G$9,'📋 Inventaire Complet'!$L$3:$L$517)))+($H$10*ISNUMBER(SEARCH($G$10,'📋 Inventaire Complet'!$L$3:$L$517))))>0)))} -> 1 | AA56: =IF(Y56="",0,Z56+ROW()/10000) -> 1.0056
A57: 2014 | B57: {=SUMPRODUCT((IFERROR(VALUE(LEFT('📋 Inventaire Complet'!$J$3:$J$517,4)),0)=$A57)*('📋 Inventaire Complet'!$B$3:$B$517="Environmental Tech & Digital Mining")*(((COUNTIF($B$6:$B$10,TRUE)=0)+ISNUMBER(IFERROR(MATCH('📋 Inventaire Complet'!$B$3:$B$517,IF($B$6:$B$10,$A$6:$A$10),0),""))>0))*(((COUNTIF($F$6:$F$20,TRUE)=0)+(ISNUMBER(IFERROR(MATCH('📋 Inventaire Complet'!$F$3:$F$517,IF($F$6:$F$19,$E$6:$E$19),0),""))+($F$20*ISNUMBER(MATCH('📋 Inventaire Complet'!$F$3:$F$517,{"D4R";"CEPH";"ISTI";"COLCOM";"HTMR"},0))))>0))*(LEN('📋 Inventaire Complet'!$D$3:$D$517)>0)*(((COUNTIF($H$6:$H$10,TRUE)=0)+(($H$6*ISNUMBER(SEARCH($G$6,'📋 Inventaire Complet'!$L$3:$L$517)))+($H$7*ISNUMBER(SEARCH($G$7,'📋 Inventaire Complet'!$L$3:$L$517)))+($H$8*ISNUMBER(SEARCH($G$8,'📋 Inventaire Complet'!$L$3:$L$517)))+($H$9*ISNUMBER(SEARCH($G$9,'📋 Inventaire Complet'!$L$3:$L$517)))+($H$10*ISNUMBER(SEARCH($G$10,'📋 Inventaire Complet'!$L$3:$L$517))))>0)))} -> 10 | C57: {=SUMPRODUCT((IFERROR(VALUE(LEFT('📋 Inventaire Complet'!$J$3:$J$517,4)),0)=$A57)*('📋 Inventaire Complet'!$B$3:$B$517="Mineral Processing & Strategic Synthesis")*(((COUNTIF($B$6:$B$10,TRUE)=0)+ISNUMBER(IFERROR(MATCH('📋 Inventaire Complet'!$B$3:$B$517,IF($B$6:$B$10,$A$6:$A$10),0),""))>0))*(((COUNTIF($F$6:$F$20,TRUE)=0)+(ISNUMBER(IFERROR(MATCH('📋 Inventaire Complet'!$F$3:$F$517,IF($F$6:$F$19,$E$6:$E$19),0),""))+($F$20*ISNUMBER(MATCH('📋 Inventaire Complet'!$F$3:$F$517,{"D4R";"CEPH";"ISTI";"COLCOM";"HTMR"},0))))>0))*(LEN('📋 Inventaire Complet'!$D$3:$D$517)>0)*(((COUNTIF($H$6:$H$10,TRUE)=0)+(($H$6*ISNUMBER(SEARCH($G$6,'📋 Inventaire Complet'!$L$3:$L$517)))+($H$7*ISNUMBER(SEARCH($G$7,'📋 Inventaire Complet'!$L$3:$L$517)))+($H$8*ISNUMBER(SEARCH($G$8,'📋 Inventaire Complet'!$L$3:$L$517)))+($H$9*ISNUMBER(SEARCH($G$9,'📋 Inventaire Complet'!$L$3:$L$517)))+($H$10*ISNUMBER(SEARCH($G$10,'📋 Inventaire Complet'!$L$3:$L$517))))>0)))} -> 5 | D57: {=SUMPRODUCT((IFERROR(VALUE(LEFT('📋 Inventaire Complet'!$J$3:$J$517,4)),0)=$A57)*('📋 Inventaire Complet'!$B$3:$B$517="Circular Chemistry & Waste Valorization")*(((COUNTIF($B$6:$B$10,TRUE)=0)+ISNUMBER(IFERROR(MATCH('📋 Inventaire Complet'!$B$3:$B$517,IF($B$6:$B$10,$A$6:$A$10),0),""))>0))*(((COUNTIF($F$6:$F$20,TRUE)=0)+(ISNUMBER(IFERROR(MATCH('📋 Inventaire Complet'!$F$3:$F$517,IF($F$6:$F$19,$E$6:$E$19),0),""))+($F$20*ISNUMBER(MATCH('📋 Inventaire Complet'!$F$3:$F$517,{"D4R";"CEPH";"ISTI";"COLCOM";"HTMR"},0))))>0))*(LEN('📋 Inventaire Complet'!$D$3:$D$517)>0)*(((COUNTIF($H$6:$H$10,TRUE)=0)+(($H$6*ISNUMBER(SEARCH($G$6,'📋 Inventaire Complet'!$L$3:$L$517)))+($H$7*ISNUMBER(SEARCH($G$7,'📋 Inventaire Complet'!$L$3:$L$517)))+($H$8*ISNUMBER(SEARCH($G$8,'📋 Inventaire Complet'!$L$3:$L$517)))+($H$9*ISNUMBER(SEARCH($G$9,'📋 Inventaire Complet'!$L$3:$L$517)))+($H$10*ISNUMBER(SEARCH($G$10,'📋 Inventaire Complet'!$L$3:$L$517))))>0)))} -> 4 | E57: {=SUMPRODUCT((IFERROR(VALUE(LEFT('📋 Inventaire Complet'!$J$3:$J$517,4)),0)=$A57)*('📋 Inventaire Complet'!$B$3:$B$517="Green Agriculture & Biotechnology")*(((COUNTIF($B$6:$B$10,TRUE)=0)+ISNUMBER(IFERROR(MATCH('📋 Inventaire Complet'!$B$3:$B$517,IF($B$6:$B$10,$A$6:$A$10),0),""))>0))*(((COUNTIF($F$6:$F$20,TRUE)=0)+(ISNUMBER(IFERROR(MATCH('📋 Inventaire Complet'!$F$3:$F$517,IF($F$6:$F$19,$E$6:$E$19),0),""))+($F$20*ISNUMBER(MATCH('📋 Inventaire Complet'!$F$3:$F$517,{"D4R";"CEPH";"ISTI";"COLCOM";"HTMR"},0))))>0))*(LEN('📋 Inventaire Complet'!$D$3:$D$517)>0)*(((COUNTIF($H$6:$H$10,TRUE)=0)+(($H$6*ISNUMBER(SEARCH($G$6,'📋 Inventaire Complet'!$L$3:$L$517)))+($H$7*ISNUMBER(SEARCH($G$7,'📋 Inventaire Complet'!$L$3:$L$517)))+($H$8*ISNUMBER(SEARCH($G$8,'📋 Inventaire Complet'!$L$3:$L$517)))+($H$9*ISNUMBER(SEARCH($G$9,'📋 Inventaire Complet'!$L$3:$L$517)))+($H$10*ISNUMBER(SEARCH($G$10,'📋 Inventaire Complet'!$L$3:$L$517))))>0)))} -> 5 | F57: {=SUMPRODUCT((IFERROR(VALUE(LEFT('📋 Inventaire Complet'!$J$3:$J$517,4)),0)=$A57)*('📋 Inventaire Complet'!$B$3:$B$517="Sustainable Energy Storage & Management")*(((COUNTIF($B$6:$B$10,TRUE)=0)+ISNUMBER(IFERROR(MATCH('📋 Inventaire Complet'!$B$3:$B$517,IF($B$6:$B$10,$A$6:$A$10),0),""))>0))*(((COUNTIF($F$6:$F$20,TRUE)=0)+(ISNUMBER(IFERROR(MATCH('📋 Inventaire Complet'!$F$3:$F$517,IF($F$6:$F$19,$E$6:$E$19),0),""))+($F$20*ISNUMBER(MATCH('📋 Inventaire Complet'!$F$3:$F$517,{"D4R";"CEPH";"ISTI";"COLCOM";"HTMR"},0))))>0))*(LEN('📋 Inventaire Complet'!$D$3:$D$517)>0)*(((COUNTIF($H$6:$H$10,TRUE)=0)+(($H$6*ISNUMBER(SEARCH($G$6,'📋 Inventaire Complet'!$L$3:$L$517)))+($H$7*ISNUMBER(SEARCH($G$7,'📋 Inventaire Complet'!$L$3:$L$517)))+($H$8*ISNUMBER(SEARCH($G$8,'📋 Inventaire Complet'!$L$3:$L$517)))+($H$9*ISNUMBER(SEARCH($G$9,'📋 Inventaire Complet'!$L$3:$L$517)))+($H$10*ISNUMBER(SEARCH($G$10,'📋 Inventaire Complet'!$L$3:$L$517))))>0)))} -> 4 | G57: =SUM(B57:F57) -> 28 | V57: Matériaux cathodiques & électrodes pour batteries Li/Na | W57: {=SUMPRODUCT(('📋 Inventaire Complet'!$C$3:$C$517=$V57)*(((COUNTIF($B$6:$B$10,TRUE)=0)+ISNUMBER(IFERROR(MATCH('📋 Inventaire Complet'!$B$3:$B$517,IF($B$6:$B$10,$A$6:$A$10),0),""))>0))*(((COUNTIF($D$6:$D$22,TRUE)=0)+ISNUMBER(IFERROR(MATCH(LEFT('📋 Inventaire Complet'!$J$3:$J$517,4),IF($D$6:$D$22,$C$6:$C$22&""),0),""))>0))*(((COUNTIF($F$6:$F$20,TRUE)=0)+(ISNUMBER(IFERROR(MATCH('📋 Inventaire Complet'!$F$3:$F$517,IF($F$6:$F$19,$E$6:$E$19),0),""))+($F$20*ISNUMBER(MATCH('📋 Inventaire Complet'!$F$3:$F$517,{"D4R";"CEPH";"ISTI";"COLCOM";"HTMR"},0))))>0))*(LEN('📋 Inventaire Complet'!$D$3:$D$517)>0)*(((COUNTIF($H$6:$H$10,TRUE)=0)+(($H$6*ISNUMBER(SEARCH($G$6,'📋 Inventaire Complet'!$L$3:$L$517)))+($H$7*ISNUMBER(SEARCH($G$7,'📋 Inventaire Complet'!$L$3:$L$517)))+($H$8*ISNUMBER(SEARCH($G$8,'📋 Inventaire Complet'!$L$3:$L$517)))+($H$9*ISNUMBER(SEARCH($G$9,'📋 Inventaire Complet'!$L$3:$L$517)))+($H$10*ISNUMBER(SEARCH($G$10,'📋 Inventaire Complet'!$L$3:$L$517))))>0)))} -> 10 | X57: =W57+ROW()/10000 -> 10.0057 | Y57: El Mokhtar ESSASSI Mounir EL ACHABI Abouelkacem QAISS Rachid BOUHFID Khalid BENMOUSSA | Z57: {=IF(Y57="",0,SUMPRODUCT(('📋 Inventaire Complet'!$E$3:$E$517=Y57)*((COUNTIF($B$6:$B$10,TRUE)=0)+ISNUMBER(IFERROR(MATCH('📋 Inventaire Complet'!$B$3:$B$517,IF($B$6:$B$10,$A$6:$A$10),0),""))>0)*((COUNTIF($D$6:$D$22,TRUE)=0)+ISNUMBER(IFERROR(MATCH(LEFT('📋 Inventaire Complet'!$J$3:$J$517,4),IF($D$6:$D$22,$C$6:$C$22&""),0),""))>0)*((COUNTIF($F$6:$F$20,TRUE)=0)+(ISNUMBER(IFERROR(MATCH('📋 Inventaire Complet'!$F$3:$F$517,IF($F$6:$F$19,$E$6:$E$19),0),""))+($F$20*ISNUMBER(MATCH('📋 Inventaire Complet'!$F$3:$F$517,{"D4R";"CEPH";"ISTI";"COLCOM";"HTMR"},0))))>0)*((COUNTIF($H$6:$H$10,TRUE)=0)+(($H$6*ISNUMBER(SEARCH($G$6,'📋 Inventaire Complet'!$L$3:$L$517)))+($H$7*ISNUMBER(SEARCH($G$7,'📋 Inventaire Complet'!$L$3:$L$517)))+($H$8*ISNUMBER(SEARCH($G$8,'📋 Inventaire Complet'!$L$3:$L$517)))+($H$9*ISNUMBER(SEARCH($G$9,'📋 Inventaire Complet'!$L$3:$L$517)))+($H$10*ISNUMBER(SEARCH($G$10,'📋 Inventaire Complet'!$L$3:$L$517))))>0)))} -> 1 | AA57: =IF(Y57="",0,Z57+ROW()/10000) -> 1.0057
A58: 2015 | B58: {=SUMPRODUCT((IFERROR(VALUE(LEFT('📋 Inventaire Complet'!$J$3:$J$517,4)),0)=$A58)*('📋 Inventaire Complet'!$B$3:$B$517="Environmental Tech & Digital Mining")*(((COUNTIF($B$6:$B$10,TRUE)=0)+ISNUMBER(IFERROR(MATCH('📋 Inventaire Complet'!$B$3:$B$517,IF($B$6:$B$10,$A$6:$A$10),0),""))>0))*(((COUNTIF($F$6:$F$20,TRUE)=0)+(ISNUMBER(IFERROR(MATCH('📋 Inventaire Complet'!$F$3:$F$517,IF($F$6:$F$19,$E$6:$E$19),0),""))+($F$20*ISNUMBER(MATCH('📋 Inventaire Complet'!$F$3:$F$517,{"D4R";"CEPH";"ISTI";"COLCOM";"HTMR"},0))))>0))*(LEN('📋 Inventaire Complet'!$D$3:$D$517)>0)*(((COUNTIF($H$6:$H$10,TRUE)=0)+(($H$6*ISNUMBER(SEARCH($G$6,'📋 Inventaire Complet'!$L$3:$L$517)))+($H$7*ISNUMBER(SEARCH($G$7,'📋 Inventaire Complet'!$L$3:$L$517)))+($H$8*ISNUMBER(SEARCH($G$8,'📋 Inventaire Complet'!$L$3:$L$517)))+($H$9*ISNUMBER(SEARCH($G$9,'📋 Inventaire Complet'!$L$3:$L$517)))+($H$10*ISNUMBER(SEARCH($G$10,'📋 Inventaire Complet'!$L$3:$L$517))))>0)))} -> 14 | C58: {=SUMPRODUCT((IFERROR(VALUE(LEFT('📋 Inventaire Complet'!$J$3:$J$517,4)),0)=$A58)*('📋 Inventaire Complet'!$B$3:$B$517="Mineral Processing & Strategic Synthesis")*(((COUNTIF($B$6:$B$10,TRUE)=0)+ISNUMBER(IFERROR(MATCH('📋 Inventaire Complet'!$B$3:$B$517,IF($B$6:$B$10,$A$6:$A$10),0),""))>0))*(((COUNTIF($F$6:$F$20,TRUE)=0)+(ISNUMBER(IFERROR(MATCH('📋 Inventaire Complet'!$F$3:$F$517,IF($F$6:$F$19,$E$6:$E$19),0),""))+($F$20*ISNUMBER(MATCH('📋 Inventaire Complet'!$F$3:$F$517,{"D4R";"CEPH";"ISTI";"COLCOM";"HTMR"},0))))>0))*(LEN('📋 Inventaire Complet'!$D$3:$D$517)>0)*(((COUNTIF($H$6:$H$10,TRUE)=0)+(($H$6*ISNUMBER(SEARCH($G$6,'📋 Inventaire Complet'!$L$3:$L$517)))+($H$7*ISNUMBER(SEARCH($G$7,'📋 Inventaire Complet'!$L$3:$L$517)))+($H$8*ISNUMBER(SEARCH($G$8,'📋 Inventaire Complet'!$L$3:$L$517)))+($H$9*ISNUMBER(SEARCH($G$9,'📋 Inventaire Complet'!$L$3:$L$517)))+($H$10*ISNUMBER(SEARCH($G$10,'📋 Inventaire Complet'!$L$3:$L$517))))>0)))} -> 5 | D58: {=SUMPRODUCT((IFERROR(VALUE(LEFT('📋 Inventaire Complet'!$J$3:$J$517,4)),0)=$A58)*('📋 Inventaire Complet'!$B$3:$B$517="Circular Chemistry & Waste Valorization")*(((COUNTIF($B$6:$B$10,TRUE)=0)+ISNUMBER(IFERROR(MATCH('📋 Inventaire Complet'!$B$3:$B$517,IF($B$6:$B$10,$A$6:$A$10),0),""))>0))*(((COUNTIF($F$6:$F$20,TRUE)=0)+(ISNUMBER(IFERROR(MATCH('📋 Inventaire Complet'!$F$3:$F$517,IF($F$6:$F$19,$E$6:$E$19),0),""))+($F$20*ISNUMBER(MATCH('📋 Inventaire Complet'!$F$3:$F$517,{"D4R";"CEPH";"ISTI";"COLCOM";"HTMR"},0))))>0))*(LEN('📋 Inventaire Complet'!$D$3:$D$517)>0)*(((COUNTIF($H$6:$H$10,TRUE)=0)+(($H$6*ISNUMBER(SEARCH($G$6,'📋 Inventaire Complet'!$L$3:$L$517)))+($H$7*ISNUMBER(SEARCH($G$7,'📋 Inventaire Complet'!$L$3:$L$517)))+($H$8*ISNUMBER(SEARCH($G$8,'📋 Inventaire Complet'!$L$3:$L$517)))+($H$9*ISNUMBER(SEARCH($G$9,'📋 Inventaire Complet'!$L$3:$L$517)))+($H$10*ISNUMBER(SEARCH($G$10,'📋 Inventaire Complet'!$L$3:$L$517))))>0)))} -> 2 | E58: {=SUMPRODUCT((IFERROR(VALUE(LEFT('📋 Inventaire Complet'!$J$3:$J$517,4)),0)=$A58)*('📋 Inventaire Complet'!$B$3:$B$517="Green Agriculture & Biotechnology")*(((COUNTIF($B$6:$B$10,TRUE)=0)+ISNUMBER(IFERROR(MATCH('📋 Inventaire Complet'!$B$3:$B$517,IF($B$6:$B$10,$A$6:$A$10),0),""))>0))*(((COUNTIF($F$6:$F$20,TRUE)=0)+(ISNUMBER(IFERROR(MATCH('📋 Inventaire Complet'!$F$3:$F$517,IF($F$6:$F$19,$E$6:$E$19),0),""))+($F$20*ISNUMBER(MATCH('📋 Inventaire Complet'!$F$3:$F$517,{"D4R";"CEPH";"ISTI";"COLCOM";"HTMR"},0))))>0))*(LEN('📋 Inventaire Complet'!$D$3:$D$517)>0)*(((COUNTIF($H$6:$H$10,TRUE)=0)+(($H$6*ISNUMBER(SEARCH($G$6,'📋 Inventaire Complet'!$L$3:$L$517)))+($H$7*ISNUMBER(SEARCH($G$7,'📋 Inventaire Complet'!$L$3:$L$517)))+($H$8*ISNUMBER(SEARCH($G$8,'📋 Inventaire Complet'!$L$3:$L$517)))+($H$9*ISNUMBER(SEARCH($G$9,'📋 Inventaire Complet'!$L$3:$L$517)))+($H$10*ISNUMBER(SEARCH($G$10,'📋 Inventaire Complet'!$L$3:$L$517))))>0)))} -> 10 | F58: {=SUMPRODUCT((IFERROR(VALUE(LEFT('📋 Inventaire Complet'!$J$3:$J$517,4)),0)=$A58)*('📋 Inventaire Complet'!$B$3:$B$517="Sustainable Energy Storage & Management")*(((COUNTIF($B$6:$B$10,TRUE)=0)+ISNUMBER(IFERROR(MATCH('📋 Inventaire Complet'!$B$3:$B$517,IF($B$6:$B$10,$A$6:$A$10),0),""))>0))*(((COUNTIF($F$6:$F$20,TRUE)=0)+(ISNUMBER(IFERROR(MATCH('📋 Inventaire Complet'!$F$3:$F$517,IF($F$6:$F$19,$E$6:$E$19),0),""))+($F$20*ISNUMBER(MATCH('📋 Inventaire Complet'!$F$3:$F$517,{"D4R";"CEPH";"ISTI";"COLCOM";"HTMR"},0))))>0))*(LEN('📋 Inventaire Complet'!$D$3:$D$517)>0)*(((COUNTIF($H$6:$H$10,TRUE)=0)+(($H$6*ISNUMBER(SEARCH($G$6,'📋 Inventaire Complet'!$L$3:$L$517)))+($H$7*ISNUMBER(SEARCH($G$7,'📋 Inventaire Complet'!$L$3:$L$517)))+($H$8*ISNUMBER(SEARCH($G$8,'📋 Inventaire Complet'!$L$3:$L$517)))+($H$9*ISNUMBER(SEARCH($G$9,'📋 Inventaire Complet'!$L$3:$L$517)))+($H$10*ISNUMBER(SEARCH($G$10,'📋 Inventaire Complet'!$L$3:$L$517))))>0)))} -> 0 | G58: =SUM(B58:F58) -> 31 | V58: Photovoltaïque, solaire & thermoélectrique | W58: {=SUMPRODUCT(('📋 Inventaire Complet'!$C$3:$C$517=$V58)*(((COUNTIF($B$6:$B$10,TRUE)=0)+ISNUMBER(IFERROR(MATCH('📋 Inventaire Complet'!$B$3:$B$517,IF($B$6:$B$10,$A$6:$A$10),0),""))>0))*(((COUNTIF($D$6:$D$22,TRUE)=0)+ISNUMBER(IFERROR(MATCH(LEFT('📋 Inventaire Complet'!$J$3:$J$517,4),IF($D$6:$D$22,$C$6:$C$22&""),0),""))>0))*(((COUNTIF($F$6:$F$20,TRUE)=0)+(ISNUMBER(IFERROR(MATCH('📋 Inventaire Complet'!$F$3:$F$517,IF($F$6:$F$19,$E$6:$E$19),0),""))+($F$20*ISNUMBER(MATCH('📋 Inventaire Complet'!$F$3:$F$517,{"D4R";"CEPH";"ISTI";"COLCOM";"HTMR"},0))))>0))*(LEN('📋 Inventaire Complet'!$D$3:$D$517)>0)*(((COUNTIF($H$6:$H$10,TRUE)=0)+(($H$6*ISNUMBER(SEARCH($G$6,'📋 Inventaire Complet'!$L$3:$L$517)))+($H$7*ISNUMBER(SEARCH($G$7,'📋 Inventaire Complet'!$L$3:$L$517)))+($H$8*ISNUMBER(SEARCH($G$8,'📋 Inventaire Complet'!$L$3:$L$517)))+($H$9*ISNUMBER(SEARCH($G$9,'📋 Inventaire Complet'!$L$3:$L$517)))+($H$10*ISNUMBER(SEARCH($G$10,'📋 Inventaire Complet'!$L$3:$L$517))))>0)))} -> 3 | X58: =W58+ROW()/10000 -> 3.0058 | Y58: BOUHFID Rachid Qaiss Abou el kacem | Z58: {=IF(Y58="",0,SUMPRODUCT(('📋 Inventaire Complet'!$E$3:$E$517=Y58)*((COUNTIF($B$6:$B$10,TRUE)=0)+ISNUMBER(IFERROR(MATCH('📋 Inventaire Complet'!$B$3:$B$517,IF($B$6:$B$10,$A$6:$A$10),0),""))>0)*((COUNTIF($D$6:$D$22,TRUE)=0)+ISNUMBER(IFERROR(MATCH(LEFT('📋 Inventaire Complet'!$J$3:$J$517,4),IF($D$6:$D$22,$C$6:$C$22&""),0),""))>0)*((COUNTIF($F$6:$F$20,TRUE)=0)+(ISNUMBER(IFERROR(MATCH('📋 Inventaire Complet'!$F$3:$F$517,IF($F$6:$F$19,$E$6:$E$19),0),""))+($F$20*ISNUMBER(MATCH('📋 Inventaire Complet'!$F$3:$F$517,{"D4R";"CEPH";"ISTI";"COLCOM";"HTMR"},0))))>0)*((COUNTIF($H$6:$H$10,TRUE)=0)+(($H$6*ISNUMBER(SEARCH($G$6,'📋 Inventaire Complet'!$L$3:$L$517)))+($H$7*ISNUMBER(SEARCH($G$7,'📋 Inventaire Complet'!$L$3:$L$517)))+($H$8*ISNUMBER(SEARCH($G$8,'📋 Inventaire Complet'!$L$3:$L$517)))+($H$9*ISNUMBER(SEARCH($G$9,'📋 Inventaire Complet'!$L$3:$L$517)))+($H$10*ISNUMBER(SEARCH($G$10,'📋 Inventaire Complet'!$L$3:$L$517))))>0)))} -> 5 | AA58: =IF(Y58="",0,Z58+ROW()/10000) -> 5.0058
A59: 2016 | B59: {=SUMPRODUCT((IFERROR(VALUE(LEFT('📋 Inventaire Complet'!$J$3:$J$517,4)),0)=$A59)*('📋 Inventaire Complet'!$B$3:$B$517="Environmental Tech & Digital Mining")*(((COUNTIF($B$6:$B$10,TRUE)=0)+ISNUMBER(IFERROR(MATCH('📋 Inventaire Complet'!$B$3:$B$517,IF($B$6:$B$10,$A$6:$A$10),0),""))>0))*(((COUNTIF($F$6:$F$20,TRUE)=0)+(ISNUMBER(IFERROR(MATCH('📋 Inventaire Complet'!$F$3:$F$517,IF($F$6:$F$19,$E$6:$E$19),0),""))+($F$20*ISNUMBER(MATCH('📋 Inventaire Complet'!$F$3:$F$517,{"D4R";"CEPH";"ISTI";"COLCOM";"HTMR"},0))))>0))*(LEN('📋 Inventaire Complet'!$D$3:$D$517)>0)*(((COUNTIF($H$6:$H$10,TRUE)=0)+(($H$6*ISNUMBER(SEARCH($G$6,'📋 Inventaire Complet'!$L$3:$L$517)))+($H$7*ISNUMBER(SEARCH($G$7,'📋 Inventaire Complet'!$L$3:$L$517)))+($H$8*ISNUMBER(SEARCH($G$8,'📋 Inventaire Complet'!$L$3:$L$517)))+($H$9*ISNUMBER(SEARCH($G$9,'📋 Inventaire Complet'!$L$3:$L$517)))+($H$10*ISNUMBER(SEARCH($G$10,'📋 Inventaire Complet'!$L$3:$L$517))))>0)))} -> 11 | C59: {=SUMPRODUCT((IFERROR(VALUE(LEFT('📋 Inventaire Complet'!$J$3:$J$517,4)),0)=$A59)*('📋 Inventaire Complet'!$B$3:$B$517="Mineral Processing & Strategic Synthesis")*(((COUNTIF($B$6:$B$10,TRUE)=0)+ISNUMBER(IFERROR(MATCH('📋 Inventaire Complet'!$B$3:$B$517,IF($B$6:$B$10,$A$6:$A$10),0),""))>0))*(((COUNTIF($F$6:$F$20,TRUE)=0)+(ISNUMBER(IFERROR(MATCH('📋 Inventaire Complet'!$F$3:$F$517,IF($F$6:$F$19,$E$6:$E$19),0),""))+($F$20*ISNUMBER(MATCH('📋 Inventaire Complet'!$F$3:$F$517,{"D4R";"CEPH";"ISTI";"COLCOM";"HTMR"},0))))>0))*(LEN('📋 Inventaire Complet'!$D$3:$D$517)>0)*(((COUNTIF($H$6:$H$10,TRUE)=0)+(($H$6*ISNUMBER(SEARCH($G$6,'📋 Inventaire Complet'!$L$3:$L$517)))+($H$7*ISNUMBER(SEARCH($G$7,'📋 Inventaire Complet'!$L$3:$L$517)))+($H$8*ISNUMBER(SEARCH($G$8,'📋 Inventaire Complet'!$L$3:$L$517)))+($H$9*ISNUMBER(SEARCH($G$9,'📋 Inventaire Complet'!$L$3:$L$517)))+($H$10*ISNUMBER(SEARCH($G$10,'📋 Inventaire Complet'!$L$3:$L$517))))>0)))} -> 3 | D59: {=SUMPRODUCT((IFERROR(VALUE(LEFT('📋 Inventaire Complet'!$J$3:$J$517,4)),0)=$A59)*('📋 Inventaire Complet'!$B$3:$B$517="Circular Chemistry & Waste Valorization")*(((COUNTIF($B$6:$B$10,TRUE)=0)+ISNUMBER(IFERROR(MATCH('📋 Inventaire Complet'!$B$3:$B$517,IF($B$6:$B$10,$A$6:$A$10),0),""))>0))*(((COUNTIF($F$6:$F$20,TRUE)=0)+(ISNUMBER(IFERROR(MATCH('📋 Inventaire Complet'!$F$3:$F$517,IF($F$6:$F$19,$E$6:$E$19),0),""))+($F$20*ISNUMBER(MATCH('📋 Inventaire Complet'!$F$3:$F$517,{"D4R";"CEPH";"ISTI";"COLCOM";"HTMR"},0))))>0))*(LEN('📋 Inventaire Complet'!$D$3:$D$517)>0)*(((COUNTIF($H$6:$H$10,TRUE)=0)+(($H$6*ISNUMBER(SEARCH($G$6,'📋 Inventaire Complet'!$L$3:$L$517)))+($H$7*ISNUMBER(SEARCH($G$7,'📋 Inventaire Complet'!$L$3:$L$517)))+($H$8*ISNUMBER(SEARCH($G$8,'📋 Inventaire Complet'!$L$3:$L$517)))+($H$9*ISNUMBER(SEARCH($G$9,'📋 Inventaire Complet'!$L$3:$L$517)))+($H$10*ISNUMBER(SEARCH($G$10,'📋 Inventaire Complet'!$L$3:$L$517))))>0)))} -> 1 | E59: {=SUMPRODUCT((IFERROR(VALUE(LEFT('📋 Inventaire Complet'!$J$3:$J$517,4)),0)=$A59)*('📋 Inventaire Complet'!$B$3:$B$517="Green Agriculture & Biotechnology")*(((COUNTIF($B$6:$B$10,TRUE)=0)+ISNUMBER(IFERROR(MATCH('📋 Inventaire Complet'!$B$3:$B$517,IF($B$6:$B$10,$A$6:$A$10),0),""))>0))*(((COUNTIF($F$6:$F$20,TRUE)=0)+(ISNUMBER(IFERROR(MATCH('📋 Inventaire Complet'!$F$3:$F$517,IF($F$6:$F$19,$E$6:$E$19),0),""))+($F$20*ISNUMBER(MATCH('📋 Inventaire Complet'!$F$3:$F$517,{"D4R";"CEPH";"ISTI";"COLCOM";"HTMR"},0))))>0))*(LEN('📋 Inventaire Complet'!$D$3:$D$517)>0)*(((COUNTIF($H$6:$H$10,TRUE)=0)+(($H$6*ISNUMBER(SEARCH($G$6,'📋 Inventaire Complet'!$L$3:$L$517)))+($H$7*ISNUMBER(SEARCH($G$7,'📋 Inventaire Complet'!$L$3:$L$517)))+($H$8*ISNUMBER(SEARCH($G$8,'📋 Inventaire Complet'!$L$3:$L$517)))+($H$9*ISNUMBER(SEARCH($G$9,'📋 Inventaire Complet'!$L$3:$L$517)))+($H$10*ISNUMBER(SEARCH($G$10,'📋 Inventaire Complet'!$L$3:$L$517))))>0)))} -> 4 | F59: {=SUMPRODUCT((IFERROR(VALUE(LEFT('📋 Inventaire Complet'!$J$3:$J$517,4)),0)=$A59)*('📋 Inventaire Complet'!$B$3:$B$517="Sustainable Energy Storage & Management")*(((COUNTIF($B$6:$B$10,TRUE)=0)+ISNUMBER(IFERROR(MATCH('📋 Inventaire Complet'!$B$3:$B$517,IF($B$6:$B$10,$A$6:$A$10),0),""))>0))*(((COUNTIF($F$6:$F$20,TRUE)=0)+(ISNUMBER(IFERROR(MATCH('📋 Inventaire Complet'!$F$3:$F$517,IF($F$6:$F$19,$E$6:$E$19),0),""))+($F$20*ISNUMBER(MATCH('📋 Inventaire Complet'!$F$3:$F$517,{"D4R";"CEPH";"ISTI";"COLCOM";"HTMR"},0))))>0))*(LEN('📋 Inventaire Complet'!$D$3:$D$517)>0)*(((COUNTIF($H$6:$H$10,TRUE)=0)+(($H$6*ISNUMBER(SEARCH($G$6,'📋 Inventaire Complet'!$L$3:$L$517)))+($H$7*ISNUMBER(SEARCH($G$7,'📋 Inventaire Complet'!$L$3:$L$517)))+($H$8*ISNUMBER(SEARCH($G$8,'📋 Inventaire Complet'!$L$3:$L$517)))+($H$9*ISNUMBER(SEARCH($G$9,'📋 Inventaire Complet'!$L$3:$L$517)))+($H$10*ISNUMBER(SEARCH($G$10,'📋 Inventaire Complet'!$L$3:$L$517))))>0)))} -> 2 | G59: =SUM(B59:F59) -> 21 | V59: Recharge, mobilité électrique & réseaux énergétiques | W59: {=SUMPRODUCT(('📋 Inventaire Complet'!$C$3:$C$517=$V59)*(((COUNTIF($B$6:$B$10,TRUE)=0)+ISNUMBER(IFERROR(MATCH('📋 Inventaire Complet'!$B$3:$B$517,IF($B$6:$B$10,$A$6:$A$10),0),""))>0))*(((COUNTIF($D$6:$D$22,TRUE)=0)+ISNUMBER(IFERROR(MATCH(LEFT('📋 Inventaire Complet'!$J$3:$J$517,4),IF($D$6:$D$22,$C$6:$C$22&""),0),""))>0))*(((COUNTIF($F$6:$F$20,TRUE)=0)+(ISNUMBER(IFERROR(MATCH('📋 Inventaire Complet'!$F$3:$F$517,IF($F$6:$F$19,$E$6:$E$19),0),""))+($F$20*ISNUMBER(MATCH('📋 Inventaire Complet'!$F$3:$F$517,{"D4R";"CEPH";"ISTI";"COLCOM";"HTMR"},0))))>0))*(LEN('📋 Inventaire Complet'!$D$3:$D$517)>0)*(((COUNTIF($H$6:$H$10,TRUE)=0)+(($H$6*ISNUMBER(SEARCH($G$6,'📋 Inventaire Complet'!$L$3:$L$517)))+($H$7*ISNUMBER(SEARCH($G$7,'📋 Inventaire Complet'!$L$3:$L$517)))+($H$8*ISNUMBER(SEARCH($G$8,'📋 Inventaire Complet'!$L$3:$L$517)))+($H$9*ISNUMBER(SEARCH($G$9,'📋 Inventaire Complet'!$L$3:$L$517)))+($H$10*ISNUMBER(SEARCH($G$10,'📋 Inventaire Complet'!$L$3:$L$517))))>0)))} -> 3 | X59: =W59+ROW()/10000 -> 3.0059 | Y59: Omar Bourja Yahia ZENNYI Hicham ISLAH | Z59: {=IF(Y59="",0,SUMPRODUCT(('📋 Inventaire Complet'!$E$3:$E$517=Y59)*((COUNTIF($B$6:$B$10,TRUE)=0)+ISNUMBER(IFERROR(MATCH('📋 Inventaire Complet'!$B$3:$B$517,IF($B$6:$B$10,$A$6:$A$10),0),""))>0)*((COUNTIF($D$6:$D$22,TRUE)=0)+ISNUMBER(IFERROR(MATCH(LEFT('📋 Inventaire Complet'!$J$3:$J$517,4),IF($D$6:$D$22,$C$6:$C$22&""),0),""))>0)*((COUNTIF($F$6:$F$20,TRUE)=0)+(ISNUMBER(IFERROR(MATCH('📋 Inventaire Complet'!$F$3:$F$517,IF($F$6:$F$19,$E$6:$E$19),0),""))+($F$20*ISNUMBER(MATCH('📋 Inventaire Complet'!$F$3:$F$517,{"D4R";"CEPH";"ISTI";"COLCOM";"HTMR"},0))))>0)*((COUNTIF($H$6:$H$10,TRUE)=0)+(($H$6*ISNUMBER(SEARCH($G$6,'📋 Inventaire Complet'!$L$3:$L$517)))+($H$7*ISNUMBER(SEARCH($G$7,'📋 Inventaire Complet'!$L$3:$L$517)))+($H$8*ISNUMBER(SEARCH($G$8,'📋 Inventaire Complet'!$L$3:$L$517)))+($H$9*ISNUMBER(SEARCH($G$9,'📋 Inventaire Complet'!$L$3:$L$517)))+($H$10*ISNUMBER(SEARCH($G$10,'📋 Inventaire Complet'!$L$3:$L$517))))>0)))} -> 1 | AA59: =IF(Y59="",0,Z59+ROW()/10000) -> 1.0059
A60: 2017 | B60: {=SUMPRODUCT((IFERROR(VALUE(LEFT('📋 Inventaire Complet'!$J$3:$J$517,4)),0)=$A60)*('📋 Inventaire Complet'!$B$3:$B$517="Environmental Tech & Digital Mining")*(((COUNTIF($B$6:$B$10,TRUE)=0)+ISNUMBER(IFERROR(MATCH('📋 Inventaire Complet'!$B$3:$B$517,IF($B$6:$B$10,$A$6:$A$10),0),""))>0))*(((COUNTIF($F$6:$F$20,TRUE)=0)+(ISNUMBER(IFERROR(MATCH('📋 Inventaire Complet'!$F$3:$F$517,IF($F$6:$F$19,$E$6:$E$19),0),""))+($F$20*ISNUMBER(MATCH('📋 Inventaire Complet'!$F$3:$F$517,{"D4R";"CEPH";"ISTI";"COLCOM";"HTMR"},0))))>0))*(LEN('📋 Inventaire Complet'!$D$3:$D$517)>0)*(((COUNTIF($H$6:$H$10,TRUE)=0)+(($H$6*ISNUMBER(SEARCH($G$6,'📋 Inventaire Complet'!$L$3:$L$517)))+($H$7*ISNUMBER(SEARCH($G$7,'📋 Inventaire Complet'!$L$3:$L$517)))+($H$8*ISNUMBER(SEARCH($G$8,'📋 Inventaire Complet'!$L$3:$L$517)))+($H$9*ISNUMBER(SEARCH($G$9,'📋 Inventaire Complet'!$L$3:$L$517)))+($H$10*ISNUMBER(SEARCH($G$10,'📋 Inventaire Complet'!$L$3:$L$517))))>0)))} -> 9 | C60: {=SUMPRODUCT((IFERROR(VALUE(LEFT('📋 Inventaire Complet'!$J$3:$J$517,4)),0)=$A60)*('📋 Inventaire Complet'!$B$3:$B$517="Mineral Processing & Strategic Synthesis")*(((COUNTIF($B$6:$B$10,TRUE)=0)+ISNUMBER(IFERROR(MATCH('📋 Inventaire Complet'!$B$3:$B$517,IF($B$6:$B$10,$A$6:$A$10),0),""))>0))*(((COUNTIF($F$6:$F$20,TRUE)=0)+(ISNUMBER(IFERROR(MATCH('📋 Inventaire Complet'!$F$3:$F$517,IF($F$6:$F$19,$E$6:$E$19),0),""))+($F$20*ISNUMBER(MATCH('📋 Inventaire Complet'!$F$3:$F$517,{"D4R";"CEPH";"ISTI";"COLCOM";"HTMR"},0))))>0))*(LEN('📋 Inventaire Complet'!$D$3:$D$517)>0)*(((COUNTIF($H$6:$H$10,TRUE)=0)+(($H$6*ISNUMBER(SEARCH($G$6,'📋 Inventaire Complet'!$L$3:$L$517)))+($H$7*ISNUMBER(SEARCH($G$7,'📋 Inventaire Complet'!$L$3:$L$517)))+($H$8*ISNUMBER(SEARCH($G$8,'📋 Inventaire Complet'!$L$3:$L$517)))+($H$9*ISNUMBER(SEARCH($G$9,'📋 Inventaire Complet'!$L$3:$L$517)))+($H$10*ISNUMBER(SEARCH($G$10,'📋 Inventaire Complet'!$L$3:$L$517))))>0)))} -> 1 | D60: {=SUMPRODUCT((IFERROR(VALUE(LEFT('📋 Inventaire Complet'!$J$3:$J$517,4)),0)=$A60)*('📋 Inventaire Complet'!$B$3:$B$517="Circular Chemistry & Waste Valorization")*(((COUNTIF($B$6:$B$10,TRUE)=0)+ISNUMBER(IFERROR(MATCH('📋 Inventaire Complet'!$B$3:$B$517,IF($B$6:$B$10,$A$6:$A$10),0),""))>0))*(((COUNTIF($F$6:$F$20,TRUE)=0)+(ISNUMBER(IFERROR(MATCH('📋 Inventaire Complet'!$F$3:$F$517,IF($F$6:$F$19,$E$6:$E$19),0),""))+($F$20*ISNUMBER(MATCH('📋 Inventaire Complet'!$F$3:$F$517,{"D4R";"CEPH";"ISTI";"COLCOM";"HTMR"},0))))>0))*(LEN('📋 Inventaire Complet'!$D$3:$D$517)>0)*(((COUNTIF($H$6:$H$10,TRUE)=0)+(($H$6*ISNUMBER(SEARCH($G$6,'📋 Inventaire Complet'!$L$3:$L$517)))+($H$7*ISNUMBER(SEARCH($G$7,'📋 Inventaire Complet'!$L$3:$L$517)))+($H$8*ISNUMBER(SEARCH($G$8,'📋 Inventaire Complet'!$L$3:$L$517)))+($H$9*ISNUMBER(SEARCH($G$9,'📋 Inventaire Complet'!$L$3:$L$517)))+($H$10*ISNUMBER(SEARCH($G$10,'📋 Inventaire Complet'!$L$3:$L$517))))>0)))} -> 1 | E60: {=SUMPRODUCT((IFERROR(VALUE(LEFT('📋 Inventaire Complet'!$J$3:$J$517,4)),0)=$A60)*('📋 Inventaire Complet'!$B$3:$B$517="Green Agriculture & Biotechnology")*(((COUNTIF($B$6:$B$10,TRUE)=0)+ISNUMBER(IFERROR(MATCH('📋 Inventaire Complet'!$B$3:$B$517,IF($B$6:$B$10,$A$6:$A$10),0),""))>0))*(((COUNTIF($F$6:$F$20,TRUE)=0)+(ISNUMBER(IFERROR(MATCH('📋 Inventaire Complet'!$F$3:$F$517,IF($F$6:$F$19,$E$6:$E$19),0),""))+($F$20*ISNUMBER(MATCH('📋 Inventaire Complet'!$F$3:$F$517,{"D4R";"CEPH";"ISTI";"COLCOM";"HTMR"},0))))>0))*(LEN('📋 Inventaire Complet'!$D$3:$D$517)>0)*(((COUNTIF($H$6:$H$10,TRUE)=0)+(($H$6*ISNUMBER(SEARCH($G$6,'📋 Inventaire Complet'!$L$3:$L$517)))+($H$7*ISNUMBER(SEARCH($G$7,'📋 Inventaire Complet'!$L$3:$L$517)))+($H$8*ISNUMBER(SEARCH($G$8,'📋 Inventaire Complet'!$L$3:$L$517)))+($H$9*ISNUMBER(SEARCH($G$9,'📋 Inventaire Complet'!$L$3:$L$517)))+($H$10*ISNUMBER(SEARCH($G$10,'📋 Inventaire Complet'!$L$3:$L$517))))>0)))} -> 5 | F60: {=SUMPRODUCT((IFERROR(VALUE(LEFT('📋 Inventaire Complet'!$J$3:$J$517,4)),0)=$A60)*('📋 Inventaire Complet'!$B$3:$B$517="Sustainable Energy Storage & Management")*(((COUNTIF($B$6:$B$10,TRUE)=0)+ISNUMBER(IFERROR(MATCH('📋 Inventaire Complet'!$B$3:$B$517,IF($B$6:$B$10,$A$6:$A$10),0),""))>0))*(((COUNTIF($F$6:$F$20,TRUE)=0)+(ISNUMBER(IFERROR(MATCH('📋 Inventaire Complet'!$F$3:$F$517,IF($F$6:$F$19,$E$6:$E$19),0),""))+($F$20*ISNUMBER(MATCH('📋 Inventaire Complet'!$F$3:$F$517,{"D4R";"CEPH";"ISTI";"COLCOM";"HTMR"},0))))>0))*(LEN('📋 Inventaire Complet'!$D$3:$D$517)>0)*(((COUNTIF($H$6:$H$10,TRUE)=0)+(($H$6*ISNUMBER(SEARCH($G$6,'📋 Inventaire Complet'!$L$3:$L$517)))+($H$7*ISNUMBER(SEARCH($G$7,'📋 Inventaire Complet'!$L$3:$L$517)))+($H$8*ISNUMBER(SEARCH($G$8,'📋 Inventaire Complet'!$L$3:$L$517)))+($H$9*ISNUMBER(SEARCH($G$9,'📋 Inventaire Complet'!$L$3:$L$517)))+($H$10*ISNUMBER(SEARCH($G$10,'📋 Inventaire Complet'!$L$3:$L$517))))>0)))} -> 0 | G60: =SUM(B60:F60) -> 16 | V60: Stockage thermique & matériaux céramiques | W60: {=SUMPRODUCT(('📋 Inventaire Complet'!$C$3:$C$517=$V60)*(((COUNTIF($B$6:$B$10,TRUE)=0)+ISNUMBER(IFERROR(MATCH('📋 Inventaire Complet'!$B$3:$B$517,IF($B$6:$B$10,$A$6:$A$10),0),""))>0))*(((COUNTIF($D$6:$D$22,TRUE)=0)+ISNUMBER(IFERROR(MATCH(LEFT('📋 Inventaire Complet'!$J$3:$J$517,4),IF($D$6:$D$22,$C$6:$C$22&""),0),""))>0))*(((COUNTIF($F$6:$F$20,TRUE)=0)+(ISNUMBER(IFERROR(MATCH('📋 Inventaire Complet'!$F$3:$F$517,IF($F$6:$F$19,$E$6:$E$19),0),""))+($F$20*ISNUMBER(MATCH('📋 Inventaire Complet'!$F$3:$F$517,{"D4R";"CEPH";"ISTI";"COLCOM";"HTMR"},0))))>0))*(LEN('📋 Inventaire Complet'!$D$3:$D$517)>0)*(((COUNTIF($H$6:$H$10,TRUE)=0)+(($H$6*ISNUMBER(SEARCH($G$6,'📋 Inventaire Complet'!$L$3:$L$517)))+($H$7*ISNUMBER(SEARCH($G$7,'📋 Inventaire Complet'!$L$3:$L$517)))+($H$8*ISNUMBER(SEARCH($G$8,'📋 Inventaire Complet'!$L$3:$L$517)))+($H$9*ISNUMBER(SEARCH($G$9,'📋 Inventaire Complet'!$L$3:$L$517)))+($H$10*ISNUMBER(SEARCH($G$10,'📋 Inventaire Complet'!$L$3:$L$517))))>0)))} -> 3 | X60: =W60+ROW()/10000 -> 3.006 | Y60: Bourja, BOANARIJESY , Zennayi | Z60: {=IF(Y60="",0,SUMPRODUCT(('📋 Inventaire Complet'!$E$3:$E$517=Y60)*((COUNTIF($B$6:$B$10,TRUE)=0)+ISNUMBER(IFERROR(MATCH('📋 Inventaire Complet'!$B$3:$B$517,IF($B$6:$B$10,$A$6:$A$10),0),""))>0)*((COUNTIF($D$6:$D$22,TRUE)=0)+ISNUMBER(IFERROR(MATCH(LEFT('📋 Inventaire Complet'!$J$3:$J$517,4),IF($D$6:$D$22,$C$6:$C$22&""),0),""))>0)*((COUNTIF($F$6:$F$20,TRUE)=0)+(ISNUMBER(IFERROR(MATCH('📋 Inventaire Complet'!$F$3:$F$517,IF($F$6:$F$19,$E$6:$E$19),0),""))+($F$20*ISNUMBER(MATCH('📋 Inventaire Complet'!$F$3:$F$517,{"D4R";"CEPH";"ISTI";"COLCOM";"HTMR"},0))))>0)*((COUNTIF($H$6:$H$10,TRUE)=0)+(($H$6*ISNUMBER(SEARCH($G$6,'📋 Inventaire Complet'!$L$3:$L$517)))+($H$7*ISNUMBER(SEARCH($G$7,'📋 Inventaire Complet'!$L$3:$L$517)))+($H$8*ISNUMBER(SEARCH($G$8,'📋 Inventaire Complet'!$L$3:$L$517)))+($H$9*ISNUMBER(SEARCH($G$9,'📋 Inventaire Complet'!$L$3:$L$517)))+($H$10*ISNUMBER(SEARCH($G$10,'📋 Inventaire Complet'!$L$3:$L$517))))>0)))} -> 1 | AA60: =IF(Y60="",0,Z60+ROW()/10000) -> 1.006
A61: 2018 | B61: {=SUMPRODUCT((IFERROR(VALUE(LEFT('📋 Inventaire Complet'!$J$3:$J$517,4)),0)=$A61)*('📋 Inventaire Complet'!$B$3:$B$517="Environmental Tech & Digital Mining")*(((COUNTIF($B$6:$B$10,TRUE)=0)+ISNUMBER(IFERROR(MATCH('📋 Inventaire Complet'!$B$3:$B$517,IF($B$6:$B$10,$A$6:$A$10),0),""))>0))*(((COUNTIF($F$6:$F$20,TRUE)=0)+(ISNUMBER(IFERROR(MATCH('📋 Inventaire Complet'!$F$3:$F$517,IF($F$6:$F$19,$E$6:$E$19),0),""))+($F$20*ISNUMBER(MATCH('📋 Inventaire Complet'!$F$3:$F$517,{"D4R";"CEPH";"ISTI";"COLCOM";"HTMR"},0))))>0))*(LEN('📋 Inventaire Complet'!$D$3:$D$517)>0)*(((COUNTIF($H$6:$H$10,TRUE)=0)+(($H$6*ISNUMBER(SEARCH($G$6,'📋 Inventaire Complet'!$L$3:$L$517)))+($H$7*ISNUMBER(SEARCH($G$7,'📋 Inventaire Complet'!$L$3:$L$517)))+($H$8*ISNUMBER(SEARCH($G$8,'📋 Inventaire Complet'!$L$3:$L$517)))+($H$9*ISNUMBER(SEARCH($G$9,'📋 Inventaire Complet'!$L$3:$L$517)))+($H$10*ISNUMBER(SEARCH($G$10,'📋 Inventaire Complet'!$L$3:$L$517))))>0)))} -> 6 | C61: {=SUMPRODUCT((IFERROR(VALUE(LEFT('📋 Inventaire Complet'!$J$3:$J$517,4)),0)=$A61)*('📋 Inventaire Complet'!$B$3:$B$517="Mineral Processing & Strategic Synthesis")*(((COUNTIF($B$6:$B$10,TRUE)=0)+ISNUMBER(IFERROR(MATCH('📋 Inventaire Complet'!$B$3:$B$517,IF($B$6:$B$10,$A$6:$A$10),0),""))>0))*(((COUNTIF($F$6:$F$20,TRUE)=0)+(ISNUMBER(IFERROR(MATCH('📋 Inventaire Complet'!$F$3:$F$517,IF($F$6:$F$19,$E$6:$E$19),0),""))+($F$20*ISNUMBER(MATCH('📋 Inventaire Complet'!$F$3:$F$517,{"D4R";"CEPH";"ISTI";"COLCOM";"HTMR"},0))))>0))*(LEN('📋 Inventaire Complet'!$D$3:$D$517)>0)*(((COUNTIF($H$6:$H$10,TRUE)=0)+(($H$6*ISNUMBER(SEARCH($G$6,'📋 Inventaire Complet'!$L$3:$L$517)))+($H$7*ISNUMBER(SEARCH($G$7,'📋 Inventaire Complet'!$L$3:$L$517)))+($H$8*ISNUMBER(SEARCH($G$8,'📋 Inventaire Complet'!$L$3:$L$517)))+($H$9*ISNUMBER(SEARCH($G$9,'📋 Inventaire Complet'!$L$3:$L$517)))+($H$10*ISNUMBER(SEARCH($G$10,'📋 Inventaire Complet'!$L$3:$L$517))))>0)))} -> 2 | D61: {=SUMPRODUCT((IFERROR(VALUE(LEFT('📋 Inventaire Complet'!$J$3:$J$517,4)),0)=$A61)*('📋 Inventaire Complet'!$B$3:$B$517="Circular Chemistry & Waste Valorization")*(((COUNTIF($B$6:$B$10,TRUE)=0)+ISNUMBER(IFERROR(MATCH('📋 Inventaire Complet'!$B$3:$B$517,IF($B$6:$B$10,$A$6:$A$10),0),""))>0))*(((COUNTIF($F$6:$F$20,TRUE)=0)+(ISNUMBER(IFERROR(MATCH('📋 Inventaire Complet'!$F$3:$F$517,IF($F$6:$F$19,$E$6:$E$19),0),""))+($F$20*ISNUMBER(MATCH('📋 Inventaire Complet'!$F$3:$F$517,{"D4R";"CEPH";"ISTI";"COLCOM";"HTMR"},0))))>0))*(LEN('📋 Inventaire Complet'!$D$3:$D$517)>0)*(((COUNTIF($H$6:$H$10,TRUE)=0)+(($H$6*ISNUMBER(SEARCH($G$6,'📋 Inventaire Complet'!$L$3:$L$517)))+($H$7*ISNUMBER(SEARCH($G$7,'📋 Inventaire Complet'!$L$3:$L$517)))+($H$8*ISNUMBER(SEARCH($G$8,'📋 Inventaire Complet'!$L$3:$L$517)))+($H$9*ISNUMBER(SEARCH($G$9,'📋 Inventaire Complet'!$L$3:$L$517)))+($H$10*ISNUMBER(SEARCH($G$10,'📋 Inventaire Complet'!$L$3:$L$517))))>0)))} -> 2 | E61: {=SUMPRODUCT((IFERROR(VALUE(LEFT('📋 Inventaire Complet'!$J$3:$J$517,4)),0)=$A61)*('📋 Inventaire Complet'!$B$3:$B$517="Green Agriculture & Biotechnology")*(((COUNTIF($B$6:$B$10,TRUE)=0)+ISNUMBER(IFERROR(MATCH('📋 Inventaire Complet'!$B$3:$B$517,IF($B$6:$B$10,$A$6:$A$10),0),""))>0))*(((COUNTIF($F$6:$F$20,TRUE)=0)+(ISNUMBER(IFERROR(MATCH('📋 Inventaire Complet'!$F$3:$F$517,IF($F$6:$F$19,$E$6:$E$19),0),""))+($F$20*ISNUMBER(MATCH('📋 Inventaire Complet'!$F$3:$F$517,{"D4R";"CEPH";"ISTI";"COLCOM";"HTMR"},0))))>0))*(LEN('📋 Inventaire Complet'!$D$3:$D$517)>0)*(((COUNTIF($H$6:$H$10,TRUE)=0)+(($H$6*ISNUMBER(SEARCH($G$6,'📋 Inventaire Complet'!$L$3:$L$517)))+($H$7*ISNUMBER(SEARCH($G$7,'📋 Inventaire Complet'!$L$3:$L$517)))+($H$8*ISNUMBER(SEARCH($G$8,'📋 Inventaire Complet'!$L$3:$L$517)))+($H$9*ISNUMBER(SEARCH($G$9,'📋 Inventaire Complet'!$L$3:$L$517)))+($H$10*ISNUMBER(SEARCH($G$10,'📋 Inventaire Complet'!$L$3:$L$517))))>0)))} -> 0 | F61: {=SUMPRODUCT((IFERROR(VALUE(LEFT('📋 Inventaire Complet'!$J$3:$J$517,4)),0)=$A61)*('📋 Inventaire Complet'!$B$3:$B$517="Sustainable Energy Storage & Management")*(((COUNTIF($B$6:$B$10,TRUE)=0)+ISNUMBER(IFERROR(MATCH('📋 Inventaire Complet'!$B$3:$B$517,IF($B$6:$B$10,$A$6:$A$10),0),""))>0))*(((COUNTIF($F$6:$F$20,TRUE)=0)+(ISNUMBER(IFERROR(MATCH('📋 Inventaire Complet'!$F$3:$F$517,IF($F$6:$F$19,$E$6:$E$19),0),""))+($F$20*ISNUMBER(MATCH('📋 Inventaire Complet'!$F$3:$F$517,{"D4R";"CEPH";"ISTI";"COLCOM";"HTMR"},0))))>0))*(LEN('📋 Inventaire Complet'!$D$3:$D$517)>0)*(((COUNTIF($H$6:$H$10,TRUE)=0)+(($H$6*ISNUMBER(SEARCH($G$6,'📋 Inventaire Complet'!$L$3:$L$517)))+($H$7*ISNUMBER(SEARCH($G$7,'📋 Inventaire Complet'!$L$3:$L$517)))+($H$8*ISNUMBER(SEARCH($G$8,'📋 Inventaire Complet'!$L$3:$L$517)))+($H$9*ISNUMBER(SEARCH($G$9,'📋 Inventaire Complet'!$L$3:$L$517)))+($H$10*ISNUMBER(SEARCH($G$10,'📋 Inventaire Complet'!$L$3:$L$517))))>0)))} -> 0 | G61: =SUM(B61:F61) -> 10 | V61: Synthèse LFP/FePO4 & matériaux actifs phosphatés | W61: {=SUMPRODUCT(('📋 Inventaire Complet'!$C$3:$C$517=$V61)*(((COUNTIF($B$6:$B$10,TRUE)=0)+ISNUMBER(IFERROR(MATCH('📋 Inventaire Complet'!$B$3:$B$517,IF($B$6:$B$10,$A$6:$A$10),0),""))>0))*(((COUNTIF($D$6:$D$22,TRUE)=0)+ISNUMBER(IFERROR(MATCH(LEFT('📋 Inventaire Complet'!$J$3:$J$517,4),IF($D$6:$D$22,$C$6:$C$22&""),0),""))>0))*(((COUNTIF($F$6:$F$20,TRUE)=0)+(ISNUMBER(IFERROR(MATCH('📋 Inventaire Complet'!$F$3:$F$517,IF($F$6:$F$19,$E$6:$E$19),0),""))+($F$20*ISNUMBER(MATCH('📋 Inventaire Complet'!$F$3:$F$517,{"D4R";"CEPH";"ISTI";"COLCOM";"HTMR"},0))))>0))*(LEN('📋 Inventaire Complet'!$D$3:$D$517)>0)*(((COUNTIF($H$6:$H$10,TRUE)=0)+(($H$6*ISNUMBER(SEARCH($G$6,'📋 Inventaire Complet'!$L$3:$L$517)))+($H$7*ISNUMBER(SEARCH($G$7,'📋 Inventaire Complet'!$L$3:$L$517)))+($H$8*ISNUMBER(SEARCH($G$8,'📋 Inventaire Complet'!$L$3:$L$517)))+($H$9*ISNUMBER(SEARCH($G$9,'📋 Inventaire Complet'!$L$3:$L$517)))+($H$10*ISNUMBER(SEARCH($G$10,'📋 Inventaire Complet'!$L$3:$L$517))))>0)))} -> 2 | X61: =W61+ROW()/10000 -> 2.0061 | Y61: ZENNAYI, BOURZEIX, BOURJA | Z61: {=IF(Y61="",0,SUMPRODUCT(('📋 Inventaire Complet'!$E$3:$E$517=Y61)*((COUNTIF($B$6:$B$10,TRUE)=0)+ISNUMBER(IFERROR(MATCH('📋 Inventaire Complet'!$B$3:$B$517,IF($B$6:$B$10,$A$6:$A$10),0),""))>0)*((COUNTIF($D$6:$D$22,TRUE)=0)+ISNUMBER(IFERROR(MATCH(LEFT('📋 Inventaire Complet'!$J$3:$J$517,4),IF($D$6:$D$22,$C$6:$C$22&""),0),""))>0)*((COUNTIF($F$6:$F$20,TRUE)=0)+(ISNUMBER(IFERROR(MATCH('📋 Inventaire Complet'!$F$3:$F$517,IF($F$6:$F$19,$E$6:$E$19),0),""))+($F$20*ISNUMBER(MATCH('📋 Inventaire Complet'!$F$3:$F$517,{"D4R";"CEPH";"ISTI";"COLCOM";"HTMR"},0))))>0)*((COUNTIF($H$6:$H$10,TRUE)=0)+(($H$6*ISNUMBER(SEARCH($G$6,'📋 Inventaire Complet'!$L$3:$L$517)))+($H$7*ISNUMBER(SEARCH($G$7,'📋 Inventaire Complet'!$L$3:$L$517)))+($H$8*ISNUMBER(SEARCH($G$8,'📋 Inventaire Complet'!$L$3:$L$517)))+($H$9*ISNUMBER(SEARCH($G$9,'📋 Inventaire Complet'!$L$3:$L$517)))+($H$10*ISNUMBER(SEARCH($G$10,'📋 Inventaire Complet'!$L$3:$L$517))))>0)))} -> 1 | AA61: =IF(Y61="",0,Z61+ROW()/10000) -> 1.0061
A62: 2019 | B62: {=SUMPRODUCT((IFERROR(VALUE(LEFT('📋 Inventaire Complet'!$J$3:$J$517,4)),0)=$A62)*('📋 Inventaire Complet'!$B$3:$B$517="Environmental Tech & Digital Mining")*(((COUNTIF($B$6:$B$10,TRUE)=0)+ISNUMBER(IFERROR(MATCH('📋 Inventaire Complet'!$B$3:$B$517,IF($B$6:$B$10,$A$6:$A$10),0),""))>0))*(((COUNTIF($F$6:$F$20,TRUE)=0)+(ISNUMBER(IFERROR(MATCH('📋 Inventaire Complet'!$F$3:$F$517,IF($F$6:$F$19,$E$6:$E$19),0),""))+($F$20*ISNUMBER(MATCH('📋 Inventaire Complet'!$F$3:$F$517,{"D4R";"CEPH";"ISTI";"COLCOM";"HTMR"},0))))>0))*(LEN('📋 Inventaire Complet'!$D$3:$D$517)>0)*(((COUNTIF($H$6:$H$10,TRUE)=0)+(($H$6*ISNUMBER(SEARCH($G$6,'📋 Inventaire Complet'!$L$3:$L$517)))+($H$7*ISNUMBER(SEARCH($G$7,'📋 Inventaire Complet'!$L$3:$L$517)))+($H$8*ISNUMBER(SEARCH($G$8,'📋 Inventaire Complet'!$L$3:$L$517)))+($H$9*ISNUMBER(SEARCH($G$9,'📋 Inventaire Complet'!$L$3:$L$517)))+($H$10*ISNUMBER(SEARCH($G$10,'📋 Inventaire Complet'!$L$3:$L$517))))>0)))} -> 8 | C62: {=SUMPRODUCT((IFERROR(VALUE(LEFT('📋 Inventaire Complet'!$J$3:$J$517,4)),0)=$A62)*('📋 Inventaire Complet'!$B$3:$B$517="Mineral Processing & Strategic Synthesis")*(((COUNTIF($B$6:$B$10,TRUE)=0)+ISNUMBER(IFERROR(MATCH('📋 Inventaire Complet'!$B$3:$B$517,IF($B$6:$B$10,$A$6:$A$10),0),""))>0))*(((COUNTIF($F$6:$F$20,TRUE)=0)+(ISNUMBER(IFERROR(MATCH('📋 Inventaire Complet'!$F$3:$F$517,IF($F$6:$F$19,$E$6:$E$19),0),""))+($F$20*ISNUMBER(MATCH('📋 Inventaire Complet'!$F$3:$F$517,{"D4R";"CEPH";"ISTI";"COLCOM";"HTMR"},0))))>0))*(LEN('📋 Inventaire Complet'!$D$3:$D$517)>0)*(((COUNTIF($H$6:$H$10,TRUE)=0)+(($H$6*ISNUMBER(SEARCH($G$6,'📋 Inventaire Complet'!$L$3:$L$517)))+($H$7*ISNUMBER(SEARCH($G$7,'📋 Inventaire Complet'!$L$3:$L$517)))+($H$8*ISNUMBER(SEARCH($G$8,'📋 Inventaire Complet'!$L$3:$L$517)))+($H$9*ISNUMBER(SEARCH($G$9,'📋 Inventaire Complet'!$L$3:$L$517)))+($H$10*ISNUMBER(SEARCH($G$10,'📋 Inventaire Complet'!$L$3:$L$517))))>0)))} -> 5 | D62: {=SUMPRODUCT((IFERROR(VALUE(LEFT('📋 Inventaire Complet'!$J$3:$J$517,4)),0)=$A62)*('📋 Inventaire Complet'!$B$3:$B$517="Circular Chemistry & Waste Valorization")*(((COUNTIF($B$6:$B$10,TRUE)=0)+ISNUMBER(IFERROR(MATCH('📋 Inventaire Complet'!$B$3:$B$517,IF($B$6:$B$10,$A$6:$A$10),0),""))>0))*(((COUNTIF($F$6:$F$20,TRUE)=0)+(ISNUMBER(IFERROR(MATCH('📋 Inventaire Complet'!$F$3:$F$517,IF($F$6:$F$19,$E$6:$E$19),0),""))+($F$20*ISNUMBER(MATCH('📋 Inventaire Complet'!$F$3:$F$517,{"D4R";"CEPH";"ISTI";"COLCOM";"HTMR"},0))))>0))*(LEN('📋 Inventaire Complet'!$D$3:$D$517)>0)*(((COUNTIF($H$6:$H$10,TRUE)=0)+(($H$6*ISNUMBER(SEARCH($G$6,'📋 Inventaire Complet'!$L$3:$L$517)))+($H$7*ISNUMBER(SEARCH($G$7,'📋 Inventaire Complet'!$L$3:$L$517)))+($H$8*ISNUMBER(SEARCH($G$8,'📋 Inventaire Complet'!$L$3:$L$517)))+($H$9*ISNUMBER(SEARCH($G$9,'📋 Inventaire Complet'!$L$3:$L$517)))+($H$10*ISNUMBER(SEARCH($G$10,'📋 Inventaire Complet'!$L$3:$L$517))))>0)))} -> 0 | E62: {=SUMPRODUCT((IFERROR(VALUE(LEFT('📋 Inventaire Complet'!$J$3:$J$517,4)),0)=$A62)*('📋 Inventaire Complet'!$B$3:$B$517="Green Agriculture & Biotechnology")*(((COUNTIF($B$6:$B$10,TRUE)=0)+ISNUMBER(IFERROR(MATCH('📋 Inventaire Complet'!$B$3:$B$517,IF($B$6:$B$10,$A$6:$A$10),0),""))>0))*(((COUNTIF($F$6:$F$20,TRUE)=0)+(ISNUMBER(IFERROR(MATCH('📋 Inventaire Complet'!$F$3:$F$517,IF($F$6:$F$19,$E$6:$E$19),0),""))+($F$20*ISNUMBER(MATCH('📋 Inventaire Complet'!$F$3:$F$517,{"D4R";"CEPH";"ISTI";"COLCOM";"HTMR"},0))))>0))*(LEN('📋 Inventaire Complet'!$D$3:$D$517)>0)*(((COUNTIF($H$6:$H$10,TRUE)=0)+(($H$6*ISNUMBER(SEARCH($G$6,'📋 Inventaire Complet'!$L$3:$L$517)))+($H$7*ISNUMBER(SEARCH($G$7,'📋 Inventaire Complet'!$L$3:$L$517)))+($H$8*ISNUMBER(SEARCH($G$8,'📋 Inventaire Complet'!$L$3:$L$517)))+($H$9*ISNUMBER(SEARCH($G$9,'📋 Inventaire Complet'!$L$3:$L$517)))+($H$10*ISNUMBER(SEARCH($G$10,'📋 Inventaire Complet'!$L$3:$L$517))))>0)))} -> 2 | F62: {=SUMPRODUCT((IFERROR(VALUE(LEFT('📋 Inventaire Complet'!$J$3:$J$517,4)),0)=$A62)*('📋 Inventaire Complet'!$B$3:$B$517="Sustainable Energy Storage & Management")*(((COUNTIF($B$6:$B$10,TRUE)=0)+ISNUMBER(IFERROR(MATCH('📋 Inventaire Complet'!$B$3:$B$517,IF($B$6:$B$10,$A$6:$A$10),0),""))>0))*(((COUNTIF($F$6:$F$20,TRUE)=0)+(ISNUMBER(IFERROR(MATCH('📋 Inventaire Complet'!$F$3:$F$517,IF($F$6:$F$19,$E$6:$E$19),0),""))+($F$20*ISNUMBER(MATCH('📋 Inventaire Complet'!$F$3:$F$517,{"D4R";"CEPH";"ISTI";"COLCOM";"HTMR"},0))))>0))*(LEN('📋 Inventaire Complet'!$D$3:$D$517)>0)*(((COUNTIF($H$6:$H$10,TRUE)=0)+(($H$6*ISNUMBER(SEARCH($G$6,'📋 Inventaire Complet'!$L$3:$L$517)))+($H$7*ISNUMBER(SEARCH($G$7,'📋 Inventaire Complet'!$L$3:$L$517)))+($H$8*ISNUMBER(SEARCH($G$8,'📋 Inventaire Complet'!$L$3:$L$517)))+($H$9*ISNUMBER(SEARCH($G$9,'📋 Inventaire Complet'!$L$3:$L$517)))+($H$10*ISNUMBER(SEARCH($G$10,'📋 Inventaire Complet'!$L$3:$L$517))))>0)))} -> 0 | G62: =SUM(B62:F62) -> 15 | W62: {=SUMPRODUCT(('📋 Inventaire Complet'!$C$3:$C$517=$V62)*(((COUNTIF($B$6:$B$10,TRUE)=0)+ISNUMBER(IFERROR(MATCH('📋 Inventaire Complet'!$B$3:$B$517,IF($B$6:$B$10,$A$6:$A$10),0),""))>0))*(((COUNTIF($D$6:$D$22,TRUE)=0)+ISNUMBER(IFERROR(MATCH(LEFT('📋 Inventaire Complet'!$J$3:$J$517,4),IF($D$6:$D$22,$C$6:$C$22&""),0),""))>0))*(((COUNTIF($F$6:$F$20,TRUE)=0)+(ISNUMBER(IFERROR(MATCH('📋 Inventaire Complet'!$F$3:$F$517,IF($F$6:$F$19,$E$6:$E$19),0),""))+($F$20*ISNUMBER(MATCH('📋 Inventaire Complet'!$F$3:$F$517,{"D4R";"CEPH";"ISTI";"COLCOM";"HTMR"},0))))>0))*(LEN('📋 Inventaire Complet'!$D$3:$D$517)>0)*(((COUNTIF($H$6:$H$10,TRUE)=0)+(($H$6*ISNUMBER(SEARCH($G$6,'📋 Inventaire Complet'!$L$3:$L$517)))+($H$7*ISNUMBER(SEARCH($G$7,'📋 Inventaire Complet'!$L$3:$L$517)))+($H$8*ISNUMBER(SEARCH($G$8,'📋 Inventaire Complet'!$L$3:$L$517)))+($H$9*ISNUMBER(SEARCH($G$9,'📋 Inventaire Complet'!$L$3:$L$517)))+($H$10*ISNUMBER(SEARCH($G$10,'📋 Inventaire Complet'!$L$3:$L$517))))>0)))} -> 2 | X62: =W62+ROW()/10000 -> 2.0062 | Y62: BOURJA, BOURZEIX, SAFAA | Z62: {=IF(Y62="",0,SUMPRODUCT(('📋 Inventaire Complet'!$E$3:$E$517=Y62)*((COUNTIF($B$6:$B$10,TRUE)=0)+ISNUMBER(IFERROR(MATCH('📋 Inventaire Complet'!$B$3:$B$517,IF($B$6:$B$10,$A$6:$A$10),0),""))>0)*((COUNTIF($D$6:$D$22,TRUE)=0)+ISNUMBER(IFERROR(MATCH(LEFT('📋 Inventaire Complet'!$J$3:$J$517,4),IF($D$6:$D$22,$C$6:$C$22&""),0),""))>0)*((COUNTIF($F$6:$F$20,TRUE)=0)+(ISNUMBER(IFERROR(MATCH('📋 Inventaire Complet'!$F$3:$F$517,IF($F$6:$F$19,$E$6:$E$19),0),""))+($F$20*ISNUMBER(MATCH('📋 Inventaire Complet'!$F$3:$F$517,{"D4R";"CEPH";"ISTI";"COLCOM";"HTMR"},0))))>0)*((COUNTIF($H$6:$H$10,TRUE)=0)+(($H$6*ISNUMBER(SEARCH($G$6,'📋 Inventaire Complet'!$L$3:$L$517)))+($H$7*ISNUMBER(SEARCH($G$7,'📋 Inventaire Complet'!$L$3:$L$517)))+($H$8*ISNUMBER(SEARCH($G$8,'📋 Inventaire Complet'!$L$3:$L$517)))+($H$9*ISNUMBER(SEARCH($G$9,'📋 Inventaire Complet'!$L$3:$L$517)))+($H$10*ISNUMBER(SEARCH($G$10,'📋 Inventaire Complet'!$L$3:$L$517))))>0)))} -> 1 | AA62: =IF(Y62="",0,Z62+ROW()/10000) -> 1.0062
A63: 2020 | B63: {=SUMPRODUCT((IFERROR(VALUE(LEFT('📋 Inventaire Complet'!$J$3:$J$517,4)),0)=$A63)*('📋 Inventaire Complet'!$B$3:$B$517="Environmental Tech & Digital Mining")*(((COUNTIF($B$6:$B$10,TRUE)=0)+ISNUMBER(IFERROR(MATCH('📋 Inventaire Complet'!$B$3:$B$517,IF($B$6:$B$10,$A$6:$A$10),0),""))>0))*(((COUNTIF($F$6:$F$20,TRUE)=0)+(ISNUMBER(IFERROR(MATCH('📋 Inventaire Complet'!$F$3:$F$517,IF($F$6:$F$19,$E$6:$E$19),0),""))+($F$20*ISNUMBER(MATCH('📋 Inventaire Complet'!$F$3:$F$517,{"D4R";"CEPH";"ISTI";"COLCOM";"HTMR"},0))))>0))*(LEN('📋 Inventaire Complet'!$D$3:$D$517)>0)*(((COUNTIF($H$6:$H$10,TRUE)=0)+(($H$6*ISNUMBER(SEARCH($G$6,'📋 Inventaire Complet'!$L$3:$L$517)))+($H$7*ISNUMBER(SEARCH($G$7,'📋 Inventaire Complet'!$L$3:$L$517)))+($H$8*ISNUMBER(SEARCH($G$8,'📋 Inventaire Complet'!$L$3:$L$517)))+($H$9*ISNUMBER(SEARCH($G$9,'📋 Inventaire Complet'!$L$3:$L$517)))+($H$10*ISNUMBER(SEARCH($G$10,'📋 Inventaire Complet'!$L$3:$L$517))))>0)))} -> 6 | C63: {=SUMPRODUCT((IFERROR(VALUE(LEFT('📋 Inventaire Complet'!$J$3:$J$517,4)),0)=$A63)*('📋 Inventaire Complet'!$B$3:$B$517="Mineral Processing & Strategic Synthesis")*(((COUNTIF($B$6:$B$10,TRUE)=0)+ISNUMBER(IFERROR(MATCH('📋 Inventaire Complet'!$B$3:$B$517,IF($B$6:$B$10,$A$6:$A$10),0),""))>0))*(((COUNTIF($F$6:$F$20,TRUE)=0)+(ISNUMBER(IFERROR(MATCH('📋 Inventaire Complet'!$F$3:$F$517,IF($F$6:$F$19,$E$6:$E$19),0),""))+($F$20*ISNUMBER(MATCH('📋 Inventaire Complet'!$F$3:$F$517,{"D4R";"CEPH";"ISTI";"COLCOM";"HTMR"},0))))>0))*(LEN('📋 Inventaire Complet'!$D$3:$D$517)>0)*(((COUNTIF($H$6:$H$10,TRUE)=0)+(($H$6*ISNUMBER(SEARCH($G$6,'📋 Inventaire Complet'!$L$3:$L$517)))+($H$7*ISNUMBER(SEARCH($G$7,'📋 Inventaire Complet'!$L$3:$L$517)))+($H$8*ISNUMBER(SEARCH($G$8,'📋 Inventaire Complet'!$L$3:$L$517)))+($H$9*ISNUMBER(SEARCH($G$9,'📋 Inventaire Complet'!$L$3:$L$517)))+($H$10*ISNUMBER(SEARCH($G$10,'📋 Inventaire Complet'!$L$3:$L$517))))>0)))} -> 0 | D63: {=SUMPRODUCT((IFERROR(VALUE(LEFT('📋 Inventaire Complet'!$J$3:$J$517,4)),0)=$A63)*('📋 Inventaire Complet'!$B$3:$B$517="Circular Chemistry & Waste Valorization")*(((COUNTIF($B$6:$B$10,TRUE)=0)+ISNUMBER(IFERROR(MATCH('📋 Inventaire Complet'!$B$3:$B$517,IF($B$6:$B$10,$A$6:$A$10),0),""))>0))*(((COUNTIF($F$6:$F$20,TRUE)=0)+(ISNUMBER(IFERROR(MATCH('📋 Inventaire Complet'!$F$3:$F$517,IF($F$6:$F$19,$E$6:$E$19),0),""))+($F$20*ISNUMBER(MATCH('📋 Inventaire Complet'!$F$3:$F$517,{"D4R";"CEPH";"ISTI";"COLCOM";"HTMR"},0))))>0))*(LEN('📋 Inventaire Complet'!$D$3:$D$517)>0)*(((COUNTIF($H$6:$H$10,TRUE)=0)+(($H$6*ISNUMBER(SEARCH($G$6,'📋 Inventaire Complet'!$L$3:$L$517)))+($H$7*ISNUMBER(SEARCH($G$7,'📋 Inventaire Complet'!$L$3:$L$517)))+($H$8*ISNUMBER(SEARCH($G$8,'📋 Inventaire Complet'!$L$3:$L$517)))+($H$9*ISNUMBER(SEARCH($G$9,'📋 Inventaire Complet'!$L$3:$L$517)))+($H$10*ISNUMBER(SEARCH($G$10,'📋 Inventaire Complet'!$L$3:$L$517))))>0)))} -> 2 | E63: {=SUMPRODUCT((IFERROR(VALUE(LEFT('📋 Inventaire Complet'!$J$3:$J$517,4)),0)=$A63)*('📋 Inventaire Complet'!$B$3:$B$517="Green Agriculture & Biotechnology")*(((COUNTIF($B$6:$B$10,TRUE)=0)+ISNUMBER(IFERROR(MATCH('📋 Inventaire Complet'!$B$3:$B$517,IF($B$6:$B$10,$A$6:$A$10),0),""))>0))*(((COUNTIF($F$6:$F$20,TRUE)=0)+(ISNUMBER(IFERROR(MATCH('📋 Inventaire Complet'!$F$3:$F$517,IF($F$6:$F$19,$E$6:$E$19),0),""))+($F$20*ISNUMBER(MATCH('📋 Inventaire Complet'!$F$3:$F$517,{"D4R";"CEPH";"ISTI";"COLCOM";"HTMR"},0))))>0))*(LEN('📋 Inventaire Complet'!$D$3:$D$517)>0)*(((COUNTIF($H$6:$H$10,TRUE)=0)+(($H$6*ISNUMBER(SEARCH($G$6,'📋 Inventaire Complet'!$L$3:$L$517)))+($H$7*ISNUMBER(SEARCH($G$7,'📋 Inventaire Complet'!$L$3:$L$517)))+($H$8*ISNUMBER(SEARCH($G$8,'📋 Inventaire Complet'!$L$3:$L$517)))+($H$9*ISNUMBER(SEARCH($G$9,'📋 Inventaire Complet'!$L$3:$L$517)))+($H$10*ISNUMBER(SEARCH($G$10,'📋 Inventaire Complet'!$L$3:$L$517))))>0)))} -> 2 | F63: {=SUMPRODUCT((IFERROR(VALUE(LEFT('📋 Inventaire Complet'!$J$3:$J$517,4)),0)=$A63)*('📋 Inventaire Complet'!$B$3:$B$517="Sustainable Energy Storage & Management")*(((COUNTIF($B$6:$B$10,TRUE)=0)+ISNUMBER(IFERROR(MATCH('📋 Inventaire Complet'!$B$3:$B$517,IF($B$6:$B$10,$A$6:$A$10),0),""))>0))*(((COUNTIF($F$6:$F$20,TRUE)=0)+(ISNUMBER(IFERROR(MATCH('📋 Inventaire Complet'!$F$3:$F$517,IF($F$6:$F$19,$E$6:$E$19),0),""))+($F$20*ISNUMBER(MATCH('📋 Inventaire Complet'!$F$3:$F$517,{"D4R";"CEPH";"ISTI";"COLCOM";"HTMR"},0))))>0))*(LEN('📋 Inventaire Complet'!$D$3:$D$517)>0)*(((COUNTIF($H$6:$H$10,TRUE)=0)+(($H$6*ISNUMBER(SEARCH($G$6,'📋 Inventaire Complet'!$L$3:$L$517)))+($H$7*ISNUMBER(SEARCH($G$7,'📋 Inventaire Complet'!$L$3:$L$517)))+($H$8*ISNUMBER(SEARCH($G$8,'📋 Inventaire Complet'!$L$3:$L$517)))+($H$9*ISNUMBER(SEARCH($G$9,'📋 Inventaire Complet'!$L$3:$L$517)))+($H$10*ISNUMBER(SEARCH($G$10,'📋 Inventaire Complet'!$L$3:$L$517))))>0)))} -> 0 | G63: =SUM(B63:F63) -> 10 | W63: {=SUMPRODUCT(('📋 Inventaire Complet'!$C$3:$C$517=$V63)*(((COUNTIF($B$6:$B$10,TRUE)=0)+ISNUMBER(IFERROR(MATCH('📋 Inventaire Complet'!$B$3:$B$517,IF($B$6:$B$10,$A$6:$A$10),0),""))>0))*(((COUNTIF($D$6:$D$22,TRUE)=0)+ISNUMBER(IFERROR(MATCH(LEFT('📋 Inventaire Complet'!$J$3:$J$517,4),IF($D$6:$D$22,$C$6:$C$22&""),0),""))>0))*(((COUNTIF($F$6:$F$20,TRUE)=0)+(ISNUMBER(IFERROR(MATCH('📋 Inventaire Complet'!$F$3:$F$517,IF($F$6:$F$19,$E$6:$E$19),0),""))+($F$20*ISNUMBER(MATCH('📋 Inventaire Complet'!$F$3:$F$517,{"D4R";"CEPH";"ISTI";"COLCOM";"HTMR"},0))))>0))*(LEN('📋 Inventaire Complet'!$D$3:$D$517)>0)*(((COUNTIF($H$6:$H$10,TRUE)=0)+(($H$6*ISNUMBER(SEARCH($G$6,'📋 Inventaire Complet'!$L$3:$L$517)))+($H$7*ISNUMBER(SEARCH($G$7,'📋 Inventaire Complet'!$L$3:$L$517)))+($H$8*ISNUMBER(SEARCH($G$8,'📋 Inventaire Complet'!$L$3:$L$517)))+($H$9*ISNUMBER(SEARCH($G$9,'📋 Inventaire Complet'!$L$3:$L$517)))+($H$10*ISNUMBER(SEARCH($G$10,'📋 Inventaire Complet'!$L$3:$L$517))))>0)))} -> 2 | X63: =W63+ROW()/10000 -> 2.0063 | Y63: BOUHFID Rachid RAJI Marya QAISS Abou El Kacem | Z63: {=IF(Y63="",0,SUMPRODUCT(('📋 Inventaire Complet'!$E$3:$E$517=Y63)*((COUNTIF($B$6:$B$10,TRUE)=0)+ISNUMBER(IFERROR(MATCH('📋 Inventaire Complet'!$B$3:$B$517,IF($B$6:$B$10,$A$6:$A$10),0),""))>0)*((COUNTIF($D$6:$D$22,TRUE)=0)+ISNUMBER(IFERROR(MATCH(LEFT('📋 Inventaire Complet'!$J$3:$J$517,4),IF($D$6:$D$22,$C$6:$C$22&""),0),""))>0)*((COUNTIF($F$6:$F$20,TRUE)=0)+(ISNUMBER(IFERROR(MATCH('📋 Inventaire Complet'!$F$3:$F$517,IF($F$6:$F$19,$E$6:$E$19),0),""))+($F$20*ISNUMBER(MATCH('📋 Inventaire Complet'!$F$3:$F$517,{"D4R";"CEPH";"ISTI";"COLCOM";"HTMR"},0))))>0)*((COUNTIF($H$6:$H$10,TRUE)=0)+(($H$6*ISNUMBER(SEARCH($G$6,'📋 Inventaire Complet'!$L$3:$L$517)))+($H$7*ISNUMBER(SEARCH($G$7,'📋 Inventaire Complet'!$L$3:$L$517)))+($H$8*ISNUMBER(SEARCH($G$8,'📋 Inventaire Complet'!$L$3:$L$517)))+($H$9*ISNUMBER(SEARCH($G$9,'📋 Inventaire Complet'!$L$3:$L$517)))+($H$10*ISNUMBER(SEARCH($G$10,'📋 Inventaire Complet'!$L$3:$L$517))))>0)))} -> 1 | AA63: =IF(Y63="",0,Z63+ROW()/10000) -> 1.0063
